{
  "type": "Feature",
  "properties": {
    "gn:admin1_code":"6.0",
    "gn:admin2_code":"828.0",
    "gn:asciiname":"Heihoek",
    "gn:country_code":"NL",
    "gn:dem":6,
    "gn:feature_class":"P",
    "gn:feature_code":"PPL",
    "gn:name":"Heihoek",
    "gn:population":970,
    "gn:timezone":"Europe/Amsterdam",
    "iso:country":"NL",
    "wof:name":"Heihoek",
    "wof:placetype":"locality",
    "wof:population":970
},
  "geometry": {"coordinates":[5.49849,51.75921],"type":"Point"}
}