{
  "type": "Feature",
  "properties": {
    "gn:admin1_code":"3.0",
    "gn:admin2_code":"1859",
    "gn:asciiname":"Olden Eibergen",
    "gn:country_code":"NL",
    "gn:dem":21,
    "gn:feature_class":"P",
    "gn:feature_code":"PPL",
    "gn:name":"Olden Eibergen",
    "gn:population":0,
    "gn:timezone":"Europe/Amsterdam",
    "iso:country":"NL",
    "wof:name":"Olden Eibergen",
    "wof:placetype":"locality"
},
  "geometry": {"coordinates":[6.62222,52.10083],"type":"Point"}
}