{
  "type": "Feature",
  "properties": {
    "gn:admin1_code":"4.0",
    "gn:admin2_code":"0048",
    "gn:asciiname":"Leemdobben",
    "gn:country_code":"NL",
    "gn:dem":6,
    "gn:feature_class":"P",
    "gn:feature_code":"PPL",
    "gn:name":"Leemdobben",
    "gn:population":0,
    "gn:timezone":"Europe/Amsterdam",
    "iso:country":"NL",
    "wof:name":"Leemdobben",
    "wof:placetype":"locality"
},
  "geometry": {"coordinates":[7.15417,52.9525],"type":"Point"}
}