{
  "type": "Feature",
  "properties": {
    "gn:admin1_code":"3.0",
    "gn:admin2_code":"1859",
    "gn:asciiname":"Hoonte",
    "gn:country_code":"NL",
    "gn:dem":18,
    "gn:feature_class":"P",
    "gn:feature_code":"PPL",
    "gn:name":"Hoonte",
    "gn:population":0,
    "gn:timezone":"Europe/Amsterdam",
    "iso:country":"NL",
    "wof:name":"Hoonte",
    "wof:placetype":"locality"
},
  "geometry": {"coordinates":[6.60833,52.12583],"type":"Point"}
}