{
  "type": "Feature",
  "properties": {
    "gn:admin1_code":"3.0",
    "gn:admin2_code":"1734.0",
    "gn:asciiname":"Herveld-Noord",
    "gn:country_code":"NL",
    "gn:dem":9,
    "gn:feature_class":"P",
    "gn:feature_code":"PPL",
    "gn:name":"Herveld-Noord",
    "gn:population":0,
    "gn:timezone":"Europe/Amsterdam",
    "iso:country":"NL",
    "wof:name":"Herveld-Noord",
    "wof:placetype":"locality"
},
  "geometry": {"coordinates":[5.74028,51.91083],"type":"Point"}
}