{
  "type": "Feature",
  "properties": {
    "gn:admin1_code":"6.0",
    "gn:admin2_code":"1702",
    "gn:asciiname":"Park",
    "gn:cc2":"NL",
    "gn:country_code":"NL",
    "gn:dem":15,
    "gn:feature_class":"P",
    "gn:feature_code":"PPL",
    "gn:name":"Park",
    "gn:population":0,
    "gn:timezone":"Europe/Amsterdam",
    "iso:country":"NL",
    "name:und_x_variant":[
        "De Park"
    ],
    "wof:name":"Park",
    "wof:placetype":"locality"
},
  "geometry": {"coordinates":[5.825,51.64167],"type":"Point"}
}