{
  "type": "Feature",
  "properties": {
    "gn:admin1_code":"5.0",
    "gn:admin2_code":"0983",
    "gn:asciiname":"Vilgert",
    "gn:country_code":"NL",
    "gn:dem":19,
    "gn:feature_class":"P",
    "gn:feature_code":"PPL",
    "gn:name":"Vilgert",
    "gn:population":0,
    "gn:timezone":"Europe/Amsterdam",
    "iso:country":"NL",
    "wof:name":"Vilgert",
    "wof:placetype":"locality"
},
  "geometry": {"coordinates":[6.17083,51.42],"type":"Point"}
}