{
  "type": "Feature",
  "properties": {
    "gn:admin1_code":"6.0",
    "gn:admin2_code":"1948",
    "gn:asciiname":"Hurkske",
    "gn:country_code":"NL",
    "gn:dem":12,
    "gn:feature_class":"P",
    "gn:feature_code":"PPL",
    "gn:name":"Hurkske",
    "gn:population":0,
    "gn:timezone":"Europe/Amsterdam",
    "iso:country":"NL",
    "wof:name":"Hurkske",
    "wof:placetype":"locality"
},
  "geometry": {"coordinates":[5.61944,51.58583],"type":"Point"}
}