{
  "type": "Feature",
  "properties": {
    "gn:admin1_code":"11.0",
    "gn:admin2_code":"1892",
    "gn:asciiname":"Klein Hitland",
    "gn:country_code":"NL",
    "gn:dem":-1,
    "gn:feature_class":"P",
    "gn:feature_code":"PPL",
    "gn:name":"Klein Hitland",
    "gn:population":0,
    "gn:timezone":"Europe/Amsterdam",
    "iso:country":"NL",
    "wof:name":"Klein Hitland",
    "wof:placetype":"locality"
},
  "geometry": {"coordinates":[4.64028,51.95833],"type":"Point"}
}