{
  "type": "Feature",
  "properties": {
    "gn:admin1_code":"5.0",
    "gn:admin2_code":"0951",
    "gn:asciiname":"Kruis",
    "gn:country_code":"NL",
    "gn:dem":134,
    "gn:feature_class":"P",
    "gn:feature_code":"PPL",
    "gn:name":"Kruis",
    "gn:population":0,
    "gn:timezone":"Europe/Amsterdam",
    "iso:country":"NL",
    "wof:name":"Kruis",
    "wof:placetype":"locality"
},
  "geometry": {"coordinates":[5.81735,50.90674],"type":"Point"}
}