{
  "type": "Feature",
  "properties": {
    "gn:admin1_code":"6.0",
    "gn:admin2_code":"762.0",
    "gn:asciiname":"De Voorstad",
    "gn:country_code":"NL",
    "gn:dem":30,
    "gn:feature_class":"P",
    "gn:feature_code":"PPL",
    "gn:name":"De Voorstad",
    "gn:population":0,
    "gn:timezone":"Europe/Amsterdam",
    "iso:country":"NL",
    "wof:name":"De Voorstad",
    "wof:placetype":"locality"
},
  "geometry": {"coordinates":[5.83889,51.39917],"type":"Point"}
}