{
  "type": "Feature",
  "properties": {
    "gn:admin1_code":"5.0",
    "gn:admin2_code":"1507.0",
    "gn:asciiname":"Zwaanenheike",
    "gn:country_code":"NL",
    "gn:dem":18,
    "gn:feature_class":"P",
    "gn:feature_code":"PPL",
    "gn:name":"Zwaanenheike",
    "gn:population":0,
    "gn:timezone":"Europe/Amsterdam",
    "iso:country":"NL",
    "wof:name":"Zwaanenheike",
    "wof:placetype":"locality"
},
  "geometry": {"coordinates":[6.14722,51.4625],"type":"Point"}
}