{
  "type": "Feature",
  "properties": {
    "gn:admin1_code":"5.0",
    "gn:admin2_code":"1894",
    "gn:asciiname":"Vosberg",
    "gn:country_code":"NL",
    "gn:dem":35,
    "gn:feature_class":"P",
    "gn:feature_code":"PPL",
    "gn:name":"Vosberg",
    "gn:population":0,
    "gn:timezone":"Europe/Amsterdam",
    "iso:country":"NL",
    "wof:name":"Vosberg",
    "wof:placetype":"locality"
},
  "geometry": {"coordinates":[5.97361,51.34],"type":"Point"}
}