{
  "type": "Feature",
  "properties": {
    "gn:admin1_code":"11.0",
    "gn:admin2_code":"0627",
    "gn:asciiname":"Noordeinde",
    "gn:country_code":"NL",
    "gn:dem":-3,
    "gn:feature_class":"P",
    "gn:feature_code":"PPLL",
    "gn:name":"Noordeinde",
    "gn:population":0,
    "gn:timezone":"Europe/Amsterdam",
    "iso:country":"NL",
    "name:fra_x_preferred":[
        "Noordeinde"
    ],
    "name:nld_x_preferred":[
        "Noordeinde"
    ],
    "wof:name":"Noordeinde",
    "wof:placetype":"locality"
},
  "geometry": {"coordinates":[4.63756,52.06782000000001],"type":"Point"}
}