{
  "type": "Feature",
  "properties": {
    "gn:admin1_code":"4.0",
    "gn:admin2_code":"37.0",
    "gn:asciiname":"Barlage",
    "gn:country_code":"NL",
    "gn:dem":3,
    "gn:feature_class":"P",
    "gn:feature_code":"PPL",
    "gn:name":"Barlage",
    "gn:population":0,
    "gn:timezone":"Europe/Amsterdam",
    "iso:country":"NL",
    "wof:name":"Barlage",
    "wof:placetype":"locality"
},
  "geometry": {"coordinates":[7.05556,53.0125],"type":"Point"}
}