{
  "type": "Feature",
  "properties": {
    "gn:admin1_code":"5.0",
    "gn:admin2_code":"983.0",
    "gn:asciiname":"Hasselt",
    "gn:country_code":"NL",
    "gn:dem":17,
    "gn:feature_class":"P",
    "gn:feature_code":"PPL",
    "gn:name":"Hasselt",
    "gn:population":0,
    "gn:timezone":"Europe/Amsterdam",
    "iso:country":"NL",
    "wof:name":"Hasselt",
    "wof:placetype":"locality"
},
  "geometry": {"coordinates":[6.16111,51.42667],"type":"Point"}
}