{
  "type": "Feature",
  "properties": {
    "gn:admin1_code":"7.0",
    "gn:admin2_code":"0417",
    "gn:asciiname":"Sint Janskerkhof",
    "gn:country_code":"NL",
    "gn:dem":10,
    "gn:feature_class":"P",
    "gn:feature_code":"PPL",
    "gn:name":"Sint Janskerkhof",
    "gn:population":0,
    "gn:timezone":"Europe/Amsterdam",
    "iso:country":"NL",
    "wof:name":"Sint Janskerkhof",
    "wof:placetype":"locality"
},
  "geometry": {"coordinates":[5.21667,52.25],"type":"Point"}
}