{
  "type": "Feature",
  "properties": {
    "gn:admin1_code":"2.0",
    "gn:admin2_code":"0070",
    "gn:asciiname":"Miedum",
    "gn:country_code":"NL",
    "gn:dem":-2,
    "gn:feature_class":"P",
    "gn:feature_code":"PPL",
    "gn:name":"Miedum",
    "gn:population":0,
    "gn:timezone":"Europe/Amsterdam",
    "iso:country":"NL",
    "wof:name":"Miedum",
    "wof:placetype":"locality"
},
  "geometry": {"coordinates":[5.5432,53.1716],"type":"Point"}
}