{
  "type": "Feature",
  "properties": {
    "gn:admin1_code":"10.0",
    "gn:admin2_code":"717.0",
    "gn:asciiname":"Hoogelande",
    "gn:country_code":"NL",
    "gn:dem":-1,
    "gn:feature_class":"P",
    "gn:feature_code":"PPL",
    "gn:name":"Hoogelande",
    "gn:population":0,
    "gn:timezone":"Europe/Amsterdam",
    "iso:country":"NL",
    "name:fra_x_preferred":[
        "Hoogelande"
    ],
    "name:nld_x_preferred":[
        "Hoogelande"
    ],
    "name:spa_x_preferred":[
        "Hoogelande"
    ],
    "name:zea_x_preferred":[
        "Ho\u00f4gelande"
    ],
    "wof:name":"Hoogelande",
    "wof:placetype":"locality"
},
  "geometry": {"coordinates":[3.5625,51.5075],"type":"Point"}
}