{
  "type": "Feature",
  "properties": {
    "gn:admin1_code":"6.0",
    "gn:admin2_code":"1948",
    "gn:asciiname":"Vossenberg",
    "gn:country_code":"NL",
    "gn:dem":9,
    "gn:feature_class":"P",
    "gn:feature_code":"PPL",
    "gn:name":"Vossenberg",
    "gn:population":0,
    "gn:timezone":"Europe/Amsterdam",
    "iso:country":"NL",
    "wof:name":"Vossenberg",
    "wof:placetype":"locality"
},
  "geometry": {"coordinates":[5.43201,51.63472],"type":"Point"}
}