{
  "type": "Feature",
  "properties": {
    "gn:admin1_code":"4.0",
    "gn:admin2_code":"56.0",
    "gn:asciiname":"Fransumervoorwerk",
    "gn:country_code":"NL",
    "gn:dem":1,
    "gn:feature_class":"P",
    "gn:feature_code":"PPL",
    "gn:name":"Fransumervoorwerk",
    "gn:population":0,
    "gn:timezone":"Europe/Amsterdam",
    "iso:country":"NL",
    "name:und_x_variant":[
        "Fransummervoorwerk",
        "Fransumervoorwerk"
    ],
    "wof:name":"Fransumervoorwerk",
    "wof:placetype":"locality"
},
  "geometry": {"coordinates":[6.46804,53.26896],"type":"Point"}
}