{
  "type": "Feature",
  "properties": {
    "gn:admin1_code":"4.0",
    "gn:admin2_code":"1651.0",
    "gn:asciiname":"Helwerd",
    "gn:country_code":"NL",
    "gn:dem":0,
    "gn:feature_class":"P",
    "gn:feature_code":"PPL",
    "gn:name":"Helwerd",
    "gn:population":0,
    "gn:timezone":"Europe/Amsterdam",
    "iso:country":"NL",
    "wof:name":"Helwerd",
    "wof:placetype":"locality"
},
  "geometry": {"coordinates":[6.61806,53.39083],"type":"Point"}
}