{
  "type": "Feature",
  "properties": {
    "gn:admin1_code":"6.0",
    "gn:admin2_code":"1674.0",
    "gn:asciiname":"Brembosch",
    "gn:country_code":"NL",
    "gn:dem":7,
    "gn:feature_class":"P",
    "gn:feature_code":"PPL",
    "gn:name":"Brembosch",
    "gn:population":0,
    "gn:timezone":"Europe/Amsterdam",
    "iso:country":"NL",
    "wof:name":"Brembosch",
    "wof:placetype":"locality"
},
  "geometry": {"coordinates":[4.43333,51.49583],"type":"Point"}
}