{
  "type": "Feature",
  "properties": {
    "gn:admin1_code":"6.0",
    "gn:admin2_code":"743.0",
    "gn:asciiname":"Dijk",
    "gn:country_code":"NL",
    "gn:dem":25,
    "gn:feature_class":"P",
    "gn:feature_code":"PPL",
    "gn:name":"Dijk",
    "gn:population":0,
    "gn:timezone":"Europe/Amsterdam",
    "iso:country":"NL",
    "wof:name":"Dijk",
    "wof:placetype":"locality"
},
  "geometry": {"coordinates":[5.71389,51.415],"type":"Point"}
}