{
  "type": "Feature",
  "properties": {
    "gn:admin1_code":"1.0",
    "gn:admin2_code":"1690",
    "gn:asciiname":"Nolde",
    "gn:country_code":"NL",
    "gn:dem":9,
    "gn:feature_class":"P",
    "gn:feature_code":"PPL",
    "gn:name":"Nolde",
    "gn:population":0,
    "gn:timezone":"Europe/Amsterdam",
    "iso:country":"NL",
    "wof:name":"Nolde",
    "wof:placetype":"locality"
},
  "geometry": {"coordinates":[6.42083,52.63417],"type":"Point"}
}