{
  "type": "Feature",
  "properties": {
    "gn:admin1_code":"10.0",
    "gn:admin2_code":"715.0",
    "gn:asciiname":"De Ratte",
    "gn:country_code":"NL",
    "gn:dem":6,
    "gn:feature_class":"P",
    "gn:feature_code":"PPL",
    "gn:name":"De Ratte",
    "gn:population":0,
    "gn:timezone":"Europe/Amsterdam",
    "iso:country":"NL",
    "wof:name":"De Ratte",
    "wof:placetype":"locality"
},
  "geometry": {"coordinates":[3.89028,51.23417],"type":"Point"}
}