{
  "type": "Feature",
  "properties": {
    "gn:admin1_code":"15.0",
    "gn:admin2_code":"189.0",
    "gn:asciiname":"De Kolonie",
    "gn:country_code":"NL",
    "gn:dem":12,
    "gn:feature_class":"P",
    "gn:feature_code":"PPL",
    "gn:name":"De Kolonie",
    "gn:population":0,
    "gn:timezone":"Europe/Amsterdam",
    "iso:country":"NL",
    "wof:name":"De Kolonie",
    "wof:placetype":"locality"
},
  "geometry": {"coordinates":[6.52639,52.395],"type":"Point"}
}