{
  "type": "Feature",
  "properties": {
    "gn:admin1_code":"10.0",
    "gn:admin2_code":"1676",
    "gn:asciiname":"Vianen",
    "gn:cc2":"NL",
    "gn:country_code":"NL",
    "gn:dem":1,
    "gn:feature_class":"P",
    "gn:feature_code":"PPL",
    "gn:name":"Vianen",
    "gn:population":0,
    "gn:timezone":"Europe/Amsterdam",
    "iso:country":"NL",
    "name:ara_x_preferred":[
        "\u0641\u064a\u0627\u0646\u0646"
    ],
    "name:cat_x_preferred":[
        "Vianen"
    ],
    "name:ceb_x_preferred":[
        "Gemeente Vianen"
    ],
    "name:deu_x_preferred":[
        "Vianen"
    ],
    "name:epo_x_preferred":[
        "Vianen"
    ],
    "name:eus_x_preferred":[
        "Vianen"
    ],
    "name:fas_x_preferred":[
        "\u0641\u06cc\u0627\u0646\u0646"
    ],
    "name:fra_x_preferred":[
        "Vianen"
    ],
    "name:fry_x_preferred":[
        "Fianen"
    ],
    "name:hye_x_preferred":[
        "\u054e\u056b\u0561\u0576\u0565\u0576"
    ],
    "name:ind_x_preferred":[
        "Vianen"
    ],
    "name:ita_x_preferred":[
        "Vianen"
    ],
    "name:lat_x_preferred":[
        "Vigenna"
    ],
    "name:lim_x_preferred":[
        "Vianen"
    ],
    "name:msa_x_preferred":[
        "Vianen"
    ],
    "name:nld_x_preferred":[
        "Vianen"
    ],
    "name:nor_x_preferred":[
        "Vianen"
    ],
    "name:pol_x_preferred":[
        "Vianen"
    ],
    "name:ron_x_preferred":[
        "Vianen"
    ],
    "name:rus_x_preferred":[
        "\u0412\u0438\u0430\u043d\u0435\u043d"
    ],
    "name:spa_x_preferred":[
        "Vianen"
    ],
    "name:sqi_x_preferred":[
        "Vianen"
    ],
    "name:swe_x_preferred":[
        "Vianen"
    ],
    "name:tur_x_preferred":[
        "Vianen"
    ],
    "name:und_x_variant":[
        "Viane"
    ],
    "name:vie_x_preferred":[
        "Vianen"
    ],
    "name:vol_x_preferred":[
        "Vianen"
    ],
    "name:war_x_preferred":[
        "Vianen"
    ],
    "name:zho_x_preferred":[
        "\u83f2\u4e9e\u5ae9"
    ],
    "wof:name":"Vianen",
    "wof:placetype":"locality"
},
  "geometry": {"coordinates":[4.00881,51.6178],"type":"Point"}
}