{
  "type": "Feature",
  "properties": {
    "gn:admin1_code":"10.0",
    "gn:admin2_code":"1676",
    "gn:asciiname":"Vianen",
    "gn:cc2":"NL",
    "gn:country_code":"NL",
    "gn:dem":1,
    "gn:feature_class":"P",
    "gn:feature_code":"PPL",
    "gn:name":"Vianen",
    "gn:population":0,
    "gn:timezone":"Europe/Amsterdam",
    "iso:country":"NL",
    "name:und_x_variant":[
        "Viane"
    ],
    "wof:name":"Vianen",
    "wof:placetype":"locality"
},
  "geometry": {"coordinates":[4.00881,51.6178],"type":"Point"}
}