{
  "type": "Feature",
  "properties": {
    "iso:country":"NL",
    "name:eng_x_preferred":[
        "Werkspoor"
    ],
    "name:nld_x_preferred":[
        "Werkspoor"
    ],
    "wof:name":"Werkspoor",
    "wof:placetype":"microhood"
},
  "geometry": {"coordinates":[4.92749274224355,52.37159481449984],"type":"Point"}
}