{
  "type": "Feature",
  "properties": {
    "gn:admin1_code":"6.0",
    "gn:admin2_code":"840.0",
    "gn:asciiname":"Heesterbosch",
    "gn:country_code":"NL",
    "gn:dem":5,
    "gn:feature_class":"P",
    "gn:feature_code":"PPL",
    "gn:name":"Heesterbosch",
    "gn:population":0,
    "gn:timezone":"Europe/Amsterdam",
    "iso:country":"NL",
    "wof:name":"Heesterbosch",
    "wof:placetype":"locality"
},
  "geometry": {"coordinates":[4.51667,51.56667],"type":"Point"}
}