{
  "type": "Feature",
  "properties": {
    "gn:admin1_code":"6.0",
    "gn:admin2_code":"1724.0",
    "gn:asciiname":"De Aa",
    "gn:country_code":"NL",
    "gn:dem":36,
    "gn:feature_class":"P",
    "gn:feature_code":"PPL",
    "gn:name":"De Aa",
    "gn:population":0,
    "gn:timezone":"Europe/Amsterdam",
    "iso:country":"NL",
    "wof:name":"De Aa",
    "wof:placetype":"locality"
},
  "geometry": {"coordinates":[5.35,51.28333],"type":"Point"}
}