{
  "type": "Feature",
  "properties": {
    "gn:admin1_code":"15.0",
    "gn:admin2_code":"1708",
    "gn:asciiname":"Muggenbeet",
    "gn:cc2":"NL",
    "gn:country_code":"NL",
    "gn:dem":1,
    "gn:feature_class":"P",
    "gn:feature_code":"PPL",
    "gn:name":"Muggenbeet",
    "gn:population":0,
    "gn:timezone":"Europe/Amsterdam",
    "iso:country":"NL",
    "name:und_x_variant":[
        "Muggebeet"
    ],
    "wof:name":"Muggenbeet",
    "wof:placetype":"locality"
},
  "geometry": {"coordinates":[5.99306,52.74166999999999],"type":"Point"}
}