{
  "type": "Feature",
  "properties": {
    "gn:admin1_code":"15.0",
    "gn:admin2_code":"148.0",
    "gn:asciiname":"Den Hulst",
    "gn:cc2":"NL",
    "gn:country_code":"NL",
    "gn:dem":3,
    "gn:feature_class":"P",
    "gn:feature_code":"PPL",
    "gn:name":"Den Hulst",
    "gn:population":0,
    "gn:timezone":"Europe/Amsterdam",
    "iso:country":"NL",
    "name:und_x_variant":[
        "Hulst",
        "De Hulst"
    ],
    "wof:name":"Den Hulst",
    "wof:placetype":"locality"
},
  "geometry": {"coordinates":[6.2875,52.5925],"type":"Point"}
}