{
  "type": "Feature",
  "properties": {
    "gn:admin1_code":"3.0",
    "gn:admin2_code":"232.0",
    "gn:asciiname":"Hegge",
    "gn:country_code":"NL",
    "gn:dem":13,
    "gn:feature_class":"P",
    "gn:feature_code":"PPL",
    "gn:name":"Hegge",
    "gn:population":0,
    "gn:timezone":"Europe/Amsterdam",
    "iso:country":"NL",
    "wof:name":"Hegge",
    "wof:placetype":"locality"
},
  "geometry": {"coordinates":[5.97083,52.29833],"type":"Point"}
}