{
  "type": "Feature",
  "properties": {
    "gn:admin1_code":"5.0",
    "gn:admin2_code":"0893",
    "gn:asciiname":"Knikkerdorp",
    "gn:country_code":"NL",
    "gn:dem":19,
    "gn:feature_class":"P",
    "gn:feature_code":"PPL",
    "gn:name":"Knikkerdorp",
    "gn:population":0,
    "gn:timezone":"Europe/Amsterdam",
    "iso:country":"NL",
    "wof:name":"Knikkerdorp",
    "wof:placetype":"locality"
},
  "geometry": {"coordinates":[6.10833,51.55333],"type":"Point"}
}