{
  "type": "Feature",
  "properties": {
    "gn:admin1_code":"9.0",
    "gn:admin2_code":"1904.0",
    "gn:asciiname":"Gieltjesdorp",
    "gn:country_code":"NL",
    "gn:dem":-2,
    "gn:feature_class":"P",
    "gn:feature_code":"PPL",
    "gn:name":"Gieltjesdorp",
    "gn:population":0,
    "gn:timezone":"Europe/Amsterdam",
    "iso:country":"NL",
    "wof:name":"Gieltjesdorp",
    "wof:placetype":"locality"
},
  "geometry": {"coordinates":[4.98056,52.13917],"type":"Point"}
}