{
  "type": "Feature",
  "properties": {
    "gn:admin1_code":"2.0",
    "gn:admin2_code":"0080",
    "gn:asciiname":"Suorein",
    "gn:country_code":"NL",
    "gn:dem":-2,
    "gn:feature_class":"P",
    "gn:feature_code":"PPL",
    "gn:name":"Suorein",
    "gn:population":0,
    "gn:timezone":"Europe/Amsterdam",
    "iso:country":"NL",
    "name:fry_x_preferred":[
        "Suorein"
    ],
    "name:nld_x_preferred":[
        "Zuiderend"
    ],
    "wof:name":"Suorein",
    "wof:placetype":"locality"
},
  "geometry": {"coordinates":[5.81503,53.08343000000001],"type":"Point"}
}