{
  "type": "Feature",
  "properties": {
    "gn:admin1_code":"15.0",
    "gn:admin2_code":"160.0",
    "gn:asciiname":"Groot-Oever",
    "gn:cc2":"NL",
    "gn:country_code":"NL",
    "gn:dem":4,
    "gn:feature_class":"P",
    "gn:feature_code":"PPL",
    "gn:name":"Groot-Oever",
    "gn:population":0,
    "gn:timezone":"Europe/Amsterdam",
    "iso:country":"NL",
    "name:und_x_variant":[
        "Groote Oever"
    ],
    "wof:name":"Groot-Oever",
    "wof:placetype":"locality"
},
  "geometry": {"coordinates":[6.33889,52.65],"type":"Point"}
}