{
  "type": "Feature",
  "properties": {
    "iso:country":"NL",
    "name:deu_x_preferred":[
        "Floradorp"
    ],
    "name:eng_x_preferred":[
        "Floradorp"
    ],
    "name:fra_x_preferred":[
        "Floradorp"
    ],
    "name:nld_x_preferred":[
        "Floradorp"
    ],
    "wof:name":"Floradorp",
    "wof:placetype":"microhood"
},
  "geometry": {"coordinates":[4.91489890344666,52.39881798016619],"type":"Point"}
}