{
  "type": "Feature",
  "properties": {
    "gn:admin1_code":"4.0",
    "gn:admin2_code":"0018",
    "gn:asciiname":"Kiel",
    "gn:country_code":"NL",
    "gn:dem":0,
    "gn:feature_class":"P",
    "gn:feature_code":"PPL",
    "gn:name":"Kiel",
    "gn:population":0,
    "gn:timezone":"Europe/Amsterdam",
    "iso:country":"NL",
    "wof:name":"Kiel",
    "wof:placetype":"locality"
},
  "geometry": {"coordinates":[6.76667,53.13333000000001],"type":"Point"}
}