{
  "type": "Feature",
  "properties": {
    "gn:admin1_code":"6.0",
    "gn:admin2_code":"1652.0",
    "gn:asciiname":"Rootvlaas",
    "gn:country_code":"NL",
    "gn:dem":20,
    "gn:feature_class":"P",
    "gn:feature_code":"PPL",
    "gn:name":"Rootvlaas",
    "gn:population":0,
    "gn:timezone":"Europe/Amsterdam",
    "iso:country":"NL",
    "wof:name":"Rootvlaas",
    "wof:placetype":"locality"
},
  "geometry": {"coordinates":[5.72639,51.4975],"type":"Point"}
}