{
  "type": "Feature",
  "properties": {
    "gn:admin1_code":"15.0",
    "gn:admin2_code":"189.0",
    "gn:asciiname":"Het Loo",
    "gn:cc2":"NL",
    "gn:country_code":"NL",
    "gn:dem":19,
    "gn:feature_class":"P",
    "gn:feature_code":"PPL",
    "gn:name":"Het Loo",
    "gn:population":0,
    "gn:timezone":"Europe/Amsterdam",
    "iso:country":"NL",
    "name:und_x_variant":[
        "'t Loo",
        "Loo"
    ],
    "wof:name":"Het Loo",
    "wof:placetype":"locality"
},
  "geometry": {"coordinates":[6.575,52.36917],"type":"Point"}
}