{
  "type": "Feature",
  "properties": {
    "gn:admin1_code":"9.0",
    "gn:admin2_code":"0736",
    "gn:asciiname":"Vinkenkade",
    "gn:country_code":"NL",
    "gn:dem":-3,
    "gn:feature_class":"P",
    "gn:feature_code":"PPL",
    "gn:name":"Vinkekade",
    "gn:population":0,
    "gn:timezone":"Europe/Amsterdam",
    "iso:country":"NL",
    "name:ceb_x_preferred":[
        "Vinkekade"
    ],
    "name:nld_x_preferred":[
        "Vinkenkade"
    ],
    "wof:name":"Vinkenkade",
    "wof:placetype":"locality"
},
  "geometry": {"coordinates":[4.97083,52.24167],"type":"Point"}
}