{
  "type": "Feature",
  "properties": {
    "gn:admin1_code":"5.0",
    "gn:admin2_code":"0984",
    "gn:asciiname":"Weverslo",
    "gn:cc2":"NL",
    "gn:country_code":"NL",
    "gn:dem":25,
    "gn:feature_class":"P",
    "gn:feature_code":"PPL",
    "gn:name":"Weverslo",
    "gn:population":0,
    "gn:timezone":"Europe/Amsterdam",
    "iso:country":"NL",
    "name:und_x_variant":[
        "Weversloo"
    ],
    "wof:name":"Weverslo",
    "wof:placetype":"locality"
},
  "geometry": {"coordinates":[5.92917,51.5125],"type":"Point"}
}