{
  "type": "Feature",
  "properties": {
    "gn:admin1_code":"4.0",
    "gn:admin2_code":"0053",
    "gn:asciiname":"Klein Wetsinge",
    "gn:country_code":"NL",
    "gn:dem":1,
    "gn:feature_class":"P",
    "gn:feature_code":"PPL",
    "gn:name":"Klein Wetsinge",
    "gn:population":0,
    "gn:timezone":"Europe/Amsterdam",
    "iso:country":"NL",
    "wof:name":"Klein Wetsinge",
    "wof:placetype":"locality"
},
  "geometry": {"coordinates":[6.53194,53.30083000000001],"type":"Point"}
}