{
  "type": "Feature",
  "properties": {
    "gn:admin1_code":"6.0",
    "gn:admin2_code":"0743",
    "gn:asciiname":"Voordeldonk",
    "gn:country_code":"NL",
    "gn:dem":26,
    "gn:feature_class":"P",
    "gn:feature_code":"PPL",
    "gn:name":"Voordeldonk",
    "gn:population":0,
    "gn:timezone":"Europe/Amsterdam",
    "iso:country":"NL",
    "wof:name":"Voordeldonk",
    "wof:placetype":"locality"
},
  "geometry": {"coordinates":[5.775,51.4025],"type":"Point"}
}