{
  "type": "Feature",
  "properties": {
    "gn:admin1_code":"6.0",
    "gn:admin2_code":"0840",
    "gn:asciiname":"Langeschouw",
    "gn:country_code":"NL",
    "gn:dem":19,
    "gn:feature_class":"P",
    "gn:feature_code":"PPL",
    "gn:name":"Langeschouw",
    "gn:population":0,
    "gn:timezone":"Europe/Amsterdam",
    "iso:country":"NL",
    "wof:name":"Langeschouw",
    "wof:placetype":"locality"
},
  "geometry": {"coordinates":[4.54028,51.4825],"type":"Point"}
}