{
  "type": "Feature",
  "properties": {
    "gn:admin1_code":"5.0",
    "gn:admin2_code":"0984",
    "gn:asciiname":"Steegsbroek",
    "gn:country_code":"NL",
    "gn:dem":29,
    "gn:feature_class":"P",
    "gn:feature_code":"PPL",
    "gn:name":"Steegsbroek",
    "gn:population":0,
    "gn:timezone":"Europe/Amsterdam",
    "iso:country":"NL",
    "wof:name":"Steegsbroek",
    "wof:placetype":"locality"
},
  "geometry": {"coordinates":[5.95,51.48333],"type":"Point"}
}