{
  "type": "Feature",
  "properties": {
    "gn:admin1_code":"10.0",
    "gn:admin2_code":"1676.0",
    "gn:asciiname":"Dijkhuisjes",
    "gn:country_code":"NL",
    "gn:dem":-1,
    "gn:feature_class":"P",
    "gn:feature_code":"PPL",
    "gn:name":"Dijkhuisjes",
    "gn:population":0,
    "gn:timezone":"Europe/Amsterdam",
    "iso:country":"NL",
    "wof:name":"Dijkhuisjes",
    "wof:placetype":"locality"
},
  "geometry": {"coordinates":[3.94583,51.725],"type":"Point"}
}