{
  "type": "Feature",
  "properties": {
    "gn:admin1_code":"15.0",
    "gn:admin2_code":"148.0",
    "gn:asciiname":"De Meele",
    "gn:country_code":"NL",
    "gn:dem":4,
    "gn:feature_class":"P",
    "gn:feature_code":"PPL",
    "gn:name":"De Meele",
    "gn:population":0,
    "gn:timezone":"Europe/Amsterdam",
    "iso:country":"NL",
    "wof:name":"De Meele",
    "wof:placetype":"locality"
},
  "geometry": {"coordinates":[6.25139,52.58667],"type":"Point"}
}