{
  "type": "Feature",
  "properties": {
    "gn:admin1_code":"6.0",
    "gn:admin2_code":"1948",
    "gn:asciiname":"Houterd",
    "gn:country_code":"NL",
    "gn:dem":8,
    "gn:feature_class":"P",
    "gn:feature_code":"PPL",
    "gn:name":"Houterd",
    "gn:population":0,
    "gn:timezone":"Europe/Amsterdam",
    "iso:country":"NL",
    "wof:name":"Houterd",
    "wof:placetype":"locality"
},
  "geometry": {"coordinates":[5.44028,51.6425],"type":"Point"}
}