{
  "type": "Feature",
  "properties": {
    "gn:admin1_code":"1.0",
    "gn:admin2_code":"0118",
    "gn:asciiname":"Zuideropgaande",
    "gn:country_code":"NL",
    "gn:dem":22,
    "gn:feature_class":"P",
    "gn:feature_code":"PPL",
    "gn:name":"Zuideropgaande",
    "gn:population":0,
    "gn:timezone":"Europe/Amsterdam",
    "iso:country":"NL",
    "wof:name":"Zuideropgaande",
    "wof:placetype":"locality"
},
  "geometry": {"coordinates":[6.55278,52.6875],"type":"Point"}
}