{
  "type": "Feature",
  "properties": {
    "gn:admin1_code":"6.0",
    "gn:admin2_code":"848.0",
    "gn:asciiname":"Eind",
    "gn:country_code":"NL",
    "gn:dem":15,
    "gn:feature_class":"P",
    "gn:feature_code":"PPLL",
    "gn:name":"Eind",
    "gn:population":0,
    "gn:timezone":"Europe/Amsterdam",
    "iso:country":"NL",
    "wof:name":"Eind",
    "wof:placetype":"locality"
},
  "geometry": {"coordinates":[5.52361,51.52083],"type":"Point"}
}