{
  "type": "Feature",
  "properties": {
    "gn:admin1_code":"5.0",
    "gn:admin2_code":"1894",
    "gn:asciiname":"'t Heeske",
    "gn:country_code":"NL",
    "gn:dem":31,
    "gn:feature_class":"P",
    "gn:feature_code":"PPL",
    "gn:name":"t Heeske",
    "gn:population":0,
    "gn:timezone":"Europe/Amsterdam",
    "iso:country":"NL",
    "wof:name":"'t Heeske",
    "wof:placetype":"locality"
},
  "geometry": {"coordinates":[6.02917,51.35083],"type":"Point"}
}