{
  "type": "Feature",
  "properties": {
    "gn:admin1_code":"2.0",
    "gn:admin2_code":"0086",
    "gn:asciiname":"Klidse",
    "gn:cc2":"NL",
    "gn:country_code":"NL",
    "gn:dem":-3,
    "gn:feature_class":"P",
    "gn:feature_code":"PPLL",
    "gn:name":"Klidse",
    "gn:population":0,
    "gn:timezone":"Europe/Amsterdam",
    "iso:country":"NL",
    "name:und_x_variant":[
        "Kliesse",
        "Kliese",
        "Klidze"
    ],
    "wof:name":"Klidse",
    "wof:placetype":"locality"
},
  "geometry": {"coordinates":[6.00399,53.00949],"type":"Point"}
}