{
  "type": "Feature",
  "properties": {
    "gn:admin1_code":"4.0",
    "gn:admin2_code":"24.0",
    "gn:asciiname":"Eenumerhoogte",
    "gn:country_code":"NL",
    "gn:dem":0,
    "gn:feature_class":"P",
    "gn:feature_code":"PPL",
    "gn:name":"Eenumerhoogte",
    "gn:population":0,
    "gn:timezone":"Europe/Amsterdam",
    "iso:country":"NL",
    "wof:name":"Eenumerhoogte",
    "wof:placetype":"locality"
},
  "geometry": {"coordinates":[6.7843,53.34199],"type":"Point"}
}