{
  "type": "Feature",
  "properties": {
    "gn:admin1_code":"2.0",
    "gn:admin2_code":"0093",
    "gn:asciiname":"Kinnum",
    "gn:country_code":"NL",
    "gn:dem":2,
    "gn:feature_class":"P",
    "gn:feature_code":"PPL",
    "gn:name":"Kinnum",
    "gn:population":0,
    "gn:timezone":"Europe/Amsterdam",
    "iso:country":"NL",
    "wof:name":"Kinnum",
    "wof:placetype":"locality"
},
  "geometry": {"coordinates":[5.2755,53.37441999999999],"type":"Point"}
}