{
  "type": "Feature",
  "properties": {
    "gn:admin1_code":"6.0",
    "gn:admin2_code":"0784",
    "gn:asciiname":"Verhoven",
    "gn:country_code":"NL",
    "gn:dem":15,
    "gn:feature_class":"P",
    "gn:feature_code":"PPL",
    "gn:name":"Verhoven",
    "gn:population":0,
    "gn:timezone":"Europe/Amsterdam",
    "iso:country":"NL",
    "wof:name":"Verhoven",
    "wof:placetype":"locality"
},
  "geometry": {"coordinates":[4.92361,51.55],"type":"Point"}
}