{
  "type": "Feature",
  "properties": {
    "gn:admin1_code":"6.0",
    "gn:admin2_code":"1674",
    "gn:asciiname":"Rietgoor",
    "gn:country_code":"NL",
    "gn:dem":8,
    "gn:feature_class":"P",
    "gn:feature_code":"PPL",
    "gn:name":"Rietgoor",
    "gn:population":0,
    "gn:timezone":"Europe/Amsterdam",
    "iso:country":"NL",
    "wof:name":"Rietgoor",
    "wof:placetype":"locality"
},
  "geometry": {"coordinates":[4.43931,51.50731],"type":"Point"}
}