{
  "type": "Feature",
  "properties": {
    "gn:admin1_code":"6.0",
    "gn:admin2_code":"1658",
    "gn:asciiname":"Kruis",
    "gn:country_code":"NL",
    "gn:dem":24,
    "gn:feature_class":"P",
    "gn:feature_code":"PPL",
    "gn:name":"Kruis",
    "gn:population":0,
    "gn:timezone":"Europe/Amsterdam",
    "iso:country":"NL",
    "wof:name":"Kruis",
    "wof:placetype":"locality"
},
  "geometry": {"coordinates":[5.56698,51.37767],"type":"Point"}
}