{
  "type": "Feature",
  "properties": {
    "gn:admin1_code":"3.0",
    "gn:admin2_code":"1859.0",
    "gn:asciiname":"Bruil",
    "gn:cc2":"NL",
    "gn:country_code":"NL",
    "gn:dem":17,
    "gn:feature_class":"P",
    "gn:feature_code":"PPL",
    "gn:name":"De Bruil",
    "gn:population":0,
    "gn:timezone":"Europe/Amsterdam",
    "iso:country":"NL",
    "name:und_x_variant":[
        "Den Bruil",
        "De Bruil"
    ],
    "wof:name":"Bruil",
    "wof:placetype":"locality"
},
  "geometry": {"coordinates":[6.45417,52.06833],"type":"Point"}
}