{
  "type": "Feature",
  "properties": {
    "gn:admin1_code":"5.0",
    "gn:admin2_code":"1729.0",
    "gn:asciiname":"Gracht Burggraaf",
    "gn:country_code":"NL",
    "gn:dem":104,
    "gn:feature_class":"P",
    "gn:feature_code":"PPL",
    "gn:name":"Gracht Burggraaf",
    "gn:population":0,
    "gn:timezone":"Europe/Amsterdam",
    "iso:country":"NL",
    "wof:name":"Gracht Burggraaf",
    "wof:placetype":"locality"
},
  "geometry": {"coordinates":[5.89028,50.82083],"type":"Point"}
}