{
  "type": "Feature",
  "properties": {
    "gn:admin1_code":"5.0",
    "gn:admin2_code":"907.0",
    "gn:asciiname":"Aaldonk",
    "gn:country_code":"NL",
    "gn:dem":13,
    "gn:feature_class":"P",
    "gn:feature_code":"PPL",
    "gn:name":"Aaldonk",
    "gn:population":0,
    "gn:timezone":"Europe/Amsterdam",
    "iso:country":"NL",
    "name:fas_x_preferred":[
        "\u0622\u0644\u062f\u0627\u0646\u06a9"
    ],
    "name:nld_x_preferred":[
        "Aaldonk"
    ],
    "name:urd_x_preferred":[
        "\u0622\u0644\u0688\u0648\u0646\u06a9"
    ],
    "wof:name":"Aaldonk",
    "wof:placetype":"locality"
},
  "geometry": {"coordinates":[5.99444,51.7125],"type":"Point"}
}