{
  "type": "Feature",
  "properties": {
    "gn:admin1_code":"5.0",
    "gn:admin2_code":"1640.0",
    "gn:asciiname":"Gendijk",
    "gn:country_code":"NL",
    "gn:dem":21,
    "gn:feature_class":"P",
    "gn:feature_code":"PPL",
    "gn:name":"Gendijk",
    "gn:population":0,
    "gn:timezone":"Europe/Amsterdam",
    "iso:country":"NL",
    "wof:name":"Gendijk",
    "wof:placetype":"locality"
},
  "geometry": {"coordinates":[5.98333,51.25333],"type":"Point"}
}