{
  "type": "Feature",
  "properties": {
    "gn:admin1_code":"6.0",
    "gn:admin2_code":"1719",
    "gn:asciiname":"Oud-Drimmelen",
    "gn:country_code":"NL",
    "gn:dem":0,
    "gn:feature_class":"P",
    "gn:feature_code":"PPL",
    "gn:name":"Oud-Drimmelen",
    "gn:population":0,
    "gn:timezone":"Europe/Amsterdam",
    "iso:country":"NL",
    "wof:name":"Oud-Drimmelen",
    "wof:placetype":"locality"
},
  "geometry": {"coordinates":[4.77639,51.69667000000001],"type":"Point"}
}