{
  "type": "Feature",
  "properties": {
    "gn:admin1_code":"5.0",
    "gn:admin2_code":"0946",
    "gn:asciiname":"Horick",
    "gn:country_code":"NL",
    "gn:dem":32,
    "gn:feature_class":"P",
    "gn:feature_code":"PPL",
    "gn:name":"Horick",
    "gn:population":0,
    "gn:timezone":"Europe/Amsterdam",
    "iso:country":"NL",
    "wof:name":"Horick",
    "wof:placetype":"locality"
},
  "geometry": {"coordinates":[5.77778,51.30583],"type":"Point"}
}