{
  "type": "Feature",
  "properties": {
    "gn:admin1_code":"6.0",
    "gn:admin2_code":"766.0",
    "gn:asciiname":"Groenstraat",
    "gn:country_code":"NL",
    "gn:dem":4,
    "gn:feature_class":"P",
    "gn:feature_code":"PPL",
    "gn:name":"Groenstraat",
    "gn:population":0,
    "gn:timezone":"Europe/Amsterdam",
    "iso:country":"NL",
    "wof:name":"Groenstraat",
    "wof:placetype":"locality"
},
  "geometry": {"coordinates":[4.91667,51.63333],"type":"Point"}
}