{
  "type": "Feature",
  "properties": {
    "gn:admin1_code":"6.0",
    "gn:admin2_code":"777.0",
    "gn:asciiname":"Grauwe Polder",
    "gn:country_code":"NL",
    "gn:dem":9,
    "gn:feature_class":"P",
    "gn:feature_code":"PPL",
    "gn:name":"Grauwe Polder",
    "gn:population":0,
    "gn:timezone":"Europe/Amsterdam",
    "iso:country":"NL",
    "wof:name":"Grauwe Polder",
    "wof:placetype":"locality"
},
  "geometry": {"coordinates":[4.63301,51.55215],"type":"Point"}
}