{
  "type": "Feature",
  "properties": {
    "gn:admin1_code":"2.0",
    "gn:admin2_code":"0079",
    "gn:asciiname":"Kettingwier",
    "gn:country_code":"NL",
    "gn:dem":1,
    "gn:feature_class":"P",
    "gn:feature_code":"PPL",
    "gn:name":"Kettingwier",
    "gn:population":0,
    "gn:timezone":"Europe/Amsterdam",
    "iso:country":"NL",
    "wof:name":"Kettingwier",
    "wof:placetype":"locality"
},
  "geometry": {"coordinates":[6.07347,53.29857],"type":"Point"}
}