{
  "type": "Feature",
  "properties": {
    "gn:admin1_code":"6.0",
    "gn:admin2_code":"1659.0",
    "gn:asciiname":"Het Hool",
    "gn:country_code":"NL",
    "gn:dem":16,
    "gn:feature_class":"P",
    "gn:feature_code":"PPL",
    "gn:name":"Het Hool",
    "gn:population":0,
    "gn:timezone":"Europe/Amsterdam",
    "iso:country":"NL",
    "wof:name":"Het Hool",
    "wof:placetype":"locality"
},
  "geometry": {"coordinates":[5.60972,51.51917],"type":"Point"}
}