{
  "type": "Feature",
  "properties": {
    "gn:admin1_code":"4.0",
    "gn:admin2_code":"0010",
    "gn:asciiname":"Kleine Wierum",
    "gn:country_code":"NL",
    "gn:dem":1,
    "gn:feature_class":"P",
    "gn:feature_code":"PPL",
    "gn:name":"Kleine Wierum",
    "gn:population":0,
    "gn:timezone":"Europe/Amsterdam",
    "iso:country":"NL",
    "wof:name":"Kleine Wierum",
    "wof:placetype":"locality"
},
  "geometry": {"coordinates":[6.88852,53.36664],"type":"Point"}
}