{
  "type": "Feature",
  "properties": {
    "gn:admin1_code":"2.0",
    "gn:admin2_code":"1940.0",
    "gn:asciiname":"De Rijlst",
    "gn:country_code":"NL",
    "gn:dem":3,
    "gn:feature_class":"P",
    "gn:feature_code":"PPL",
    "gn:name":"De Rijlst",
    "gn:population":0,
    "gn:timezone":"Europe/Amsterdam",
    "iso:country":"NL",
    "wof:name":"De Rijlst",
    "wof:placetype":"locality"
},
  "geometry": {"coordinates":[5.75384,52.92936],"type":"Point"}
}