{
  "type": "Feature",
  "properties": {
    "gn:admin1_code":"3.0",
    "gn:admin2_code":"0203",
    "gn:asciiname":"Kallenbroek",
    "gn:country_code":"NL",
    "gn:dem":7,
    "gn:feature_class":"P",
    "gn:feature_code":"PPL",
    "gn:name":"Kallenbroek",
    "gn:population":0,
    "gn:timezone":"Europe/Amsterdam",
    "iso:country":"NL",
    "wof:name":"Kallenbroek",
    "wof:placetype":"locality"
},
  "geometry": {"coordinates":[5.53333,52.15083],"type":"Point"}
}