{
  "type": "Feature",
  "properties": {
    "gn:admin1_code":"6.0",
    "gn:admin2_code":"1709",
    "gn:asciiname":"Zevenbergen",
    "gn:country_code":"NL",
    "gn:dem":5,
    "gn:feature_class":"P",
    "gn:feature_code":"PPL",
    "gn:name":"Zevenbergen",
    "gn:population":0,
    "gn:timezone":"Europe/Amsterdam",
    "iso:country":"NL",
    "name:jpn_x_preferred":[
        "\u30bc\u30fc\u30d5\u30a7\u30f3\u30d9\u30eb\u30b2\u30f3"
    ],
    "name:ukr_x_preferred":[
        "\u0417\u0435\u0432\u0435\u043d\u0431\u0435\u0440\u0433\u0435\u043d"
    ],
    "name:zho_x_preferred":[
        "\u6fa4\u82ac\u8c9d\u4ea8"
    ],
    "wof:name":"Zevenbergen",
    "wof:placetype":"locality"
},
  "geometry": {"coordinates":[4.60417,51.645],"type":"Point"}
}