{
  "type": "Feature",
  "properties": {
    "gn:admin1_code":"7.0",
    "gn:admin2_code":"0852",
    "gn:asciiname":"Rozewerf",
    "gn:country_code":"NL",
    "gn:dem":1,
    "gn:feature_class":"P",
    "gn:feature_code":"PPL",
    "gn:name":"Rozewerf",
    "gn:population":0,
    "gn:timezone":"Europe/Amsterdam",
    "iso:country":"NL",
    "wof:name":"Rozewerf",
    "wof:placetype":"locality"
},
  "geometry": {"coordinates":[5.11389,52.455],"type":"Point"}
}