{
  "type": "Feature",
  "properties": {
    "gn:admin1_code":"2.0",
    "gn:admin2_code":"90.0",
    "gn:asciiname":"De Galhoek",
    "gn:country_code":"NL",
    "gn:dem":0,
    "gn:feature_class":"P",
    "gn:feature_code":"PPL",
    "gn:name":"De Galhoek",
    "gn:population":0,
    "gn:timezone":"Europe/Amsterdam",
    "iso:country":"NL",
    "name:fry_x_preferred":[
        "Galhoeke"
    ],
    "name:nld_x_preferred":[
        "De Galhoek"
    ],
    "wof:name":"De Galhoek",
    "wof:placetype":"locality"
},
  "geometry": {"coordinates":[6.05,53.08333],"type":"Point"}
}