{
  "type": "Feature",
  "properties": {
    "gn:admin1_code":"4.0",
    "gn:admin2_code":"0765",
    "gn:asciiname":"Wildeplaats",
    "gn:country_code":"NL",
    "gn:dem":1,
    "gn:feature_class":"P",
    "gn:feature_code":"PPL",
    "gn:name":"Wildeplaats",
    "gn:population":0,
    "gn:timezone":"Europe/Amsterdam",
    "iso:country":"NL",
    "wof:name":"Wildeplaats",
    "wof:placetype":"locality"
},
  "geometry": {"coordinates":[6.93472,53.02833],"type":"Point"}
}