{
  "type": "Feature",
  "properties": {
    "gn:admin1_code":"3.0",
    "gn:admin2_code":"1945.0",
    "gn:asciiname":"Colonjes",
    "gn:cc2":"NL",
    "gn:country_code":"NL",
    "gn:dem":40,
    "gn:feature_class":"P",
    "gn:feature_code":"PPLL",
    "gn:name":"Colonjes",
    "gn:population":0,
    "gn:timezone":"Europe/Amsterdam",
    "iso:country":"NL",
    "name:und_x_variant":[
        "Colonies"
    ],
    "wof:name":"Colonjes",
    "wof:placetype":"locality"
},
  "geometry": {"coordinates":[5.93333,51.76667],"type":"Point"}
}