{
  "type": "Feature",
  "properties": {
    "gn:admin1_code":"15.0",
    "gn:admin2_code":"1700",
    "gn:asciiname":"Zwarte Gat",
    "gn:country_code":"NL",
    "gn:dem":9,
    "gn:feature_class":"P",
    "gn:feature_code":"PPLL",
    "gn:name":"Zwarte Gat",
    "gn:population":0,
    "gn:timezone":"Europe/Amsterdam",
    "iso:country":"NL",
    "wof:name":"Zwarte Gat",
    "wof:placetype":"locality"
},
  "geometry": {"coordinates":[6.56667,52.46666999999999],"type":"Point"}
}