{
  "type": "Feature",
  "properties": {
    "gn:admin1_code":"9.0",
    "gn:admin2_code":"1581.0",
    "gn:asciiname":"Haspel",
    "gn:country_code":"NL",
    "gn:dem":8,
    "gn:feature_class":"P",
    "gn:feature_code":"PPL",
    "gn:name":"Haspel",
    "gn:population":0,
    "gn:timezone":"Europe/Amsterdam",
    "iso:country":"NL",
    "wof:name":"Haspel",
    "wof:placetype":"locality"
},
  "geometry": {"coordinates":[5.51944,52.03167],"type":"Point"}
}