{
  "type": "Feature",
  "properties": {
    "gn:admin1_code":"6.0",
    "gn:admin2_code":"1771.0",
    "gn:asciiname":"Goor",
    "gn:country_code":"NL",
    "gn:dem":19,
    "gn:feature_class":"P",
    "gn:feature_code":"PPL",
    "gn:name":"Goor",
    "gn:population":0,
    "gn:timezone":"Europe/Amsterdam",
    "iso:country":"NL",
    "wof:name":"Goor",
    "wof:placetype":"locality"
},
  "geometry": {"coordinates":[5.64028,51.455],"type":"Point"}
}