{
  "type": "Feature",
  "properties": {
    "gn:admin1_code":"6.0",
    "gn:admin2_code":"1771.0",
    "gn:asciiname":"Goor",
    "gn:country_code":"NL",
    "gn:dem":19,
    "gn:feature_class":"P",
    "gn:feature_code":"PPL",
    "gn:name":"Goor",
    "gn:population":0,
    "gn:timezone":"Europe/Amsterdam",
    "iso:country":"NL",
    "name:ceb_x_preferred":[
        "Goor"
    ],
    "name:fas_x_preferred":[
        "\u062e\u0648\u0631"
    ],
    "name:fra_x_preferred":[
        "Goor"
    ],
    "name:ita_x_preferred":[
        "Goor"
    ],
    "name:lat_x_preferred":[
        "Gora"
    ],
    "name:nld_x_preferred":[
        "Goor"
    ],
    "name:rus_x_preferred":[
        "\u0413\u043e\u043e\u0440"
    ],
    "wof:name":"Goor",
    "wof:placetype":"locality"
},
  "geometry": {"coordinates":[5.64028,51.455],"type":"Point"}
}