{
  "type": "Feature",
  "properties": {
    "gn:admin1_code":"3.0",
    "gn:admin2_code":"1876",
    "gn:asciiname":"Linde",
    "gn:country_code":"NL",
    "gn:dem":15,
    "gn:feature_class":"P",
    "gn:feature_code":"PPL",
    "gn:name":"Linde",
    "gn:population":0,
    "gn:timezone":"Europe/Amsterdam",
    "iso:country":"NL",
    "name:als_x_preferred":[
        "Linde"
    ],
    "name:ceb_x_preferred":[
        "Linde"
    ],
    "name:ces_x_preferred":[
        "Linde"
    ],
    "name:dan_x_preferred":[
        "Linde"
    ],
    "name:deu_x_preferred":[
        "Linde"
    ],
    "name:epo_x_preferred":[
        "Linde"
    ],
    "name:fra_x_preferred":[
        "Linde"
    ],
    "name:ita_x_preferred":[
        "Linde"
    ],
    "name:nld_x_preferred":[
        "Linde"
    ],
    "name:pol_x_preferred":[
        "Linde"
    ],
    "name:rus_x_preferred":[
        "\u041b\u0438\u043d\u0434\u0435"
    ],
    "name:spa_x_preferred":[
        "Linde"
    ],
    "name:swe_x_preferred":[
        "Linde"
    ],
    "name:ukr_x_preferred":[
        "\u041b\u0456\u043d\u0434\u0435"
    ],
    "name:vls_x_preferred":[
        "Linde"
    ],
    "wof:name":"Linde",
    "wof:placetype":"locality"
},
  "geometry": {"coordinates":[6.35278,52.08083],"type":"Point"}
}