{
  "type": "Feature",
  "properties": {
    "gn:admin1_code":"6.0",
    "gn:admin2_code":"861.0",
    "gn:asciiname":"Berkt",
    "gn:country_code":"NL",
    "gn:dem":21,
    "gn:feature_class":"P",
    "gn:feature_code":"PPL",
    "gn:name":"Berkt",
    "gn:population":0,
    "gn:timezone":"Europe/Amsterdam",
    "iso:country":"NL",
    "wof:name":"Berkt",
    "wof:placetype":"locality"
},
  "geometry": {"coordinates":[5.37917,51.4275],"type":"Point"}
}