{
  "type": "Feature",
  "properties": {
    "gn:admin1_code":"5.0",
    "gn:admin2_code":"1507",
    "gn:asciiname":"Nachtegaal",
    "gn:country_code":"NL",
    "gn:dem":19,
    "gn:feature_class":"P",
    "gn:feature_code":"PPL",
    "gn:name":"Nachtegaal",
    "gn:population":0,
    "gn:timezone":"Europe/Amsterdam",
    "iso:country":"NL",
    "wof:name":"Nachtegaal",
    "wof:placetype":"locality"
},
  "geometry": {"coordinates":[6.14273,51.51035],"type":"Point"}
}