{
  "type": "Feature",
  "properties": {
    "gn:admin1_code":"3.0",
    "gn:admin2_code":"285.0",
    "gn:asciiname":"Duistervoorde",
    "gn:country_code":"NL",
    "gn:dem":8,
    "gn:feature_class":"P",
    "gn:feature_code":"PPL",
    "gn:name":"Duistervoorde",
    "gn:population":0,
    "gn:timezone":"Europe/Amsterdam",
    "iso:country":"NL",
    "wof:name":"Duistervoorde",
    "wof:placetype":"locality"
},
  "geometry": {"coordinates":[6.09167,52.22917],"type":"Point"}
}