{
  "type": "Feature",
  "properties": {
    "gn:admin1_code":"6.0",
    "gn:admin2_code":"1659.0",
    "gn:asciiname":"Broekkant",
    "gn:country_code":"NL",
    "gn:dem":15,
    "gn:feature_class":"P",
    "gn:feature_code":"PPL",
    "gn:name":"Broekkant",
    "gn:population":0,
    "gn:timezone":"Europe/Amsterdam",
    "iso:country":"NL",
    "wof:name":"Broekkant",
    "wof:placetype":"locality"
},
  "geometry": {"coordinates":[5.65278,51.53583],"type":"Point"}
}