{
  "type": "Feature",
  "properties": {
    "gn:admin1_code":"11.0",
    "gn:admin2_code":"689.0",
    "gn:asciiname":"Den Dool",
    "gn:country_code":"NL",
    "gn:dem":0,
    "gn:feature_class":"P",
    "gn:feature_code":"PPL",
    "gn:name":"Den Dool",
    "gn:population":0,
    "gn:timezone":"Europe/Amsterdam",
    "iso:country":"NL",
    "wof:name":"Den Dool",
    "wof:placetype":"locality"
},
  "geometry": {"coordinates":[4.95972,51.91167],"type":"Point"}
}