{
  "type": "Feature",
  "properties": {
    "gn:admin1_code":"6.0",
    "gn:admin2_code":"1706",
    "gn:asciiname":"Schoordijk",
    "gn:country_code":"NL",
    "gn:dem":31,
    "gn:feature_class":"P",
    "gn:feature_code":"PPL",
    "gn:name":"Schoordijk",
    "gn:population":0,
    "gn:timezone":"Europe/Amsterdam",
    "iso:country":"NL",
    "wof:name":"Schoordijk",
    "wof:placetype":"locality"
},
  "geometry": {"coordinates":[5.59306,51.2775],"type":"Point"}
}