{
  "type": "Feature",
  "properties": {
    "gn:admin1_code":"5.0",
    "gn:admin2_code":"0893",
    "gn:asciiname":"Zeelberg",
    "gn:country_code":"NL",
    "gn:dem":21,
    "gn:feature_class":"P",
    "gn:feature_code":"PPL",
    "gn:name":"Zeelberg",
    "gn:population":0,
    "gn:timezone":"Europe/Amsterdam",
    "iso:country":"NL",
    "wof:name":"Zeelberg",
    "wof:placetype":"locality"
},
  "geometry": {"coordinates":[6.14167,51.525],"type":"Point"}
}