{
  "type": "Feature",
  "properties": {
    "gn:admin1_code":"4.0",
    "gn:admin2_code":"0009",
    "gn:asciiname":"Lutjewolde",
    "gn:country_code":"NL",
    "gn:dem":-3,
    "gn:feature_class":"P",
    "gn:feature_code":"PPL",
    "gn:name":"Lutjewolde",
    "gn:population":0,
    "gn:timezone":"Europe/Amsterdam",
    "iso:country":"NL",
    "wof:name":"Lutjewolde",
    "wof:placetype":"locality"
},
  "geometry": {"coordinates":[6.65139,53.29333000000001],"type":"Point"}
}