{
  "type": "Feature",
  "properties": {
    "gn:admin1_code":"15.0",
    "gn:admin2_code":"1708",
    "gn:asciiname":"Verlaat",
    "gn:country_code":"NL",
    "gn:dem":3,
    "gn:feature_class":"P",
    "gn:feature_code":"PPL",
    "gn:name":"Verlaat",
    "gn:population":0,
    "gn:timezone":"Europe/Amsterdam",
    "iso:country":"NL",
    "wof:name":"Verlaat",
    "wof:placetype":"locality"
},
  "geometry": {"coordinates":[6.10972,52.785],"type":"Point"}
}