{
  "type": "Feature",
  "properties": {
    "gn:admin1_code":"15.0",
    "gn:admin2_code":"0180",
    "gn:asciiname":"Leenders",
    "gn:country_code":"NL",
    "gn:dem":1,
    "gn:feature_class":"P",
    "gn:feature_code":"PPLL",
    "gn:name":"Leenders",
    "gn:population":0,
    "gn:timezone":"Europe/Amsterdam",
    "iso:country":"NL",
    "wof:name":"Leenders",
    "wof:placetype":"locality"
},
  "geometry": {"coordinates":[6.15784,52.69007],"type":"Point"}
}