{
  "type": "Feature",
  "properties": {
    "gn:admin1_code":"15.0",
    "gn:admin2_code":"158.0",
    "gn:asciiname":"Eppenzolder",
    "gn:country_code":"NL",
    "gn:dem":20,
    "gn:feature_class":"P",
    "gn:feature_code":"PPL",
    "gn:name":"Eppenzolder",
    "gn:population":0,
    "gn:timezone":"Europe/Amsterdam",
    "iso:country":"NL",
    "wof:name":"Eppenzolder",
    "wof:placetype":"locality"
},
  "geometry": {"coordinates":[6.71111,52.18667],"type":"Point"}
}