{
  "type": "Feature",
  "properties": {
    "gn:admin1_code":"9.0",
    "gn:admin2_code":"0344",
    "gn:asciiname":"Oudenrijn",
    "gn:country_code":"NL",
    "gn:dem":3,
    "gn:feature_class":"P",
    "gn:feature_code":"PPL",
    "gn:name":"Oudenrijn",
    "gn:population":0,
    "gn:timezone":"Europe/Amsterdam",
    "iso:country":"NL",
    "name:fra_x_preferred":[
        "Oudenrijn"
    ],
    "name:nld_x_preferred":[
        "Oudenrijn"
    ],
    "wof:name":"Oudenrijn",
    "wof:placetype":"locality"
},
  "geometry": {"coordinates":[5.06944,52.08167],"type":"Point"}
}