{
  "type": "Feature",
  "properties": {
    "gn:admin1_code":"5.0",
    "gn:admin2_code":"0935",
    "gn:asciiname":"Marienwaard",
    "gn:country_code":"NL",
    "gn:dem":47,
    "gn:feature_class":"P",
    "gn:feature_code":"PPL",
    "gn:name":"Mari\u00ebnwaard",
    "gn:population":0,
    "gn:timezone":"Europe/Amsterdam",
    "iso:country":"NL",
    "wof:name":"Marienwaard",
    "wof:placetype":"locality"
},
  "geometry": {"coordinates":[5.72222,50.87083],"type":"Point"}
}