{
  "type": "Feature",
  "properties": {
    "gn:admin1_code":"6.0",
    "gn:admin2_code":"0786",
    "gn:asciiname":"Nieuw-Gassel",
    "gn:country_code":"NL",
    "gn:dem":11,
    "gn:feature_class":"P",
    "gn:feature_code":"PPL",
    "gn:name":"Nieuw-Gassel",
    "gn:population":0,
    "gn:timezone":"Europe/Amsterdam",
    "iso:country":"NL",
    "wof:name":"Nieuw-Gassel",
    "wof:placetype":"locality"
},
  "geometry": {"coordinates":[5.76944,51.73333],"type":"Point"}
}