{
  "type": "Feature",
  "properties": {
    "gn:admin1_code":"5.0",
    "gn:admin2_code":"0957",
    "gn:asciiname":"Thuserhof",
    "gn:country_code":"NL",
    "gn:dem":27,
    "gn:feature_class":"P",
    "gn:feature_code":"PPL",
    "gn:name":"Thuserhof",
    "gn:population":0,
    "gn:timezone":"Europe/Amsterdam",
    "iso:country":"NL",
    "wof:name":"Thuserhof",
    "wof:placetype":"locality"
},
  "geometry": {"coordinates":[6.04167,51.18417],"type":"Point"}
}