{
  "type": "Feature",
  "properties": {
    "gn:admin1_code":"6.0",
    "gn:admin2_code":"1652",
    "gn:asciiname":"Hoogen-Aarle",
    "gn:country_code":"NL",
    "gn:dem":22,
    "gn:feature_class":"P",
    "gn:feature_code":"PPL",
    "gn:name":"Hoogen-Aarle",
    "gn:population":0,
    "gn:timezone":"Europe/Amsterdam",
    "iso:country":"NL",
    "wof:name":"Hoogen-Aarle",
    "wof:placetype":"locality"
},
  "geometry": {"coordinates":[5.71944,51.53],"type":"Point"}
}