{
  "type": "Feature",
  "properties": {
    "gn:admin1_code":"5.0",
    "gn:admin2_code":"0951",
    "gn:asciiname":"Klein Haasdal",
    "gn:cc2":"NL",
    "gn:country_code":"NL",
    "gn:dem":138,
    "gn:feature_class":"P",
    "gn:feature_code":"PPL",
    "gn:name":"Klein Haasdal",
    "gn:population":0,
    "gn:timezone":"Europe/Amsterdam",
    "iso:country":"NL",
    "name:und_x_variant":[
        "Klein Haesdal"
    ],
    "wof:name":"Klein Haasdal",
    "wof:placetype":"locality"
},
  "geometry": {"coordinates":[5.82083,50.89833],"type":"Point"}
}