{
  "type": "Feature",
  "properties": {
    "gn:admin1_code":"6.0",
    "gn:admin2_code":"1674",
    "gn:asciiname":"Zoomvliet",
    "gn:country_code":"NL",
    "gn:dem":10,
    "gn:feature_class":"P",
    "gn:feature_code":"PPL",
    "gn:name":"Zoomvliet",
    "gn:population":0,
    "gn:timezone":"Europe/Amsterdam",
    "iso:country":"NL",
    "wof:name":"Zoomvliet",
    "wof:placetype":"locality"
},
  "geometry": {"coordinates":[4.35833,51.49417],"type":"Point"}
}