{
  "type": "Feature",
  "properties": {
    "gn:admin1_code":"6.0",
    "gn:admin2_code":"1652",
    "gn:asciiname":"Nuijeneind",
    "gn:country_code":"NL",
    "gn:dem":19,
    "gn:feature_class":"P",
    "gn:feature_code":"PPL",
    "gn:name":"Nuijeneind",
    "gn:population":0,
    "gn:timezone":"Europe/Amsterdam",
    "iso:country":"NL",
    "wof:name":"Nuijeneind",
    "wof:placetype":"locality"
},
  "geometry": {"coordinates":[5.71667,51.50667],"type":"Point"}
}