{
  "type": "Feature",
  "properties": {
    "gn:admin1_code":"10.0",
    "gn:admin2_code":"1714",
    "gn:asciiname":"Maaidijk",
    "gn:country_code":"NL",
    "gn:dem":0,
    "gn:feature_class":"P",
    "gn:feature_code":"PPL",
    "gn:name":"Maaidijk",
    "gn:population":0,
    "gn:timezone":"Europe/Amsterdam",
    "iso:country":"NL",
    "wof:name":"Maaidijk",
    "wof:placetype":"locality"
},
  "geometry": {"coordinates":[3.50139,51.3375],"type":"Point"}
}