{
  "type": "Feature",
  "properties": {
    "gn:admin1_code":"6.0",
    "gn:admin2_code":"856.0",
    "gn:asciiname":"Duifhuis",
    "gn:country_code":"NL",
    "gn:dem":10,
    "gn:feature_class":"P",
    "gn:feature_code":"PPL",
    "gn:name":"Duifhuis",
    "gn:population":0,
    "gn:timezone":"Europe/Amsterdam",
    "iso:country":"NL",
    "wof:name":"Duifhuis",
    "wof:placetype":"locality"
},
  "geometry": {"coordinates":[5.59583,51.63917],"type":"Point"}
}