{
  "type": "Feature",
  "properties": {
    "gn:admin1_code":"3.0",
    "gn:admin2_code":"0263",
    "gn:asciiname":"Wordragen",
    "gn:country_code":"NL",
    "gn:dem":2,
    "gn:feature_class":"P",
    "gn:feature_code":"PPL",
    "gn:name":"Wordragen",
    "gn:population":0,
    "gn:timezone":"Europe/Amsterdam",
    "iso:country":"NL",
    "wof:name":"Wordragen",
    "wof:placetype":"locality"
},
  "geometry": {"coordinates":[5.22778,51.75667],"type":"Point"}
}