{
  "type": "Feature",
  "properties": {
    "gn:admin1_code":"1.0",
    "gn:admin2_code":"109.0",
    "gn:asciiname":"De Hoek",
    "gn:country_code":"NL",
    "gn:dem":17,
    "gn:feature_class":"P",
    "gn:feature_code":"PPLL",
    "gn:name":"De Hoek",
    "gn:population":0,
    "gn:timezone":"Europe/Amsterdam",
    "iso:country":"NL",
    "wof:name":"De Hoek",
    "wof:placetype":"locality"
},
  "geometry": {"coordinates":[6.81058,52.75541],"type":"Point"}
}