{
  "type": "Feature",
  "properties": {
    "gn:admin1_code":"3.0",
    "gn:admin2_code":"0214",
    "gn:asciiname":"Hoog Kana",
    "gn:country_code":"NL",
    "gn:dem":5,
    "gn:feature_class":"P",
    "gn:feature_code":"PPL",
    "gn:name":"Hoog Kana",
    "gn:population":0,
    "gn:timezone":"Europe/Amsterdam",
    "iso:country":"NL",
    "wof:name":"Hoog Kana",
    "wof:placetype":"locality"
},
  "geometry": {"coordinates":[5.49306,51.96583],"type":"Point"}
}