{
  "type": "Feature",
  "properties": {
    "gn:admin1_code":"3.0",
    "gn:admin2_code":"263.0",
    "gn:asciiname":"Berm",
    "gn:country_code":"NL",
    "gn:dem":4,
    "gn:feature_class":"P",
    "gn:feature_code":"PPL",
    "gn:name":"Berm",
    "gn:population":0,
    "gn:timezone":"Europe/Amsterdam",
    "iso:country":"NL",
    "wof:name":"Berm",
    "wof:placetype":"locality"
},
  "geometry": {"coordinates":[5.32416,51.78197],"type":"Point"}
}