{
  "type": "Feature",
  "properties": {
    "gn:admin1_code":"3.0",
    "gn:admin2_code":"263.0",
    "gn:asciiname":"Berm",
    "gn:country_code":"NL",
    "gn:dem":4,
    "gn:feature_class":"P",
    "gn:feature_code":"PPL",
    "gn:name":"Berm",
    "gn:population":0,
    "gn:timezone":"Europe/Amsterdam",
    "iso:country":"NL",
    "name:bel_x_preferred":[
        "\u0411\u0435\u0440\u043c\u0430"
    ],
    "name:cat_x_preferred":[
        "Berma"
    ],
    "name:ces_x_preferred":[
        "Berma"
    ],
    "name:dan_x_preferred":[
        "Berme"
    ],
    "name:deu_x_preferred":[
        "Berme"
    ],
    "name:epo_x_preferred":[
        "Bermo"
    ],
    "name:est_x_preferred":[
        "Berm"
    ],
    "name:fra_x_preferred":[
        "Risberme"
    ],
    "name:ido_x_preferred":[
        "Bermo"
    ],
    "name:ita_x_preferred":[
        "Berma"
    ],
    "name:jpn_x_preferred":[
        "\u72ac\u8d70\u308a"
    ],
    "name:nld_x_preferred":[
        "Berm"
    ],
    "name:pol_x_preferred":[
        "Odsadzka"
    ],
    "name:rus_x_preferred":[
        "\u0411\u0435\u0440\u043c\u0430"
    ],
    "name:slv_x_preferred":[
        "Berma"
    ],
    "name:spa_x_preferred":[
        "Berma"
    ],
    "name:ukr_x_preferred":[
        "\u0411\u0435\u0440\u043c\u0430"
    ],
    "wof:name":"Berm",
    "wof:placetype":"locality"
},
  "geometry": {"coordinates":[5.32416,51.78197],"type":"Point"}
}