{
  "type": "Feature",
  "properties": {
    "gn:admin1_code":"5.0",
    "gn:admin2_code":"0938",
    "gn:asciiname":"Voulwames",
    "gn:cc2":"NL",
    "gn:country_code":"NL",
    "gn:dem":41,
    "gn:feature_class":"P",
    "gn:feature_code":"PPL",
    "gn:name":"Voulwames",
    "gn:population":0,
    "gn:timezone":"Europe/Amsterdam",
    "iso:country":"NL",
    "name:und_x_variant":[
        "Voulwamus",
        "Vuilwammes",
        "Voulwamis"
    ],
    "wof:name":"Voulwames",
    "wof:placetype":"locality"
},
  "geometry": {"coordinates":[5.72222,50.90667],"type":"Point"}
}