{
  "type": "Feature",
  "properties": {
    "gn:admin1_code":"3.0",
    "gn:admin2_code":"228.0",
    "gn:asciiname":"Hoekelum",
    "gn:country_code":"NL",
    "gn:dem":15,
    "gn:feature_class":"P",
    "gn:feature_code":"PPL",
    "gn:name":"Hoekelum",
    "gn:population":0,
    "gn:timezone":"Europe/Amsterdam",
    "iso:country":"NL",
    "wof:name":"Hoekelum",
    "wof:placetype":"locality"
},
  "geometry": {"coordinates":[5.66389,52.01083],"type":"Point"}
}