{
  "type": "Feature",
  "properties": {
    "gn:admin1_code":"2.0",
    "gn:admin2_code":"70.0",
    "gn:asciiname":"Arkens",
    "gn:country_code":"NL",
    "gn:dem":0,
    "gn:feature_class":"P",
    "gn:feature_code":"PPLL",
    "gn:name":"Arkens",
    "gn:population":0,
    "gn:timezone":"Europe/Amsterdam",
    "iso:country":"NL",
    "name:fry_x_preferred":[
        "Erkens"
    ],
    "name:nld_x_preferred":[
        "Arkens"
    ],
    "wof:name":"Arkens",
    "wof:placetype":"locality"
},
  "geometry": {"coordinates":[5.55179,53.19333],"type":"Point"}
}