{
  "type": "Feature",
  "properties": {
    "gn:admin1_code":"1.0",
    "gn:admin2_code":"1699.0",
    "gn:asciiname":"Boerelaan",
    "gn:country_code":"NL",
    "gn:dem":2,
    "gn:feature_class":"P",
    "gn:feature_code":"PPL",
    "gn:name":"Boerelaan",
    "gn:population":0,
    "gn:timezone":"Europe/Amsterdam",
    "iso:country":"NL",
    "wof:name":"Boerelaan",
    "wof:placetype":"locality"
},
  "geometry": {"coordinates":[6.49167,53.1325],"type":"Point"}
}