{
  "type": "Feature",
  "properties": {
    "gn:admin1_code":"6.0",
    "gn:admin2_code":"1658",
    "gn:asciiname":"Oosterik",
    "gn:country_code":"NL",
    "gn:dem":26,
    "gn:feature_class":"P",
    "gn:feature_code":"PPL",
    "gn:name":"Oosterik",
    "gn:population":0,
    "gn:timezone":"Europe/Amsterdam",
    "iso:country":"NL",
    "wof:name":"Oosterik",
    "wof:placetype":"locality"
},
  "geometry": {"coordinates":[5.5625,51.355],"type":"Point"}
}