{
  "type": "Feature",
  "properties": {
    "gn:admin1_code":"2.0",
    "gn:admin2_code":"79.0",
    "gn:asciiname":"De Kolk",
    "gn:country_code":"NL",
    "gn:dem":1,
    "gn:feature_class":"P",
    "gn:feature_code":"PPL",
    "gn:name":"De Kolk",
    "gn:population":0,
    "gn:timezone":"Europe/Amsterdam",
    "iso:country":"NL",
    "wof:name":"De Kolk",
    "wof:placetype":"locality"
},
  "geometry": {"coordinates":[6.24467,53.29748000000001],"type":"Point"}
}