{
  "type": "Feature",
  "properties": {
    "gn:admin1_code":"5.0",
    "gn:admin2_code":"1640.0",
    "gn:asciiname":"Aan de Bergen",
    "gn:country_code":"NL",
    "gn:dem":29,
    "gn:feature_class":"P",
    "gn:feature_code":"PPL",
    "gn:name":"Aan de Bergen",
    "gn:population":0,
    "gn:timezone":"Europe/Amsterdam",
    "iso:country":"NL",
    "wof:name":"Aan de Bergen",
    "wof:placetype":"locality"
},
  "geometry": {"coordinates":[5.87778,51.26583],"type":"Point"}
}