{
  "type": "Feature",
  "properties": {
    "gn:admin1_code":"6.0",
    "gn:admin2_code":"0855",
    "gn:asciiname":"Rugdijk",
    "gn:country_code":"NL",
    "gn:dem":12,
    "gn:feature_class":"P",
    "gn:feature_code":"PPL",
    "gn:name":"Rugdijk",
    "gn:population":0,
    "gn:timezone":"Europe/Amsterdam",
    "iso:country":"NL",
    "wof:name":"Rugdijk",
    "wof:placetype":"locality"
},
  "geometry": {"coordinates":[5.09722,51.59083],"type":"Point"}
}