{
  "type": "Feature",
  "properties": {
    "gn:admin1_code":"3.0",
    "gn:admin2_code":"232.0",
    "gn:asciiname":"Dijkhuizen",
    "gn:country_code":"NL",
    "gn:dem":9,
    "gn:feature_class":"P",
    "gn:feature_code":"PPL",
    "gn:name":"Dijkhuizen",
    "gn:population":0,
    "gn:timezone":"Europe/Amsterdam",
    "iso:country":"NL",
    "wof:name":"Dijkhuizen",
    "wof:placetype":"locality"
},
  "geometry": {"coordinates":[6.01389,52.355],"type":"Point"}
}