{
  "type": "Feature",
  "properties": {
    "gn:admin1_code":"7.0",
    "gn:admin2_code":"0448",
    "gn:asciiname":"Zuidhaffel",
    "gn:cc2":"NL",
    "gn:country_code":"NL",
    "gn:dem":5,
    "gn:feature_class":"P",
    "gn:feature_code":"PPL",
    "gn:name":"Zuidhaffel",
    "gn:population":0,
    "gn:timezone":"Europe/Amsterdam",
    "iso:country":"NL",
    "name:und_x_variant":[
        "Zuidhappel"
    ],
    "wof:name":"Zuidhaffel",
    "wof:placetype":"locality"
},
  "geometry": {"coordinates":[4.80515,53.03768],"type":"Point"}
}