{
  "type": "Feature",
  "properties": {
    "gn:admin1_code":"4.0",
    "gn:admin2_code":"0010",
    "gn:asciiname":"Lesterhuis",
    "gn:country_code":"NL",
    "gn:dem":-3,
    "gn:feature_class":"P",
    "gn:feature_code":"PPL",
    "gn:name":"Lesterhuis",
    "gn:population":0,
    "gn:timezone":"Europe/Amsterdam",
    "iso:country":"NL",
    "wof:name":"Lesterhuis",
    "wof:placetype":"locality"
},
  "geometry": {"coordinates":[7.02355,53.28233],"type":"Point"}
}