{
  "type": "Feature",
  "properties": {
    "gn:admin1_code":"11.0",
    "gn:admin2_code":"0707",
    "gn:asciiname":"Hoogewaard",
    "gn:country_code":"NL",
    "gn:dem":2,
    "gn:feature_class":"P",
    "gn:feature_code":"PPL",
    "gn:name":"Hoogewaard",
    "gn:population":0,
    "gn:timezone":"Europe/Amsterdam",
    "iso:country":"NL",
    "wof:name":"Hoogewaard",
    "wof:placetype":"locality"
},
  "geometry": {"coordinates":[4.95556,51.955],"type":"Point"}
}