{
  "type": "Feature",
  "properties": {
    "gn:admin1_code":"6.0",
    "gn:admin2_code":"744.0",
    "gn:asciiname":"Het Goordonk",
    "gn:country_code":"NL",
    "gn:dem":28,
    "gn:feature_class":"P",
    "gn:feature_code":"PPL",
    "gn:name":"Het Goordonk",
    "gn:population":0,
    "gn:timezone":"Europe/Amsterdam",
    "iso:country":"NL",
    "wof:name":"Het Goordonk",
    "wof:placetype":"locality"
},
  "geometry": {"coordinates":[4.90833,51.45333],"type":"Point"}
}