{
  "type": "Feature",
  "properties": {
    "gn:admin1_code":"4.0",
    "gn:admin2_code":"0048",
    "gn:asciiname":"Sellingerzwarteveen",
    "gn:country_code":"NL",
    "gn:dem":5,
    "gn:feature_class":"P",
    "gn:feature_code":"PPL",
    "gn:name":"Sellingerzwarteveen",
    "gn:population":0,
    "gn:timezone":"Europe/Amsterdam",
    "iso:country":"NL",
    "wof:name":"Sellingerzwarteveen",
    "wof:placetype":"locality"
},
  "geometry": {"coordinates":[7.15833,52.9575],"type":"Point"}
}