{
  "type": "Feature",
  "properties": {
    "gn:admin1_code":"4.0",
    "gn:admin2_code":"0048",
    "gn:asciiname":"Ter Borg",
    "gn:country_code":"NL",
    "gn:dem":10,
    "gn:feature_class":"P",
    "gn:feature_code":"PPL",
    "gn:name":"Ter Borg",
    "gn:population":0,
    "gn:timezone":"Europe/Amsterdam",
    "iso:country":"NL",
    "wof:name":"Ter Borg",
    "wof:placetype":"locality"
},
  "geometry": {"coordinates":[7.13056,52.93833000000001],"type":"Point"}
}