{
  "type": "Feature",
  "properties": {
    "gn:admin1_code":"3.0",
    "gn:admin2_code":"0214",
    "gn:asciiname":"Zwarte Paard",
    "gn:country_code":"NL",
    "gn:dem":5,
    "gn:feature_class":"P",
    "gn:feature_code":"PPL",
    "gn:name":"Zwarte Paard",
    "gn:population":0,
    "gn:timezone":"Europe/Amsterdam",
    "iso:country":"NL",
    "name:und_x_variant":[
        "Het Zwarte Paard",
        "Zwarte Paard"
    ],
    "wof:name":"Zwarte Paard",
    "wof:placetype":"locality"
},
  "geometry": {"coordinates":[5.45036,51.95062],"type":"Point"}
}