{
  "type": "Feature",
  "properties": {
    "gn:admin1_code":"11.0",
    "gn:admin2_code":"1842.0",
    "gn:asciiname":"Gaag",
    "gn:country_code":"NL",
    "gn:dem":-2,
    "gn:feature_class":"P",
    "gn:feature_code":"PPL",
    "gn:name":"Gaag",
    "gn:population":0,
    "gn:timezone":"Europe/Amsterdam",
    "iso:country":"NL",
    "wof:name":"Gaag",
    "wof:placetype":"locality"
},
  "geometry": {"coordinates":[4.28889,51.955],"type":"Point"}
}