{
  "type": "Feature",
  "properties": {
    "gn:admin1_code":"6.0",
    "gn:admin2_code":"0758",
    "gn:asciiname":"Tervoort",
    "gn:country_code":"NL",
    "gn:dem":6,
    "gn:feature_class":"P",
    "gn:feature_code":"PPL",
    "gn:name":"Tervoort",
    "gn:population":0,
    "gn:timezone":"Europe/Amsterdam",
    "iso:country":"NL",
    "wof:name":"Tervoort",
    "wof:placetype":"locality"
},
  "geometry": {"coordinates":[4.83889,51.575],"type":"Point"}
}