{
  "type": "Feature",
  "properties": {
    "gn:admin1_code":"6.0",
    "gn:admin2_code":"0879",
    "gn:asciiname":"Moeren",
    "gn:country_code":"NL",
    "gn:dem":14,
    "gn:feature_class":"P",
    "gn:feature_code":"PPL",
    "gn:name":"Moeren",
    "gn:population":0,
    "gn:timezone":"Europe/Amsterdam",
    "iso:country":"NL",
    "wof:name":"Moeren",
    "wof:placetype":"locality"
},
  "geometry": {"coordinates":[4.61111,51.485],"type":"Point"}
}