{
  "type": "Feature",
  "properties": {
    "gn:admin1_code":"6.0",
    "gn:admin2_code":"0851",
    "gn:asciiname":"Rolaf",
    "gn:country_code":"NL",
    "gn:dem":-1,
    "gn:feature_class":"P",
    "gn:feature_code":"PPL",
    "gn:name":"Rolaf",
    "gn:population":0,
    "gn:timezone":"Europe/Amsterdam",
    "iso:country":"NL",
    "wof:name":"Rolaf",
    "wof:placetype":"locality"
},
  "geometry": {"coordinates":[4.24587,51.57248],"type":"Point"}
}