{
  "type": "Feature",
  "properties": {
    "gn:admin1_code":"10.0",
    "gn:admin2_code":"0717",
    "gn:asciiname":"Klein-Valkenisse",
    "gn:country_code":"NL",
    "gn:dem":0,
    "gn:feature_class":"P",
    "gn:feature_code":"PPL",
    "gn:name":"Klein-Valkenisse",
    "gn:population":0,
    "gn:timezone":"Europe/Amsterdam",
    "iso:country":"NL",
    "wof:name":"Klein-Valkenisse",
    "wof:placetype":"locality"
},
  "geometry": {"coordinates":[3.51528,51.48833],"type":"Point"}
}