{
  "type": "Feature",
  "properties": {
    "gn:admin1_code":"3.0",
    "gn:admin2_code":"1586.0",
    "gn:asciiname":"De Wopereis",
    "gn:country_code":"NL",
    "gn:dem":19,
    "gn:feature_class":"P",
    "gn:feature_code":"PPL",
    "gn:name":"De Wopereis",
    "gn:population":0,
    "gn:timezone":"Europe/Amsterdam",
    "iso:country":"NL",
    "wof:name":"De Wopereis",
    "wof:placetype":"locality"
},
  "geometry": {"coordinates":[6.49583,52.00417],"type":"Point"}
}