{
  "type": "Feature",
  "properties": {
    "gn:admin1_code":"6.0",
    "gn:admin2_code":"1709",
    "gn:asciiname":"Zevenhuizen",
    "gn:country_code":"NL",
    "gn:dem":-1,
    "gn:feature_class":"P",
    "gn:feature_code":"PPL",
    "gn:name":"Zevenhuizen",
    "gn:population":0,
    "gn:timezone":"Europe/Amsterdam",
    "iso:country":"NL",
    "wof:name":"Zevenhuizen",
    "wof:placetype":"locality"
},
  "geometry": {"coordinates":[4.41528,51.64833],"type":"Point"}
}