{
  "type": "Feature",
  "properties": {
    "gn:admin1_code":"3.0",
    "gn:admin2_code":"0214",
    "gn:asciiname":"Meerten",
    "gn:country_code":"NL",
    "gn:dem":6,
    "gn:feature_class":"P",
    "gn:feature_code":"PPL",
    "gn:name":"Meerten",
    "gn:population":0,
    "gn:timezone":"Europe/Amsterdam",
    "iso:country":"NL",
    "wof:name":"Meerten",
    "wof:placetype":"locality"
},
  "geometry": {"coordinates":[5.52222,51.93917],"type":"Point"}
}