{
  "type": "Feature",
  "properties": {
    "gn:admin1_code":"4.0",
    "gn:admin2_code":"48.0",
    "gn:asciiname":"Ter Walslage",
    "gn:country_code":"NL",
    "gn:dem":8,
    "gn:feature_class":"P",
    "gn:feature_code":"PPL",
    "gn:name":"Ter Walslage",
    "gn:population":0,
    "gn:timezone":"Europe/Amsterdam",
    "iso:country":"NL",
    "wof:name":"Ter Walslage",
    "wof:placetype":"locality"
},
  "geometry": {"coordinates":[7.11944,52.92167],"type":"Point"}
}