{
  "type": "Feature",
  "properties": {
    "gn:admin1_code":"10.0",
    "gn:admin2_code":"716.0",
    "gn:asciiname":"De Rand",
    "gn:country_code":"NL",
    "gn:dem":-4,
    "gn:feature_class":"P",
    "gn:feature_code":"PPL",
    "gn:name":"De Rand",
    "gn:population":0,
    "gn:timezone":"Europe/Amsterdam",
    "iso:country":"NL",
    "wof:name":"De Rand",
    "wof:placetype":"locality"
},
  "geometry": {"coordinates":[4.11528,51.55583],"type":"Point"}
}