{
  "type": "Feature",
  "properties": {
    "gn:admin1_code":"1.0",
    "gn:admin2_code":"119.0",
    "gn:asciiname":"De Kolk",
    "gn:country_code":"NL",
    "gn:dem":0,
    "gn:feature_class":"P",
    "gn:feature_code":"PPL",
    "gn:name":"De Kolk",
    "gn:population":0,
    "gn:timezone":"Europe/Amsterdam",
    "iso:country":"NL",
    "wof:name":"De Kolk",
    "wof:placetype":"locality"
},
  "geometry": {"coordinates":[6.14583,52.71167],"type":"Point"}
}