{
  "type": "Feature",
  "properties": {
    "gn:admin1_code":"15.0",
    "gn:admin2_code":"163.0",
    "gn:asciiname":"Hankate",
    "gn:cc2":"NL",
    "gn:country_code":"NL",
    "gn:dem":8,
    "gn:feature_class":"P",
    "gn:feature_code":"PPL",
    "gn:name":"Hankate",
    "gn:population":0,
    "gn:timezone":"Europe/Amsterdam",
    "iso:country":"NL",
    "name:und_x_variant":[
        "'t Hankale"
    ],
    "wof:name":"Hankate",
    "wof:placetype":"locality"
},
  "geometry": {"coordinates":[6.43889,52.43417],"type":"Point"}
}