{
  "type": "Feature",
  "properties": {
    "gn:admin1_code":"4.0",
    "gn:admin2_code":"0037",
    "gn:asciiname":"Oomsberg",
    "gn:country_code":"NL",
    "gn:dem":4,
    "gn:feature_class":"P",
    "gn:feature_code":"PPL",
    "gn:name":"Oomsberg",
    "gn:population":0,
    "gn:timezone":"Europe/Amsterdam",
    "iso:country":"NL",
    "wof:name":"Oomsberg",
    "wof:placetype":"locality"
},
  "geometry": {"coordinates":[7.02361,52.9675],"type":"Point"}
}