{
  "type": "Feature",
  "properties": {
    "gn:admin1_code":"6.0",
    "gn:admin2_code":"1724.0",
    "gn:asciiname":"De Rund",
    "gn:country_code":"NL",
    "gn:dem":34,
    "gn:feature_class":"P",
    "gn:feature_code":"PPL",
    "gn:name":"De Rund",
    "gn:population":0,
    "gn:timezone":"Europe/Amsterdam",
    "iso:country":"NL",
    "wof:name":"De Rund",
    "wof:placetype":"locality"
},
  "geometry": {"coordinates":[5.32592,51.30709],"type":"Point"}
}