{
  "type": "Feature",
  "properties": {
    "gn:admin1_code":"4.0",
    "gn:admin2_code":"7.0",
    "gn:asciiname":"Den Ham",
    "gn:cc2":"NL",
    "gn:country_code":"NL",
    "gn:dem":-2,
    "gn:feature_class":"P",
    "gn:feature_code":"PPL",
    "gn:name":"Den Ham",
    "gn:population":0,
    "gn:timezone":"Europe/Amsterdam",
    "iso:country":"NL",
    "name:fra_x_preferred":[
        "Den Ham"
    ],
    "name:nld_x_preferred":[
        "Den Ham"
    ],
    "name:und_x_variant":[
        "Ham"
    ],
    "wof:name":"Den Ham",
    "wof:placetype":"locality"
},
  "geometry": {"coordinates":[7.16667,53.13583000000001],"type":"Point"}
}