{
  "type": "Feature",
  "properties": {
    "gn:admin1_code":"10.0",
    "gn:admin2_code":"0717",
    "gn:asciiname":"Pitteperk",
    "gn:country_code":"NL",
    "gn:dem":0,
    "gn:feature_class":"P",
    "gn:feature_code":"PPL",
    "gn:name":"Pitteperk",
    "gn:population":0,
    "gn:timezone":"Europe/Amsterdam",
    "iso:country":"NL",
    "wof:name":"Pitteperk",
    "wof:placetype":"locality"
},
  "geometry": {"coordinates":[3.60833,51.56167],"type":"Point"}
}