{
  "type": "Feature",
  "properties": {
    "gn:admin1_code":"15.0",
    "gn:admin2_code":"160.0",
    "gn:asciiname":"Collendoornerveen",
    "gn:country_code":"NL",
    "gn:dem":8,
    "gn:feature_class":"P",
    "gn:feature_code":"PPL",
    "gn:name":"Collendoornerveen",
    "gn:population":0,
    "gn:timezone":"Europe/Amsterdam",
    "iso:country":"NL",
    "wof:name":"Collendoornerveen",
    "wof:placetype":"locality"
},
  "geometry": {"coordinates":[6.59167,52.59333],"type":"Point"}
}