{
  "type": "Feature",
  "properties": {
    "gn:admin1_code":"6.0",
    "gn:admin2_code":"1771.0",
    "gn:asciiname":"Diepenbroek",
    "gn:country_code":"NL",
    "gn:dem":18,
    "gn:feature_class":"P",
    "gn:feature_code":"PPL",
    "gn:name":"Diepenbroek",
    "gn:population":0,
    "gn:timezone":"Europe/Amsterdam",
    "iso:country":"NL",
    "wof:name":"Diepenbroek",
    "wof:placetype":"locality"
},
  "geometry": {"coordinates":[5.60417,51.465],"type":"Point"}
}