{
  "type": "Feature",
  "properties": {
    "gn:admin1_code":"3.0",
    "gn:admin2_code":"1734",
    "gn:asciiname":"Loenen",
    "gn:cc2":"NL",
    "gn:country_code":"NL",
    "gn:dem":8,
    "gn:feature_class":"P",
    "gn:feature_code":"PPL",
    "gn:name":"Loenen",
    "gn:population":0,
    "gn:timezone":"Europe/Amsterdam",
    "iso:country":"NL",
    "name:und_x_variant":[
        "Wolferen",
        "Loenen en Wolferen"
    ],
    "wof:name":"Loenen",
    "wof:placetype":"locality"
},
  "geometry": {"coordinates":[5.775,51.8875],"type":"Point"}
}