{
  "type": "Feature",
  "properties": {
    "gn:admin1_code":"3.0",
    "gn:admin2_code":"1734.0",
    "gn:asciiname":"Aam",
    "gn:country_code":"NL",
    "gn:dem":8,
    "gn:feature_class":"P",
    "gn:feature_code":"PPL",
    "gn:name":"Aam",
    "gn:population":0,
    "gn:timezone":"Europe/Amsterdam",
    "iso:country":"NL",
    "wof:name":"Aam",
    "wof:placetype":"locality"
},
  "geometry": {"coordinates":[5.86667,51.915],"type":"Point"}
}