{
  "type": "Feature",
  "properties": {
    "gn:admin1_code":"6.0",
    "gn:admin2_code":"0858",
    "gn:asciiname":"Voorste Brug",
    "gn:country_code":"NL",
    "gn:dem":31,
    "gn:feature_class":"P",
    "gn:feature_code":"PPL",
    "gn:name":"Voorste Brug",
    "gn:population":0,
    "gn:timezone":"Europe/Amsterdam",
    "iso:country":"NL",
    "wof:name":"Voorste Brug",
    "wof:placetype":"locality"
},
  "geometry": {"coordinates":[5.42639,51.28417],"type":"Point"}
}