{
  "type": "Feature",
  "properties": {
    "gn:admin1_code":"3.0",
    "gn:admin2_code":"214.0",
    "gn:asciiname":"Bontemorgen",
    "gn:country_code":"NL",
    "gn:dem":5,
    "gn:feature_class":"P",
    "gn:feature_code":"PPL",
    "gn:name":"Bontemorgen",
    "gn:population":0,
    "gn:timezone":"Europe/Amsterdam",
    "iso:country":"NL",
    "wof:name":"Bontemorgen",
    "wof:placetype":"locality"
},
  "geometry": {"coordinates":[5.52083,51.96333],"type":"Point"}
}