{
  "type": "Feature",
  "properties": {
    "gn:admin1_code":"6.0",
    "gn:admin2_code":"0784",
    "gn:asciiname":"Nerhoven",
    "gn:country_code":"NL",
    "gn:dem":14,
    "gn:feature_class":"P",
    "gn:feature_code":"PPL",
    "gn:name":"Nerhoven",
    "gn:population":0,
    "gn:timezone":"Europe/Amsterdam",
    "iso:country":"NL",
    "wof:name":"Nerhoven",
    "wof:placetype":"locality"
},
  "geometry": {"coordinates":[4.94861,51.55333],"type":"Point"}
}