{
  "type": "Feature",
  "properties": {
    "gn:admin1_code":"6.0",
    "gn:admin2_code":"1702.0",
    "gn:asciiname":"Den Hoek",
    "gn:country_code":"NL",
    "gn:dem":17,
    "gn:feature_class":"P",
    "gn:feature_code":"PPL",
    "gn:name":"Den Hoek",
    "gn:population":0,
    "gn:timezone":"Europe/Amsterdam",
    "iso:country":"NL",
    "wof:name":"Den Hoek",
    "wof:placetype":"locality"
},
  "geometry": {"coordinates":[5.88611,51.6175],"type":"Point"}
}