{
  "type": "Feature",
  "properties": {
    "gn:admin1_code":"3.0",
    "gn:admin2_code":"668.0",
    "gn:asciiname":"De Tuut",
    "gn:country_code":"NL",
    "gn:dem":7,
    "gn:feature_class":"P",
    "gn:feature_code":"PPL",
    "gn:name":"De Tuut",
    "gn:population":0,
    "gn:timezone":"Europe/Amsterdam",
    "iso:country":"NL",
    "wof:name":"De Tuut",
    "wof:placetype":"locality"
},
  "geometry": {"coordinates":[5.59722,51.83417],"type":"Point"}
}