{
  "type": "Feature",
  "properties": {
    "gn:admin1_code":"10.0",
    "gn:admin2_code":"0664",
    "gn:asciiname":"Planketent",
    "gn:country_code":"NL",
    "gn:dem":-1,
    "gn:feature_class":"P",
    "gn:feature_code":"PPL",
    "gn:name":"Planketent",
    "gn:population":0,
    "gn:timezone":"Europe/Amsterdam",
    "iso:country":"NL",
    "wof:name":"Planketent",
    "wof:placetype":"locality"
},
  "geometry": {"coordinates":[3.84167,51.5075],"type":"Point"}
}