{
  "type": "Feature",
  "properties": {
    "gn:admin1_code":"2.0",
    "gn:admin2_code":"0074",
    "gn:asciiname":"Sijthuizen",
    "gn:cc2":"NL",
    "gn:country_code":"NL",
    "gn:dem":-1,
    "gn:feature_class":"P",
    "gn:feature_code":"PPL",
    "gn:name":"Sijthuizen",
    "gn:population":0,
    "gn:timezone":"Europe/Amsterdam",
    "iso:country":"NL",
    "name:fry_x_preferred":[
        "Sythuzen"
    ],
    "name:nld_x_preferred":[
        "Sijthuizen"
    ],
    "name:nld_x_variant":[
        "Sythuizen"
    ],
    "wof:name":"Sijthuizen",
    "wof:placetype":"locality"
},
  "geometry": {"coordinates":[5.85,53.03333000000001],"type":"Point"}
}