{
  "type": "Feature",
  "properties": {
    "gn:admin1_code":"3.0",
    "gn:admin2_code":"0252",
    "gn:asciiname":"Schoonenburg",
    "gn:cc2":"NL",
    "gn:country_code":"NL",
    "gn:dem":9,
    "gn:feature_class":"P",
    "gn:feature_code":"PPL",
    "gn:name":"Schoonenburg",
    "gn:population":0,
    "gn:timezone":"Europe/Amsterdam",
    "iso:country":"NL",
    "name:und_x_variant":[
        "Schoonenberg"
    ],
    "wof:name":"Schoonenburg",
    "wof:placetype":"locality"
},
  "geometry": {"coordinates":[5.775,51.7675],"type":"Point"}
}