{
  "type": "Feature",
  "properties": {
    "gn:admin1_code":"10.0",
    "gn:admin2_code":"717.0",
    "gn:asciiname":"De Zandput",
    "gn:country_code":"NL",
    "gn:dem":0,
    "gn:feature_class":"P",
    "gn:feature_code":"PPL",
    "gn:name":"De Zandput",
    "gn:population":0,
    "gn:timezone":"Europe/Amsterdam",
    "iso:country":"NL",
    "wof:name":"De Zandput",
    "wof:placetype":"locality"
},
  "geometry": {"coordinates":[3.47241,51.51229],"type":"Point"}
}