{
  "type": "Feature",
  "properties": {
    "gn:admin1_code":"3.0",
    "gn:admin2_code":"668.0",
    "gn:asciiname":"Blauwesluis",
    "gn:country_code":"NL",
    "gn:dem":6,
    "gn:feature_class":"P",
    "gn:feature_code":"PPL",
    "gn:name":"Blauwesluis",
    "gn:population":0,
    "gn:timezone":"Europe/Amsterdam",
    "iso:country":"NL",
    "wof:name":"Blauwesluis",
    "wof:placetype":"locality"
},
  "geometry": {"coordinates":[5.55139,51.84083],"type":"Point"}
}