{
  "type": "Feature",
  "properties": {
    "gn:admin1_code":"5.0",
    "gn:admin2_code":"988.0",
    "gn:asciiname":"Rietbroek",
    "gn:cc2":"NL,BE",
    "gn:country_code":"NL",
    "gn:dem":32,
    "gn:feature_class":"P",
    "gn:feature_code":"PPL",
    "gn:name":"Rietbroek",
    "gn:population":0,
    "gn:timezone":"Europe/Amsterdam",
    "iso:country":"NL",
    "wof:name":"Rietbroek",
    "wof:placetype":"locality"
},
  "geometry": {"coordinates":[5.73472,51.19083],"type":"Point"}
}