{
  "type": "Feature",
  "properties": {
    "gn:admin1_code":"6.0",
    "gn:admin2_code":"1674.0",
    "gn:asciiname":"De Rotting",
    "gn:country_code":"NL",
    "gn:dem":1,
    "gn:feature_class":"P",
    "gn:feature_code":"PPL",
    "gn:name":"De Rotting",
    "gn:population":0,
    "gn:timezone":"Europe/Amsterdam",
    "iso:country":"NL",
    "wof:name":"De Rotting",
    "wof:placetype":"locality"
},
  "geometry": {"coordinates":[4.37222,51.535],"type":"Point"}
}