{
  "type": "Feature",
  "properties": {
    "gn:admin1_code":"6.0",
    "gn:admin2_code":"777.0",
    "gn:asciiname":"Brakkenstraat",
    "gn:country_code":"NL",
    "gn:dem":7,
    "gn:feature_class":"P",
    "gn:feature_code":"PPL",
    "gn:name":"Brakkenstraat",
    "gn:population":0,
    "gn:timezone":"Europe/Amsterdam",
    "iso:country":"NL",
    "wof:name":"Brakkenstraat",
    "wof:placetype":"locality"
},
  "geometry": {"coordinates":[4.65597,51.55066],"type":"Point"}
}