{
  "type": "Feature",
  "properties": {
    "gn:admin1_code":"6.0",
    "gn:admin2_code":"1652",
    "gn:asciiname":"Klef",
    "gn:country_code":"NL",
    "gn:dem":28,
    "gn:feature_class":"P",
    "gn:feature_code":"PPL",
    "gn:name":"Klef",
    "gn:population":0,
    "gn:timezone":"Europe/Amsterdam",
    "iso:country":"NL",
    "wof:name":"Klef",
    "wof:placetype":"locality"
},
  "geometry": {"coordinates":[5.79861,51.51167],"type":"Point"}
}