{
  "type": "Feature",
  "properties": {
    "gn:admin1_code":"2.0",
    "gn:admin2_code":"1900",
    "gn:asciiname":"Vierhuizen",
    "gn:country_code":"NL",
    "gn:dem":1,
    "gn:feature_class":"P",
    "gn:feature_code":"PPL",
    "gn:name":"Vierhuizen",
    "gn:population":0,
    "gn:timezone":"Europe/Amsterdam",
    "iso:country":"NL",
    "wof:name":"Vierhuizen",
    "wof:placetype":"locality"
},
  "geometry": {"coordinates":[5.45332,53.04396],"type":"Point"}
}