{
  "type": "Feature",
  "properties": {
    "gn:admin1_code":"15.0",
    "gn:admin2_code":"163.0",
    "gn:asciiname":"Egede",
    "gn:country_code":"NL",
    "gn:dem":6,
    "gn:feature_class":"P",
    "gn:feature_code":"PPL",
    "gn:name":"Egede",
    "gn:population":0,
    "gn:timezone":"Europe/Amsterdam",
    "iso:country":"NL",
    "name:nld_x_preferred":[
        "Egede"
    ],
    "wof:name":"Egede",
    "wof:placetype":"locality"
},
  "geometry": {"coordinates":[6.45278,52.44083000000001],"type":"Point"}
}