{
  "type": "Feature",
  "properties": {
    "gn:admin1_code":"6.0",
    "gn:admin2_code":"1948.0",
    "gn:asciiname":"Everse",
    "gn:country_code":"NL",
    "gn:dem":10,
    "gn:feature_class":"P",
    "gn:feature_code":"PPL",
    "gn:name":"Everse",
    "gn:population":0,
    "gn:timezone":"Europe/Amsterdam",
    "iso:country":"NL",
    "wof:name":"Everse",
    "wof:placetype":"locality"
},
  "geometry": {"coordinates":[5.4875,51.57167000000001],"type":"Point"}
}