{
  "type": "Feature",
  "properties": {
    "gn:admin1_code":"6.0",
    "gn:admin2_code":"755.0",
    "gn:asciiname":"Burgt",
    "gn:country_code":"NL",
    "gn:dem":20,
    "gn:feature_class":"P",
    "gn:feature_code":"PPL",
    "gn:name":"Burgt",
    "gn:population":0,
    "gn:timezone":"Europe/Amsterdam",
    "iso:country":"NL",
    "wof:name":"Burgt",
    "wof:placetype":"locality"
},
  "geometry": {"coordinates":[5.68056,51.6075],"type":"Point"}
}