{
  "type": "Feature",
  "properties": {
    "gn:admin1_code":"9.0",
    "gn:admin2_code":"0344",
    "gn:asciiname":"Ockhuizen",
    "gn:country_code":"NL",
    "gn:dem":4,
    "gn:feature_class":"P",
    "gn:feature_code":"PPL",
    "gn:name":"Ockhuizen",
    "gn:population":0,
    "gn:timezone":"Europe/Amsterdam",
    "iso:country":"NL",
    "name:fas_x_preferred":[
        "\u0627\u06a9\u200c\u0647\u0627\u06cc\u0632\u0646"
    ],
    "name:nld_x_preferred":[
        "Ockhuizen"
    ],
    "name:por_x_preferred":[
        "Ockhuizen"
    ],
    "wof:name":"Ockhuizen",
    "wof:placetype":"locality"
},
  "geometry": {"coordinates":[4.99722,52.12833],"type":"Point"}
}