{
  "type": "Feature",
  "properties": {
    "gn:admin1_code":"9.0",
    "gn:admin2_code":"0344",
    "gn:asciiname":"Ockhuizen",
    "gn:country_code":"NL",
    "gn:dem":4,
    "gn:feature_class":"P",
    "gn:feature_code":"PPL",
    "gn:name":"Ockhuizen",
    "gn:population":0,
    "gn:timezone":"Europe/Amsterdam",
    "iso:country":"NL",
    "wof:name":"Ockhuizen",
    "wof:placetype":"locality"
},
  "geometry": {"coordinates":[4.99722,52.12833],"type":"Point"}
}