{
  "type": "Feature",
  "properties": {
    "gn:admin1_code":"2.0",
    "gn:admin2_code":"0074",
    "gn:asciiname":"Spitsendijk",
    "gn:country_code":"NL",
    "gn:dem":2,
    "gn:feature_class":"P",
    "gn:feature_code":"PPL",
    "gn:name":"Spitsendijk",
    "gn:population":0,
    "gn:timezone":"Europe/Amsterdam",
    "iso:country":"NL",
    "wof:name":"Spitsendijk",
    "wof:placetype":"locality"
},
  "geometry": {"coordinates":[5.88674,52.99534],"type":"Point"}
}