{
  "type": "Feature",
  "properties": {
    "gn:admin1_code":"6.0",
    "gn:admin2_code":"0748",
    "gn:asciiname":"Spinolaberg",
    "gn:country_code":"NL",
    "gn:dem":13,
    "gn:feature_class":"P",
    "gn:feature_code":"PPL",
    "gn:name":"Spinolaberg",
    "gn:population":0,
    "gn:timezone":"Europe/Amsterdam",
    "iso:country":"NL",
    "wof:name":"Spinolaberg",
    "wof:placetype":"locality"
},
  "geometry": {"coordinates":[4.26944,51.51417],"type":"Point"}
}