{
  "type": "Feature",
  "properties": {
    "gn:admin1_code":"6.0",
    "gn:admin2_code":"0748",
    "gn:asciiname":"Kijkuit",
    "gn:country_code":"NL",
    "gn:dem":4,
    "gn:feature_class":"P",
    "gn:feature_code":"PPL",
    "gn:name":"Kijkuit",
    "gn:population":0,
    "gn:timezone":"Europe/Amsterdam",
    "iso:country":"NL",
    "wof:name":"Kijkuit",
    "wof:placetype":"locality"
},
  "geometry": {"coordinates":[4.25833,51.53917],"type":"Point"}
}