{
  "type": "Feature",
  "properties": {
    "gn:admin1_code":"6.0",
    "gn:admin2_code":"757.0",
    "gn:asciiname":"Den Berg",
    "gn:country_code":"NL",
    "gn:dem":9,
    "gn:feature_class":"P",
    "gn:feature_code":"PPL",
    "gn:name":"Den Berg",
    "gn:population":0,
    "gn:timezone":"Europe/Amsterdam",
    "iso:country":"NL",
    "wof:name":"Den Berg",
    "wof:placetype":"locality"
},
  "geometry": {"coordinates":[5.36541,51.57614],"type":"Point"}
}