{
  "type": "Feature",
  "properties": {
    "gn:admin1_code":"3.0",
    "gn:admin2_code":"273.0",
    "gn:asciiname":"Halvinkhuizen",
    "gn:country_code":"NL",
    "gn:dem":12,
    "gn:feature_class":"P",
    "gn:feature_code":"PPL",
    "gn:name":"Halvinkhuizen",
    "gn:population":0,
    "gn:timezone":"Europe/Amsterdam",
    "iso:country":"NL",
    "wof:name":"Halvinkhuizen",
    "wof:placetype":"locality"
},
  "geometry": {"coordinates":[5.58889,52.24583],"type":"Point"}
}