{
  "type": "Feature",
  "properties": {
    "gn:admin1_code":"5.0",
    "gn:admin2_code":"0951",
    "gn:asciiname":"Reuken",
    "gn:country_code":"NL",
    "gn:dem":80,
    "gn:feature_class":"P",
    "gn:feature_code":"PPL",
    "gn:name":"Reuken",
    "gn:population":0,
    "gn:timezone":"Europe/Amsterdam",
    "iso:country":"NL",
    "name:und_x_variant":[
        "G'n Reuken"
    ],
    "wof:name":"Reuken",
    "wof:placetype":"locality"
},
  "geometry": {"coordinates":[5.89258,50.91518],"type":"Point"}
}