{
  "type": "Feature",
  "properties": {
    "gn:admin1_code":"1.0",
    "gn:admin2_code":"0109",
    "gn:asciiname":"Vlieghuis",
    "gn:country_code":"NL",
    "gn:dem":12,
    "gn:feature_class":"P",
    "gn:feature_code":"PPL",
    "gn:name":"Vlieghuis",
    "gn:population":0,
    "gn:timezone":"Europe/Amsterdam",
    "iso:country":"NL",
    "name:fas_x_preferred":[
        "\u0641\u0644\u06cc\u062e\u200c\u0647\u0627\u06cc\u0633"
    ],
    "name:nld_x_preferred":[
        "Vlieghuis"
    ],
    "wof:name":"Vlieghuis",
    "wof:placetype":"locality"
},
  "geometry": {"coordinates":[6.8375,52.65833000000001],"type":"Point"}
}