{
  "type": "Feature",
  "properties": {
    "gn:admin1_code":"6.0",
    "gn:admin2_code":"0743",
    "gn:asciiname":"Ommelschebosch",
    "gn:cc2":"NL",
    "gn:country_code":"NL",
    "gn:dem":23,
    "gn:feature_class":"P",
    "gn:feature_code":"PPLL",
    "gn:name":"Ommelschebosch",
    "gn:population":0,
    "gn:timezone":"Europe/Amsterdam",
    "iso:country":"NL",
    "name:und_x_variant":[
        "Ommelse Bosch"
    ],
    "wof:name":"Ommelschebosch",
    "wof:placetype":"locality"
},
  "geometry": {"coordinates":[5.75031,51.42905],"type":"Point"}
}