{
  "type": "Feature",
  "properties": {
    "gn:admin1_code":"6.0",
    "gn:admin2_code":"0847",
    "gn:asciiname":"Moorsel",
    "gn:country_code":"NL",
    "gn:dem":23,
    "gn:feature_class":"P",
    "gn:feature_code":"PPL",
    "gn:name":"Moorsel",
    "gn:population":0,
    "gn:timezone":"Europe/Amsterdam",
    "iso:country":"NL",
    "name:ceb_x_preferred":[
        "Moorsel"
    ],
    "name:deu_x_preferred":[
        "Aalst#Moorsel"
    ],
    "name:fas_x_preferred":[
        "\u0645\u0648\u0631\u0633\u0644"
    ],
    "name:fra_x_preferred":[
        "Moorsel"
    ],
    "name:hun_x_preferred":[
        "Moorsel"
    ],
    "name:ita_x_preferred":[
        "Moorsel"
    ],
    "name:nld_x_preferred":[
        "Moorsel"
    ],
    "name:swe_x_preferred":[
        "Moorsel"
    ],
    "wof:name":"Moorsel",
    "wof:placetype":"locality"
},
  "geometry": {"coordinates":[5.65278,51.415],"type":"Point"}
}