{
  "type": "Feature",
  "properties": {
    "gn:admin1_code":"6.0",
    "gn:admin2_code":"0847",
    "gn:asciiname":"Moorsel",
    "gn:country_code":"NL",
    "gn:dem":23,
    "gn:feature_class":"P",
    "gn:feature_code":"PPL",
    "gn:name":"Moorsel",
    "gn:population":0,
    "gn:timezone":"Europe/Amsterdam",
    "iso:country":"NL",
    "wof:name":"Moorsel",
    "wof:placetype":"locality"
},
  "geometry": {"coordinates":[5.65278,51.415],"type":"Point"}
}