{
  "type": "Feature",
  "properties": {
    "gn:admin1_code":"6.0",
    "gn:admin2_code":"0855",
    "gn:asciiname":"Schoorstraat",
    "gn:country_code":"NL",
    "gn:dem":11,
    "gn:feature_class":"P",
    "gn:feature_code":"PPL",
    "gn:name":"Schoorstraat",
    "gn:population":0,
    "gn:timezone":"Europe/Amsterdam",
    "iso:country":"NL",
    "wof:name":"Schoorstraat",
    "wof:placetype":"locality"
},
  "geometry": {"coordinates":[5.11806,51.62667],"type":"Point"}
}