{
  "type": "Feature",
  "properties": {
    "gn:admin1_code":"6.0",
    "gn:admin2_code":"0845",
    "gn:asciiname":"Ruimel",
    "gn:country_code":"NL",
    "gn:dem":4,
    "gn:feature_class":"P",
    "gn:feature_code":"PPL",
    "gn:name":"Ruimel",
    "gn:population":0,
    "gn:timezone":"Europe/Amsterdam",
    "iso:country":"NL",
    "wof:name":"Ruimel",
    "wof:placetype":"locality"
},
  "geometry": {"coordinates":[5.34444,51.65083],"type":"Point"}
}