{
  "type": "Feature",
  "properties": {
    "gn:admin1_code":"7.0",
    "gn:admin2_code":"0498",
    "gn:asciiname":"Oostergouw",
    "gn:country_code":"NL",
    "gn:dem":-1,
    "gn:feature_class":"P",
    "gn:feature_code":"PPL",
    "gn:name":"Oostergouw",
    "gn:population":0,
    "gn:timezone":"Europe/Amsterdam",
    "iso:country":"NL",
    "wof:name":"Oostergouw",
    "wof:placetype":"locality"
},
  "geometry": {"coordinates":[5.23889,52.67833],"type":"Point"}
}