{
  "type": "Feature",
  "properties": {
    "gn:admin1_code":"5.0",
    "gn:admin2_code":"0917",
    "gn:asciiname":"Smitzerveld",
    "gn:country_code":"NL",
    "gn:dem":83,
    "gn:feature_class":"P",
    "gn:feature_code":"PPL",
    "gn:name":"Smitzerveld",
    "gn:population":0,
    "gn:timezone":"Europe/Amsterdam",
    "iso:country":"NL",
    "wof:name":"Smitzerveld",
    "wof:placetype":"locality"
},
  "geometry": {"coordinates":[5.95,50.91667],"type":"Point"}
}