{
  "type": "Feature",
  "properties": {
    "gn:admin1_code":"3.0",
    "gn:admin2_code":"1876.0",
    "gn:asciiname":"Bakermark",
    "gn:country_code":"NL",
    "gn:dem":7,
    "gn:feature_class":"P",
    "gn:feature_code":"PPL",
    "gn:name":"Bakermark",
    "gn:population":0,
    "gn:timezone":"Europe/Amsterdam",
    "iso:country":"NL",
    "wof:name":"Bakermark",
    "wof:placetype":"locality"
},
  "geometry": {"coordinates":[6.23564,52.06409],"type":"Point"}
}