{
  "type": "Feature",
  "properties": {
    "gn:admin1_code":"6.0",
    "gn:admin2_code":"1674.0",
    "gn:asciiname":"Hollandsdiep",
    "gn:cc2":"NL,BE",
    "gn:country_code":"NL",
    "gn:dem":12,
    "gn:feature_class":"P",
    "gn:feature_code":"PPL",
    "gn:name":"Hollandsdiep",
    "gn:population":0,
    "gn:timezone":"Europe/Amsterdam",
    "iso:country":"NL",
    "wof:name":"Hollandsdiep",
    "wof:placetype":"locality"
},
  "geometry": {"coordinates":[4.45278,51.47167],"type":"Point"}
}