{
  "type": "Feature",
  "properties": {
    "gn:admin1_code":"4.0",
    "gn:admin2_code":"56.0",
    "gn:asciiname":"De Ruigewaard",
    "gn:country_code":"NL",
    "gn:dem":0,
    "gn:feature_class":"P",
    "gn:feature_code":"PPL",
    "gn:name":"De Ruigewaard",
    "gn:population":0,
    "gn:timezone":"Europe/Amsterdam",
    "iso:country":"NL",
    "wof:name":"De Ruigewaard",
    "wof:placetype":"locality"
},
  "geometry": {"coordinates":[6.3125,53.30167],"type":"Point"}
}