{
  "type": "Feature",
  "properties": {
    "gn:admin1_code":"4.0",
    "gn:admin2_code":"1895.0",
    "gn:asciiname":"Beersterhoogen",
    "gn:cc2":"NL",
    "gn:country_code":"NL",
    "gn:dem":0,
    "gn:feature_class":"P",
    "gn:feature_code":"PPL",
    "gn:name":"Beersterhoogen",
    "gn:population":0,
    "gn:timezone":"Europe/Amsterdam",
    "iso:country":"NL",
    "name:und_x_variant":[
        "Beersterhogen",
        "Beersterhoogen"
    ],
    "wof:name":"Beersterhoogen",
    "wof:placetype":"locality"
},
  "geometry": {"coordinates":[7.13333,53.18333000000001],"type":"Point"}
}