{
  "type": "Feature",
  "properties": {
    "gn:admin1_code":"10.0",
    "gn:admin2_code":"1714",
    "gn:asciiname":"Kruisdijk",
    "gn:country_code":"NL",
    "gn:dem":1,
    "gn:feature_class":"P",
    "gn:feature_code":"PPL",
    "gn:name":"Kruisdijk",
    "gn:population":0,
    "gn:timezone":"Europe/Amsterdam",
    "iso:country":"NL",
    "wof:name":"Kruisdijk",
    "wof:placetype":"locality"
},
  "geometry": {"coordinates":[3.54722,51.3775],"type":"Point"}
}