{
  "type": "Feature",
  "properties": {
    "gn:admin1_code":"6.0",
    "gn:admin2_code":"855.0",
    "gn:asciiname":"t Hoekske",
    "gn:country_code":"NL",
    "gn:dem":11,
    "gn:feature_class":"P",
    "gn:feature_code":"PPL",
    "gn:name":"t Hoekske",
    "gn:population":0,
    "gn:timezone":"Europe/Amsterdam",
    "iso:country":"NL",
    "wof:name":"t Hoekske",
    "wof:placetype":"locality"
},
  "geometry": {"coordinates":[5.13333,51.595],"type":"Point"}
}