{
  "type": "Feature",
  "properties": {
    "gn:admin1_code":"11.0",
    "gn:admin2_code":"0617",
    "gn:asciiname":"Keizersdijk",
    "gn:country_code":"NL",
    "gn:dem":-3,
    "gn:feature_class":"P",
    "gn:feature_code":"PPL",
    "gn:name":"Keizersdijk",
    "gn:population":0,
    "gn:timezone":"Europe/Amsterdam",
    "iso:country":"NL",
    "name:fas_x_preferred":[
        "\u06a9\u06cc\u0632\u0631\u0633\u200c\u062f\u06cc\u06a9"
    ],
    "name:nld_x_preferred":[
        "Keizersdijk"
    ],
    "wof:name":"Keizersdijk",
    "wof:placetype":"locality"
},
  "geometry": {"coordinates":[4.54722,51.75667],"type":"Point"}
}