{
  "type": "Feature",
  "properties": {
    "gn:admin1_code":"6.0",
    "gn:admin2_code":"1659.0",
    "gn:asciiname":"Aarle",
    "gn:country_code":"NL",
    "gn:dem":18,
    "gn:feature_class":"P",
    "gn:feature_code":"PPL",
    "gn:name":"Aarle",
    "gn:population":0,
    "gn:timezone":"Europe/Amsterdam",
    "iso:country":"NL",
    "wof:name":"Aarle",
    "wof:placetype":"locality"
},
  "geometry": {"coordinates":[5.63221,51.5096],"type":"Point"}
}