{
  "type": "Feature",
  "properties": {
    "gn:admin1_code":"10.0",
    "gn:admin2_code":"1714",
    "gn:asciiname":"Koninginnehaven",
    "gn:country_code":"NL",
    "gn:dem":0,
    "gn:feature_class":"P",
    "gn:feature_code":"PPL",
    "gn:name":"Koninginnehaven",
    "gn:population":0,
    "gn:timezone":"Europe/Amsterdam",
    "iso:country":"NL",
    "wof:name":"Koninginnehaven",
    "wof:placetype":"locality"
},
  "geometry": {"coordinates":[3.70833,51.315],"type":"Point"}
}