{
  "type": "Feature",
  "properties": {
    "gn:admin1_code":"4.0",
    "gn:admin2_code":"1895",
    "gn:asciiname":"Sint Vitusholt",
    "gn:country_code":"NL",
    "gn:dem":-1,
    "gn:feature_class":"P",
    "gn:feature_code":"PPL",
    "gn:name":"Sint Vitusholt",
    "gn:population":0,
    "gn:timezone":"Europe/Amsterdam",
    "iso:country":"NL",
    "wof:name":"Sint Vitusholt",
    "wof:placetype":"locality"
},
  "geometry": {"coordinates":[7.02083,53.14167],"type":"Point"}
}