{
  "type": "Feature",
  "properties": {
    "gn:admin1_code":"6.0",
    "gn:admin2_code":"0865",
    "gn:asciiname":"Vlasmeer",
    "gn:country_code":"NL",
    "gn:dem":7,
    "gn:feature_class":"P",
    "gn:feature_code":"PPL",
    "gn:name":"Vlasmeer",
    "gn:population":0,
    "gn:timezone":"Europe/Amsterdam",
    "iso:country":"NL",
    "wof:name":"Vlasmeer",
    "wof:placetype":"locality"
},
  "geometry": {"coordinates":[5.29659,51.64911],"type":"Point"}
}