{
  "type": "Feature",
  "properties": {
    "gn:admin1_code":"6.0",
    "gn:admin2_code":"0762",
    "gn:asciiname":"Hoogebrug",
    "gn:cc2":"NL",
    "gn:country_code":"NL",
    "gn:dem":30,
    "gn:feature_class":"P",
    "gn:feature_code":"PPLL",
    "gn:name":"Hoogebrug",
    "gn:population":0,
    "gn:timezone":"Europe/Amsterdam",
    "iso:country":"NL",
    "name:und_x_variant":[
        "Hoge Brug"
    ],
    "wof:name":"Hoogebrug",
    "wof:placetype":"locality"
},
  "geometry": {"coordinates":[5.8773,51.39672],"type":"Point"}
}