{
  "type": "Feature",
  "properties": {
    "gn:admin1_code":"3.0",
    "gn:admin2_code":"0232",
    "gn:asciiname":"Wijnbergen",
    "gn:country_code":"NL",
    "gn:dem":4,
    "gn:feature_class":"P",
    "gn:feature_code":"PPL",
    "gn:name":"Wijnbergen",
    "gn:population":0,
    "gn:timezone":"Europe/Amsterdam",
    "iso:country":"NL",
    "wof:name":"Wijnbergen",
    "wof:placetype":"locality"
},
  "geometry": {"coordinates":[6.01944,52.32167000000001],"type":"Point"}
}