{
  "type": "Feature",
  "properties": {
    "gn:admin1_code":"5.0",
    "gn:admin2_code":"1729.0",
    "gn:asciiname":"Dijk",
    "gn:country_code":"NL",
    "gn:dem":105,
    "gn:feature_class":"P",
    "gn:feature_code":"PPL",
    "gn:name":"Dijk",
    "gn:population":0,
    "gn:timezone":"Europe/Amsterdam",
    "iso:country":"NL",
    "wof:name":"Dijk",
    "wof:placetype":"locality"
},
  "geometry": {"coordinates":[5.91806,50.79333],"type":"Point"}
}