{
  "type": "Feature",
  "properties": {
    "gn:admin1_code":"4.0",
    "gn:admin2_code":"0015",
    "gn:asciiname":"Oosterzand",
    "gn:country_code":"NL",
    "gn:dem":1,
    "gn:feature_class":"P",
    "gn:feature_code":"PPL",
    "gn:name":"Oosterzand",
    "gn:population":0,
    "gn:timezone":"Europe/Amsterdam",
    "iso:country":"NL",
    "wof:name":"Oosterzand",
    "wof:placetype":"locality"
},
  "geometry": {"coordinates":[6.32222,53.23417],"type":"Point"}
}