{
  "type": "Feature",
  "properties": {
    "gn:admin1_code":"10.0",
    "gn:admin2_code":"0716",
    "gn:asciiname":"Strijenham",
    "gn:country_code":"NL",
    "gn:dem":-1,
    "gn:feature_class":"P",
    "gn:feature_code":"PPL",
    "gn:name":"Strijenham",
    "gn:population":0,
    "gn:timezone":"Europe/Amsterdam",
    "iso:country":"NL",
    "wof:name":"Strijenham",
    "wof:placetype":"locality"
},
  "geometry": {"coordinates":[4.15556,51.52417],"type":"Point"}
}