{
  "type": "Feature",
  "properties": {
    "gn:admin1_code":"10.0",
    "gn:admin2_code":"0715",
    "gn:asciiname":"Nieuwemolen",
    "gn:country_code":"NL",
    "gn:dem":3,
    "gn:feature_class":"P",
    "gn:feature_code":"PPL",
    "gn:name":"Nieuwemolen",
    "gn:population":0,
    "gn:timezone":"Europe/Amsterdam",
    "iso:country":"NL",
    "wof:name":"Nieuwemolen",
    "wof:placetype":"locality"
},
  "geometry": {"coordinates":[3.93889,51.24083],"type":"Point"}
}