{
  "type": "Feature",
  "properties": {
    "gn:admin1_code":"3.0",
    "gn:admin2_code":"1509",
    "gn:asciiname":"Wals",
    "gn:country_code":"NL",
    "gn:dem":14,
    "gn:feature_class":"P",
    "gn:feature_code":"PPL",
    "gn:name":"Wals",
    "gn:population":0,
    "gn:timezone":"Europe/Amsterdam",
    "iso:country":"NL",
    "wof:name":"Wals",
    "wof:placetype":"locality"
},
  "geometry": {"coordinates":[6.35,51.86167],"type":"Point"}
}