{
  "type": "Feature",
  "properties": {
    "gn:admin1_code":"11.0",
    "gn:admin2_code":"0597",
    "gn:asciiname":"Zwet",
    "gn:country_code":"NL",
    "gn:dem":-3,
    "gn:feature_class":"P",
    "gn:feature_code":"PPL",
    "gn:name":"Zwet",
    "gn:population":0,
    "gn:timezone":"Europe/Amsterdam",
    "iso:country":"NL",
    "wof:name":"Zwet",
    "wof:placetype":"locality"
},
  "geometry": {"coordinates":[4.55972,51.865],"type":"Point"}
}