{
  "type": "Feature",
  "properties": {
    "gn:admin1_code":"2.0",
    "gn:admin2_code":"1940",
    "gn:asciiname":"Schouw",
    "gn:country_code":"NL",
    "gn:dem":0,
    "gn:feature_class":"P",
    "gn:feature_code":"PPL",
    "gn:name":"Schouw",
    "gn:population":0,
    "gn:timezone":"Europe/Amsterdam",
    "iso:country":"NL",
    "wof:name":"Schouw",
    "wof:placetype":"locality"
},
  "geometry": {"coordinates":[5.52268,52.86618000000001],"type":"Point"}
}