{
  "type": "Feature",
  "properties": {
    "gn:admin1_code":"6.0",
    "gn:admin2_code":"1771",
    "gn:asciiname":"Loeswijk",
    "gn:cc2":"NL",
    "gn:country_code":"NL",
    "gn:dem":20,
    "gn:feature_class":"P",
    "gn:feature_code":"PPL",
    "gn:name":"Loeswijk",
    "gn:population":0,
    "gn:timezone":"Europe/Amsterdam",
    "iso:country":"NL",
    "name:und_x_variant":[
        "Loerwijk"
    ],
    "wof:name":"Loeswijk",
    "wof:placetype":"locality"
},
  "geometry": {"coordinates":[5.63056,51.44333],"type":"Point"}
}