{
  "type": "Feature",
  "properties": {
    "gn:admin1_code":"5.0",
    "gn:admin2_code":"0893",
    "gn:asciiname":"Smal",
    "gn:country_code":"NL",
    "gn:dem":18,
    "gn:feature_class":"P",
    "gn:feature_code":"PPL",
    "gn:name":"Smal",
    "gn:population":0,
    "gn:timezone":"Europe/Amsterdam",
    "iso:country":"NL",
    "wof:name":"Smal",
    "wof:placetype":"locality"
},
  "geometry": {"coordinates":[6.05103,51.61492],"type":"Point"}
}