{
  "type": "Feature",
  "properties": {
    "gn:admin1_code":"9.0",
    "gn:admin2_code":"327.0",
    "gn:asciiname":"Asschat",
    "gn:country_code":"NL",
    "gn:dem":4,
    "gn:feature_class":"P",
    "gn:feature_code":"PPL",
    "gn:name":"Asschat",
    "gn:population":0,
    "gn:timezone":"Europe/Amsterdam",
    "iso:country":"NL",
    "name:fry_x_preferred":[
        "Asschat"
    ],
    "name:nld_x_preferred":[
        "Asschat"
    ],
    "name:und_x_variant":[
        "Aschat",
        "Asschot"
    ],
    "wof:name":"Asschat",
    "wof:placetype":"locality"
},
  "geometry": {"coordinates":[5.45169,52.13135],"type":"Point"}
}