{
  "type": "Feature",
  "properties": {
    "gn:admin1_code":"9.0",
    "gn:admin2_code":"0331",
    "gn:asciiname":"Polsbroekerdam",
    "gn:country_code":"NL",
    "gn:dem":-1,
    "gn:feature_class":"P",
    "gn:feature_code":"PPL",
    "gn:name":"Polsbroekerdam",
    "gn:population":0,
    "gn:timezone":"Europe/Amsterdam",
    "iso:country":"NL",
    "wof:name":"Polsbroekerdam",
    "wof:placetype":"locality"
},
  "geometry": {"coordinates":[4.90278,51.995],"type":"Point"}
}