{
  "type": "Feature",
  "properties": {
    "gn:admin1_code":"6.0",
    "gn:admin2_code":"0874",
    "gn:asciiname":"Rietdijk",
    "gn:country_code":"NL",
    "gn:dem":0,
    "gn:feature_class":"P",
    "gn:feature_code":"PPL",
    "gn:name":"Rietdijk",
    "gn:population":0,
    "gn:timezone":"Europe/Amsterdam",
    "iso:country":"NL",
    "wof:name":"Rietdijk",
    "wof:placetype":"locality"
},
  "geometry": {"coordinates":[5.03526,51.7812],"type":"Point"}
}