{
  "type": "Feature",
  "properties": {
    "gn:admin1_code":"5.0",
    "gn:admin2_code":"957.0",
    "gn:asciiname":"Kapellerlaan",
    "gn:country_code":"NL",
    "gn:dem":27,
    "gn:feature_class":"P",
    "gn:feature_code":"PPL",
    "gn:name":"Kapellerlaan",
    "gn:population":0,
    "gn:timezone":"Europe/Amsterdam",
    "iso:country":"NL",
    "wof:name":"Kapellerlaan",
    "wof:placetype":"locality"
},
  "geometry": {"coordinates":[5.99359,51.18456],"type":"Point"}
}