{
  "type": "Feature",
  "properties": {
    "gn:admin1_code":"6.0",
    "gn:admin2_code":"0798",
    "gn:asciiname":"Hoogeind",
    "gn:country_code":"NL",
    "gn:dem":21,
    "gn:feature_class":"P",
    "gn:feature_code":"PPL",
    "gn:name":"Hoogeind",
    "gn:population":0,
    "gn:timezone":"Europe/Amsterdam",
    "iso:country":"NL",
    "wof:name":"Hoogeind",
    "wof:placetype":"locality"
},
  "geometry": {"coordinates":[5.13611,51.45],"type":"Point"}
}