{
  "type": "Feature",
  "properties": {
    "gn:admin1_code":"9.0",
    "gn:admin2_code":"0335",
    "gn:asciiname":"Mastwijk",
    "gn:country_code":"NL",
    "gn:dem":-1,
    "gn:feature_class":"P",
    "gn:feature_code":"PPL",
    "gn:name":"Mastwijk",
    "gn:population":0,
    "gn:timezone":"Europe/Amsterdam",
    "iso:country":"NL",
    "name:fas_x_preferred":[
        "\u0645\u0627\u0633\u062a\u200c\u0648\u06cc\u06a9"
    ],
    "name:nld_x_preferred":[
        "Mastwijk"
    ],
    "name:por_x_preferred":[
        "Mastwijk"
    ],
    "wof:name":"Mastwijk",
    "wof:placetype":"locality"
},
  "geometry": {"coordinates":[4.95556,52.055],"type":"Point"}
}