{
  "type": "Feature",
  "properties": {
    "gn:admin1_code":"2.0",
    "gn:admin2_code":"1900",
    "gn:asciiname":"Jonkershuizen",
    "gn:country_code":"NL",
    "gn:dem":1,
    "gn:feature_class":"P",
    "gn:feature_code":"PPL",
    "gn:name":"Jonkershuizen",
    "gn:population":0,
    "gn:timezone":"Europe/Amsterdam",
    "iso:country":"NL",
    "wof:name":"Jonkershuizen",
    "wof:placetype":"locality"
},
  "geometry": {"coordinates":[5.50983,53.03361],"type":"Point"}
}