{
  "type": "Feature",
  "properties": {
    "gn:admin1_code":"9.0",
    "gn:admin2_code":"0327",
    "gn:asciiname":"Musschendorp",
    "gn:cc2":"NL",
    "gn:country_code":"NL",
    "gn:dem":3,
    "gn:feature_class":"P",
    "gn:feature_code":"PPL",
    "gn:name":"Musschendorp",
    "gn:population":0,
    "gn:timezone":"Europe/Amsterdam",
    "iso:country":"NL",
    "name:und_x_variant":[
        "Mussendorp"
    ],
    "wof:name":"Musschendorp",
    "wof:placetype":"locality"
},
  "geometry": {"coordinates":[5.45556,52.14667],"type":"Point"}
}