{
  "type": "Feature",
  "properties": {
    "gn:admin1_code":"2.0",
    "gn:admin2_code":"0070",
    "gn:asciiname":"Roptazijl",
    "gn:country_code":"NL",
    "gn:dem":0,
    "gn:feature_class":"P",
    "gn:feature_code":"PPL",
    "gn:name":"Roptazijl",
    "gn:population":0,
    "gn:timezone":"Europe/Amsterdam",
    "iso:country":"NL",
    "name:fry_x_preferred":[
        "Roptasyl"
    ],
    "name:nld_x_preferred":[
        "Roptazijl"
    ],
    "wof:name":"Roptazijl",
    "wof:placetype":"locality"
},
  "geometry": {"coordinates":[5.44561,53.20686],"type":"Point"}
}