{
  "type": "Feature",
  "properties": {
    "gn:admin1_code":"5.0",
    "gn:admin2_code":"1883.0",
    "gn:asciiname":"Schipperskerk",
    "gn:country_code":"NL",
    "gn:dem":31,
    "gn:feature_class":"P",
    "gn:feature_code":"PPL",
    "gn:name":"Schipperskerk",
    "gn:population":0,
    "gn:timezone":"Europe/Amsterdam",
    "iso:country":"NL",
    "wof:name":"Schipperskerk",
    "wof:placetype":"locality"
},
  "geometry": {"coordinates":[5.79028,51.04583],"type":"Point"}
}