{
  "type": "Feature",
  "properties": {
    "gn:admin1_code":"6.0",
    "gn:admin2_code":"855.0",
    "gn:asciiname":"Loonse Hoek",
    "gn:country_code":"NL",
    "gn:dem":7,
    "gn:feature_class":"P",
    "gn:feature_code":"PPL",
    "gn:name":"Loonse Hoek",
    "gn:population":0,
    "gn:timezone":"Europe/Amsterdam",
    "iso:country":"NL",
    "wof:name":"Loonse Hoek",
    "wof:placetype":"locality"
},
  "geometry": {"coordinates":[5.10694,51.63083],"type":"Point"}
}