{
  "type": "Feature",
  "properties": {
    "gn:admin1_code":"6.0",
    "gn:admin2_code":"0744",
    "gn:asciiname":"Keizershoek",
    "gn:country_code":"NL",
    "gn:dem":26,
    "gn:feature_class":"P",
    "gn:feature_code":"PPL",
    "gn:name":"Keizershoek",
    "gn:population":0,
    "gn:timezone":"Europe/Amsterdam",
    "iso:country":"NL",
    "wof:name":"Keizershoek",
    "wof:placetype":"locality"
},
  "geometry": {"coordinates":[4.95417,51.4425],"type":"Point"}
}