{
  "type": "Feature",
  "properties": {
    "gn:admin1_code":"4.0",
    "gn:admin2_code":"1663.0",
    "gn:asciiname":"Grijssloot",
    "gn:country_code":"NL",
    "gn:dem":1,
    "gn:feature_class":"P",
    "gn:feature_code":"PPL",
    "gn:name":"Grijssloot",
    "gn:population":0,
    "gn:timezone":"Europe/Amsterdam",
    "iso:country":"NL",
    "wof:name":"Grijssloot",
    "wof:placetype":"locality"
},
  "geometry": {"coordinates":[6.38333,53.37416999999999],"type":"Point"}
}