{
  "type": "Feature",
  "properties": {
    "gn:admin1_code":"2.0",
    "gn:admin2_code":"1722.0",
    "gn:asciiname":"Boteburen",
    "gn:country_code":"NL",
    "gn:dem":-1,
    "gn:feature_class":"P",
    "gn:feature_code":"PPL",
    "gn:name":"Boteburen",
    "gn:population":0,
    "gn:timezone":"Europe/Amsterdam",
    "iso:country":"NL",
    "wof:name":"Boteburen",
    "wof:placetype":"locality"
},
  "geometry": {"coordinates":[5.85,53.35],"type":"Point"}
}