{
  "type": "Feature",
  "properties": {
    "gn:admin1_code":"6.0",
    "gn:admin2_code":"0762",
    "gn:asciiname":"Schelm",
    "gn:country_code":"NL",
    "gn:dem":31,
    "gn:feature_class":"P",
    "gn:feature_code":"PPL",
    "gn:name":"Schelm",
    "gn:population":0,
    "gn:timezone":"Europe/Amsterdam",
    "iso:country":"NL",
    "wof:name":"Schelm",
    "wof:placetype":"locality"
},
  "geometry": {"coordinates":[5.86806,51.36083],"type":"Point"}
}