{
  "type": "Feature",
  "properties": {
    "gn:admin1_code":"6.0",
    "gn:admin2_code":"0788",
    "gn:asciiname":"Molenstraat",
    "gn:country_code":"NL",
    "gn:dem":9,
    "gn:feature_class":"P",
    "gn:feature_code":"PPL",
    "gn:name":"Molenstraat",
    "gn:population":0,
    "gn:timezone":"Europe/Amsterdam",
    "iso:country":"NL",
    "wof:name":"Molenstraat",
    "wof:placetype":"locality"
},
  "geometry": {"coordinates":[5.23889,51.62],"type":"Point"}
}