{
  "type": "Feature",
  "properties": {
    "gn:admin1_code":"5.0",
    "gn:admin2_code":"1507.0",
    "gn:asciiname":"Broek",
    "gn:country_code":"NL",
    "gn:dem":25,
    "gn:feature_class":"P",
    "gn:feature_code":"PPL",
    "gn:name":"Broek",
    "gn:population":0,
    "gn:timezone":"Europe/Amsterdam",
    "iso:country":"NL",
    "name:ceb_x_preferred":[
        "Broek"
    ],
    "name:deu_x_preferred":[
        "Broek"
    ],
    "name:fra_x_preferred":[
        "Broek"
    ],
    "name:nld_x_preferred":[
        "Broek"
    ],
    "wof:name":"Broek",
    "wof:placetype":"locality"
},
  "geometry": {"coordinates":[6.06389,51.44333],"type":"Point"}
}