{
  "type": "Feature",
  "properties": {
    "gn:admin1_code":"6.0",
    "gn:admin2_code":"1948",
    "gn:asciiname":"Morsche Hoef",
    "gn:cc2":"NL",
    "gn:country_code":"NL",
    "gn:dem":12,
    "gn:feature_class":"P",
    "gn:feature_code":"PPL",
    "gn:name":"Morsche Hoef",
    "gn:population":0,
    "gn:timezone":"Europe/Amsterdam",
    "iso:country":"NL",
    "name:und_x_variant":[
        "Moorse Hoef"
    ],
    "wof:name":"Morsche Hoef",
    "wof:placetype":"locality"
},
  "geometry": {"coordinates":[5.61111,51.61],"type":"Point"}
}