{
  "type": "Feature",
  "properties": {
    "gn:admin1_code":"3.0",
    "gn:admin2_code":"304.0",
    "gn:asciiname":"Hattelaar",
    "gn:country_code":"NL",
    "gn:dem":3,
    "gn:feature_class":"P",
    "gn:feature_code":"PPL",
    "gn:name":"Hattelaar",
    "gn:population":0,
    "gn:timezone":"Europe/Amsterdam",
    "iso:country":"NL",
    "wof:name":"Hattelaar",
    "wof:placetype":"locality"
},
  "geometry": {"coordinates":[5.35833,51.84667],"type":"Point"}
}