{
  "type": "Feature",
  "properties": {
    "gn:admin1_code":"10.0",
    "gn:admin2_code":"715.0",
    "gn:asciiname":"Axelsche Sassing",
    "gn:cc2":"NL",
    "gn:country_code":"NL",
    "gn:dem":1,
    "gn:feature_class":"P",
    "gn:feature_code":"PPL",
    "gn:name":"Axelsche Sassing",
    "gn:population":0,
    "gn:timezone":"Europe/Amsterdam",
    "iso:country":"NL",
    "name:und_x_variant":[
        "Sassing",
        "Axels Sassing"
    ],
    "wof:name":"Axelsche Sassing",
    "wof:placetype":"locality"
},
  "geometry": {"coordinates":[3.875,51.27],"type":"Point"}
}