{
  "type": "Feature",
  "properties": {
    "gn:admin1_code":"2.0",
    "gn:admin2_code":"86.0",
    "gn:asciiname":"Allardsoog",
    "gn:cc2":"NL",
    "gn:country_code":"NL",
    "gn:dem":11,
    "gn:feature_class":"P",
    "gn:feature_code":"PPL",
    "gn:name":"Allardsoog",
    "gn:population":0,
    "gn:timezone":"Europe/Amsterdam",
    "iso:country":"NL",
    "name:und_x_variant":[
        "Allartsoog",
        "Allerdsoog"
    ],
    "wof:name":"Allardsoog",
    "wof:placetype":"locality"
},
  "geometry": {"coordinates":[6.29208,53.09454],"type":"Point"}
}