{
  "type": "Feature",
  "properties": {
    "gn:admin1_code":"6.0",
    "gn:admin2_code":"855.0",
    "gn:asciiname":"Brem",
    "gn:country_code":"NL",
    "gn:dem":12,
    "gn:feature_class":"P",
    "gn:feature_code":"PPL",
    "gn:name":"Brem",
    "gn:population":0,
    "gn:timezone":"Europe/Amsterdam",
    "iso:country":"NL",
    "name:fra_x_preferred":[
        "Brem"
    ],
    "name:hun_x_preferred":[
        "Brem"
    ],
    "name:ind_x_preferred":[
        "Brem"
    ],
    "name:jav_x_preferred":[
        "Brem"
    ],
    "name:jpn_x_preferred":[
        "\u30d6\u30eb\u30e0"
    ],
    "name:lit_x_preferred":[
        "Bremas"
    ],
    "name:nld_x_preferred":[
        "Brem"
    ],
    "name:pol_x_preferred":[
        "Brem"
    ],
    "wof:name":"Brem",
    "wof:placetype":"locality"
},
  "geometry": {"coordinates":[5.14722,51.5975],"type":"Point"}
}