{
  "type": "Feature",
  "properties": {
    "gn:admin1_code":"11.0",
    "gn:admin2_code":"0689",
    "gn:asciiname":"Nederslingeland",
    "gn:country_code":"NL",
    "gn:dem":-3,
    "gn:feature_class":"P",
    "gn:feature_code":"PPL",
    "gn:name":"Nederslingeland",
    "gn:population":0,
    "gn:timezone":"Europe/Amsterdam",
    "iso:country":"NL",
    "name:fra_x_preferred":[
        "Nederslingeland"
    ],
    "name:nld_x_preferred":[
        "Nederslingeland"
    ],
    "wof:name":"Nederslingeland",
    "wof:placetype":"locality"
},
  "geometry": {"coordinates":[4.91667,51.86667],"type":"Point"}
}