{
  "type": "Feature",
  "properties": {
    "gn:admin1_code":"15.0",
    "gn:admin2_code":"141.0",
    "gn:asciiname":"De Aa",
    "gn:country_code":"NL",
    "gn:dem":7,
    "gn:feature_class":"P",
    "gn:feature_code":"PPL",
    "gn:name":"De Aa",
    "gn:population":0,
    "gn:timezone":"Europe/Amsterdam",
    "iso:country":"NL",
    "wof:name":"De Aa",
    "wof:placetype":"locality"
},
  "geometry": {"coordinates":[6.66206,52.3832],"type":"Point"}
}