{
  "type": "Feature",
  "properties": {
    "gn:admin1_code":"1.0",
    "gn:admin2_code":"1701.0",
    "gn:asciiname":"Busselte",
    "gn:country_code":"NL",
    "gn:dem":1,
    "gn:feature_class":"P",
    "gn:feature_code":"PPL",
    "gn:name":"Busselte",
    "gn:population":0,
    "gn:timezone":"Europe/Amsterdam",
    "iso:country":"NL",
    "wof:name":"Busselte",
    "wof:placetype":"locality"
},
  "geometry": {"coordinates":[6.19722,52.765],"type":"Point"}
}