{
  "type": "Feature",
  "properties": {
    "gn:admin1_code":"6.0",
    "gn:admin2_code":"1674",
    "gn:asciiname":"Visdonk",
    "gn:country_code":"NL",
    "gn:dem":9,
    "gn:feature_class":"P",
    "gn:feature_code":"PPL",
    "gn:name":"Visdonk",
    "gn:population":0,
    "gn:timezone":"Europe/Amsterdam",
    "iso:country":"NL",
    "wof:name":"Visdonk",
    "wof:placetype":"locality"
},
  "geometry": {"coordinates":[4.48472,51.5025],"type":"Point"}
}