{
  "type": "Feature",
  "properties": {
    "gn:admin1_code":"6.0",
    "gn:admin2_code":"0772",
    "gn:asciiname":"'t Coll",
    "gn:country_code":"NL",
    "gn:dem":15,
    "gn:feature_class":"P",
    "gn:feature_code":"PPL",
    "gn:name":"t Coll",
    "gn:population":0,
    "gn:timezone":"Europe/Amsterdam",
    "iso:country":"NL",
    "wof:name":"'t Coll",
    "wof:placetype":"locality"
},
  "geometry": {"coordinates":[5.54167,51.44583],"type":"Point"}
}