{
  "type": "Feature",
  "properties": {
    "gn:admin1_code":"4.0",
    "gn:admin2_code":"10.0",
    "gn:asciiname":"Grijzemonnikenklooster",
    "gn:country_code":"NL",
    "gn:dem":-3,
    "gn:feature_class":"P",
    "gn:feature_code":"PPL",
    "gn:name":"Grijzemonnikenklooster",
    "gn:population":0,
    "gn:timezone":"Europe/Amsterdam",
    "iso:country":"NL",
    "wof:name":"Grijzemonnikenklooster",
    "wof:placetype":"locality"
},
  "geometry": {"coordinates":[7.01667,53.28333000000001],"type":"Point"}
}