{
  "type": "Feature",
  "properties": {
    "gn:admin1_code":"4.0",
    "gn:admin2_code":"0007",
    "gn:asciiname":"Lutjeloo",
    "gn:cc2":"NL",
    "gn:country_code":"NL",
    "gn:dem":-1,
    "gn:feature_class":"P",
    "gn:feature_code":"PPL",
    "gn:name":"Lutjeloo",
    "gn:population":0,
    "gn:timezone":"Europe/Amsterdam",
    "iso:country":"NL",
    "name:und_x_variant":[
        "Lutjelo"
    ],
    "wof:name":"Lutjeloo",
    "wof:placetype":"locality"
},
  "geometry": {"coordinates":[7.08611,53.09417],"type":"Point"}
}