{
  "type": "Feature",
  "properties": {
    "gn:admin1_code":"3.0",
    "gn:admin2_code":"1509.0",
    "gn:asciiname":"Heuven",
    "gn:country_code":"NL",
    "gn:dem":13,
    "gn:feature_class":"P",
    "gn:feature_code":"PPL",
    "gn:name":"Heuven",
    "gn:population":0,
    "gn:timezone":"Europe/Amsterdam",
    "iso:country":"NL",
    "wof:name":"Heuven",
    "wof:placetype":"locality"
},
  "geometry": {"coordinates":[6.31389,51.92583],"type":"Point"}
}