{
  "type": "Feature",
  "properties": {
    "gn:admin1_code":"6.0",
    "gn:admin2_code":"874.0",
    "gn:asciiname":"Emmikhoven",
    "gn:cc2":"NL",
    "gn:country_code":"NL",
    "gn:dem":-1,
    "gn:feature_class":"P",
    "gn:feature_code":"PPL",
    "gn:name":"Emmikhoven",
    "gn:population":0,
    "gn:timezone":"Europe/Amsterdam",
    "iso:country":"NL",
    "name:nld_x_preferred":[
        "Emmikhoven"
    ],
    "name:und_x_variant":[
        "Emmikhovenschedijk"
    ],
    "wof:name":"Emmikhoven",
    "wof:placetype":"locality"
},
  "geometry": {"coordinates":[4.98333,51.78333],"type":"Point"}
}