{
  "type": "Feature",
  "properties": {
    "gn:admin1_code":"4.0",
    "gn:admin2_code":"1895",
    "gn:asciiname":"Oostwolderhamrik",
    "gn:country_code":"NL",
    "gn:dem":-1,
    "gn:feature_class":"P",
    "gn:feature_code":"PPL",
    "gn:name":"Oostwolderhamrik",
    "gn:population":0,
    "gn:timezone":"Europe/Amsterdam",
    "iso:country":"NL",
    "name:nld_x_preferred":[
        "Oostwolder Hamrik"
    ],
    "wof:name":"Oostwolderhamrik",
    "wof:placetype":"locality"
},
  "geometry": {"coordinates":[7.01667,53.25],"type":"Point"}
}