{
  "type": "Feature",
  "properties": {
    "gn:admin1_code":"6.0",
    "gn:admin2_code":"0873",
    "gn:asciiname":"Overberg",
    "gn:country_code":"NL",
    "gn:dem":19,
    "gn:feature_class":"P",
    "gn:feature_code":"PPL",
    "gn:name":"Overberg",
    "gn:population":0,
    "gn:timezone":"Europe/Amsterdam",
    "iso:country":"NL",
    "name:afr_x_preferred":[
        "Overberg"
    ],
    "name:deu_x_preferred":[
        "Overberg"
    ],
    "name:nor_x_preferred":[
        "Overberg"
    ],
    "name:pol_x_preferred":[
        "Overberg"
    ],
    "wof:name":"Overberg",
    "wof:placetype":"locality"
},
  "geometry": {"coordinates":[4.37222,51.44167],"type":"Point"}
}