{
  "type": "Feature",
  "properties": {
    "gn:admin1_code":"6.0",
    "gn:admin2_code":"785.0",
    "gn:asciiname":"Boschkens",
    "gn:country_code":"NL",
    "gn:dem":21,
    "gn:feature_class":"P",
    "gn:feature_code":"PPL",
    "gn:name":"Boschkens",
    "gn:population":0,
    "gn:timezone":"Europe/Amsterdam",
    "iso:country":"NL",
    "wof:name":"Boschkens",
    "wof:placetype":"locality"
},
  "geometry": {"coordinates":[5.06389,51.53333],"type":"Point"}
}