{
  "type": "Feature",
  "properties": {
    "gn:admin1_code":"6.0",
    "gn:admin2_code":"0815",
    "gn:asciiname":"Princepeel",
    "gn:cc2":"NL",
    "gn:country_code":"NL",
    "gn:dem":18,
    "gn:feature_class":"P",
    "gn:feature_code":"PPLL",
    "gn:name":"Princepeel",
    "gn:population":0,
    "gn:timezone":"Europe/Amsterdam",
    "iso:country":"NL",
    "name:und_x_variant":[
        "Peel",
        "Prinsenpeel",
        "Principeel"
    ],
    "wof:name":"Princepeel",
    "wof:placetype":"locality"
},
  "geometry": {"coordinates":[5.76667,51.65],"type":"Point"}
}