{
  "type": "Feature",
  "properties": {
    "gn:admin1_code":"10.0",
    "gn:admin2_code":"677.0",
    "gn:asciiname":"Drie Hoefijzers",
    "gn:country_code":"NL",
    "gn:dem":3,
    "gn:feature_class":"P",
    "gn:feature_code":"PPL",
    "gn:name":"Drie Hoefijzers",
    "gn:population":0,
    "gn:timezone":"Europe/Amsterdam",
    "iso:country":"NL",
    "wof:name":"Drie Hoefijzers",
    "wof:placetype":"locality"
},
  "geometry": {"coordinates":[4.00278,51.24333],"type":"Point"}
}