{
  "type": "Feature",
  "properties": {
    "gn:admin1_code":"5.0",
    "gn:admin2_code":"0986",
    "gn:asciiname":"Overheek",
    "gn:country_code":"NL",
    "gn:dem":135,
    "gn:feature_class":"P",
    "gn:feature_code":"PPL",
    "gn:name":"Overheek",
    "gn:population":0,
    "gn:timezone":"Europe/Amsterdam",
    "iso:country":"NL",
    "wof:name":"Overheek",
    "wof:placetype":"locality"
},
  "geometry": {"coordinates":[5.87086,50.8823],"type":"Point"}
}