{
  "type": "Feature",
  "properties": {
    "gn:admin1_code":"9.0",
    "gn:admin2_code":"736.0",
    "gn:asciiname":"Achterbos",
    "gn:cc2":"NL",
    "gn:country_code":"NL",
    "gn:dem":-2,
    "gn:feature_class":"P",
    "gn:feature_code":"PPL",
    "gn:name":"Achterbos",
    "gn:population":0,
    "gn:timezone":"Europe/Amsterdam",
    "iso:country":"NL",
    "name:und_x_variant":[
        "Achterbosch"
    ],
    "wof:name":"Achterbos",
    "wof:placetype":"locality"
},
  "geometry": {"coordinates":[4.92639,52.225],"type":"Point"}
}