{
  "type": "Feature",
  "properties": {
    "gn:admin1_code":"7.0",
    "gn:admin2_code":"1911.0",
    "gn:asciiname":"Dam",
    "gn:country_code":"NL",
    "gn:dem":2,
    "gn:feature_class":"P",
    "gn:feature_code":"PPL",
    "gn:name":"Dam",
    "gn:population":0,
    "gn:timezone":"Europe/Amsterdam",
    "iso:country":"NL",
    "wof:name":"Dam",
    "wof:placetype":"locality"
},
  "geometry": {"coordinates":[4.9125,52.89583],"type":"Point"}
}