{
  "type": "Feature",
  "properties": {
    "gn:admin1_code":"3.0",
    "gn:admin2_code":"0230",
    "gn:asciiname":"Werfhorst",
    "gn:country_code":"NL",
    "gn:dem":2,
    "gn:feature_class":"P",
    "gn:feature_code":"PPL",
    "gn:name":"Werfhorst",
    "gn:population":0,
    "gn:timezone":"Europe/Amsterdam",
    "iso:country":"NL",
    "wof:name":"Werfhorst",
    "wof:placetype":"locality"
},
  "geometry": {"coordinates":[5.80921,52.41084],"type":"Point"}
}