{
  "type": "Feature",
  "properties": {
    "gn:admin1_code":"1.0",
    "gn:admin2_code":"0109",
    "gn:asciiname":"Schimmelarij",
    "gn:country_code":"NL",
    "gn:dem":12,
    "gn:feature_class":"P",
    "gn:feature_code":"PPL",
    "gn:name":"Schimmelarij",
    "gn:population":0,
    "gn:timezone":"Europe/Amsterdam",
    "iso:country":"NL",
    "wof:name":"Schimmelarij",
    "wof:placetype":"locality"
},
  "geometry": {"coordinates":[6.81667,52.70083],"type":"Point"}
}