{
  "type": "Feature",
  "properties": {
    "gn:admin1_code":"7.0",
    "gn:admin2_code":"1911.0",
    "gn:asciiname":"De Strook",
    "gn:country_code":"NL",
    "gn:dem":0,
    "gn:feature_class":"P",
    "gn:feature_code":"PPL",
    "gn:name":"De Strook",
    "gn:population":0,
    "gn:timezone":"Europe/Amsterdam",
    "iso:country":"NL",
    "wof:name":"De Strook",
    "wof:placetype":"locality"
},
  "geometry": {"coordinates":[4.89861,52.7925],"type":"Point"}
}