{
  "type": "Feature",
  "properties": {
    "gn:admin1_code":"2.0",
    "gn:admin2_code":"0079",
    "gn:asciiname":"Leegte",
    "gn:country_code":"NL",
    "gn:dem":0,
    "gn:feature_class":"P",
    "gn:feature_code":"PPL",
    "gn:name":"Leegte",
    "gn:population":0,
    "gn:timezone":"Europe/Amsterdam",
    "iso:country":"NL",
    "wof:name":"Leegte",
    "wof:placetype":"locality"
},
  "geometry": {"coordinates":[6.2503,53.2893],"type":"Point"}
}