{
  "type": "Feature",
  "properties": {
    "gn:admin1_code":"3.0",
    "gn:admin2_code":"0226",
    "gn:asciiname":"Nieuwgraaf",
    "gn:cc2":"NL",
    "gn:country_code":"NL",
    "gn:dem":10,
    "gn:feature_class":"P",
    "gn:feature_code":"PPL",
    "gn:name":"Nieuwgraaf",
    "gn:population":0,
    "gn:timezone":"Europe/Amsterdam",
    "iso:country":"NL",
    "name:und_x_variant":[
        "Nijgraaf"
    ],
    "wof:name":"Nieuwgraaf",
    "wof:placetype":"locality"
},
  "geometry": {"coordinates":[6.00417,51.97583],"type":"Point"}
}