{
  "type": "Feature",
  "properties": {
    "gn:admin1_code":"1.0",
    "gn:admin2_code":"0118",
    "gn:asciiname":"'t Noorden",
    "gn:country_code":"NL",
    "gn:dem":13,
    "gn:feature_class":"P",
    "gn:feature_code":"PPL",
    "gn:name":"t Noorden",
    "gn:population":0,
    "gn:timezone":"Europe/Amsterdam",
    "iso:country":"NL",
    "wof:name":"'t Noorden",
    "wof:placetype":"locality"
},
  "geometry": {"coordinates":[6.55833,52.7425],"type":"Point"}
}