{
  "type": "Feature",
  "properties": {
    "gn:admin1_code":"6.0",
    "gn:admin2_code":"1658.0",
    "gn:asciiname":"Heezerenbosch",
    "gn:country_code":"NL",
    "gn:dem":23,
    "gn:feature_class":"P",
    "gn:feature_code":"PPL",
    "gn:name":"Heezerenbosch",
    "gn:population":0,
    "gn:timezone":"Europe/Amsterdam",
    "iso:country":"NL",
    "wof:name":"Heezerenbosch",
    "wof:placetype":"locality"
},
  "geometry": {"coordinates":[5.55139,51.37417],"type":"Point"}
}