{
  "type": "Feature",
  "properties": {
    "gn:admin1_code":"6.0",
    "gn:admin2_code":"1702",
    "gn:asciiname":"Rondveld",
    "gn:country_code":"NL",
    "gn:dem":18,
    "gn:feature_class":"P",
    "gn:feature_code":"PPL",
    "gn:name":"Rondveld",
    "gn:population":0,
    "gn:timezone":"Europe/Amsterdam",
    "iso:country":"NL",
    "wof:name":"Rondveld",
    "wof:placetype":"locality"
},
  "geometry": {"coordinates":[5.89722,51.62083],"type":"Point"}
}