{
  "type": "Feature",
  "properties": {
    "gn:admin1_code":"10.0",
    "gn:admin2_code":"1714.0",
    "gn:asciiname":"Akkerput",
    "gn:country_code":"NL",
    "gn:dem":0,
    "gn:feature_class":"P",
    "gn:feature_code":"PPL",
    "gn:name":"Akkerput",
    "gn:population":0,
    "gn:timezone":"Europe/Amsterdam",
    "iso:country":"NL",
    "wof:name":"Akkerput",
    "wof:placetype":"locality"
},
  "geometry": {"coordinates":[3.46528,51.35],"type":"Point"}
}