{
  "type": "Feature",
  "properties": {
    "gn:admin1_code":"4.0",
    "gn:admin2_code":"0040",
    "gn:asciiname":"Ruiten",
    "gn:country_code":"NL",
    "gn:dem":-1,
    "gn:feature_class":"P",
    "gn:feature_code":"PPL",
    "gn:name":"Ruiten",
    "gn:population":0,
    "gn:timezone":"Europe/Amsterdam",
    "iso:country":"NL",
    "wof:name":"Ruiten",
    "wof:placetype":"locality"
},
  "geometry": {"coordinates":[6.76528,53.20166999999999],"type":"Point"}
}