{
  "type": "Feature",
  "properties": {
    "gn:admin1_code":"1.0",
    "gn:admin2_code":"1690.0",
    "gn:asciiname":"Bazuin",
    "gn:country_code":"NL",
    "gn:dem":10,
    "gn:feature_class":"P",
    "gn:feature_code":"PPL",
    "gn:name":"Bazuin",
    "gn:population":0,
    "gn:timezone":"Europe/Amsterdam",
    "iso:country":"NL",
    "wof:name":"Bazuin",
    "wof:placetype":"locality"
},
  "geometry": {"coordinates":[6.41389,52.65416999999999],"type":"Point"}
}