{
  "type": "Feature",
  "properties": {
    "gn:admin1_code":"2.0",
    "gn:admin2_code":"86.0",
    "gn:asciiname":"Grootwijngaarden",
    "gn:country_code":"NL",
    "gn:dem":-1,
    "gn:feature_class":"P",
    "gn:feature_code":"PPL",
    "gn:name":"Grootwijngaarden",
    "gn:population":0,
    "gn:timezone":"Europe/Amsterdam",
    "iso:country":"NL",
    "name:fry_x_preferred":[
        "Grutwingerden"
    ],
    "name:nld_x_preferred":[
        "Grootwijngaarden"
    ],
    "wof:name":"Grootwijngaarden",
    "wof:placetype":"locality"
},
  "geometry": {"coordinates":[5.97332,52.98562],"type":"Point"}
}