{
  "type": "Feature",
  "properties": {
    "gn:admin1_code":"3.0",
    "gn:admin2_code":"200.0",
    "gn:asciiname":"De Krim",
    "gn:cc2":"NL",
    "gn:country_code":"NL",
    "gn:dem":56,
    "gn:feature_class":"P",
    "gn:feature_code":"PPL",
    "gn:name":"De Krim",
    "gn:population":0,
    "gn:timezone":"Europe/Amsterdam",
    "iso:country":"NL",
    "name:und_x_variant":[
        "Krim"
    ],
    "wof:name":"De Krim",
    "wof:placetype":"locality"
},
  "geometry": {"coordinates":[5.89583,52.1225],"type":"Point"}
}