{
  "type": "Feature",
  "properties": {
    "gn:admin1_code":"3.0",
    "gn:admin2_code":"0668",
    "gn:asciiname":"Woerd",
    "gn:cc2":"NL",
    "gn:country_code":"NL",
    "gn:dem":6,
    "gn:feature_class":"P",
    "gn:feature_code":"PPL",
    "gn:name":"Woerd",
    "gn:population":0,
    "gn:timezone":"Europe/Amsterdam",
    "iso:country":"NL",
    "name:und_x_variant":[
        "De Woerd"
    ],
    "wof:name":"Woerd",
    "wof:placetype":"locality"
},
  "geometry": {"coordinates":[5.54861,51.8525],"type":"Point"}
}