{
  "type": "Feature",
  "properties": {
    "gn:admin1_code":"6.0",
    "gn:admin2_code":"1721",
    "gn:asciiname":"Lage Wijst",
    "gn:country_code":"NL",
    "gn:dem":9,
    "gn:feature_class":"P",
    "gn:feature_code":"PPL",
    "gn:name":"Lage Wijst",
    "gn:population":0,
    "gn:timezone":"Europe/Amsterdam",
    "iso:country":"NL",
    "wof:name":"Lage Wijst",
    "wof:placetype":"locality"
},
  "geometry": {"coordinates":[5.51806,51.72333],"type":"Point"}
}