{
  "type": "Feature",
  "properties": {
    "gn:admin1_code":"3.0",
    "gn:admin2_code":"203.0",
    "gn:asciiname":"Garderbroek",
    "gn:cc2":"NL",
    "gn:country_code":"NL",
    "gn:dem":15,
    "gn:feature_class":"P",
    "gn:feature_code":"PPL",
    "gn:name":"Garderbroek",
    "gn:population":0,
    "gn:timezone":"Europe/Amsterdam",
    "iso:country":"NL",
    "name:und_x_variant":[
        "Gardererbroek",
        "Garderenbroek"
    ],
    "wof:name":"Garderbroek",
    "wof:placetype":"locality"
},
  "geometry": {"coordinates":[5.67083,52.1725],"type":"Point"}
}