{
  "type": "Feature",
  "properties": {
    "gn:admin1_code":"7.0",
    "gn:admin2_code":"1598.0",
    "gn:asciiname":"Berkmeer",
    "gn:country_code":"NL",
    "gn:dem":-1,
    "gn:feature_class":"P",
    "gn:feature_code":"PPL",
    "gn:name":"Berkmeer",
    "gn:population":0,
    "gn:timezone":"Europe/Amsterdam",
    "iso:country":"NL",
    "wof:name":"Berkmeer",
    "wof:placetype":"locality"
},
  "geometry": {"coordinates":[4.90278,52.6875],"type":"Point"}
}