{
  "type": "Feature",
  "properties": {
    "gn:admin1_code":"15.0",
    "gn:admin2_code":"141.0",
    "gn:asciiname":"Bolkshoek",
    "gn:cc2":"NL",
    "gn:country_code":"NL",
    "gn:dem":13,
    "gn:feature_class":"P",
    "gn:feature_code":"PPLL",
    "gn:name":"Bolkshoek",
    "gn:population":0,
    "gn:timezone":"Europe/Amsterdam",
    "iso:country":"NL",
    "name:und_x_variant":[
        "Bolkhoek"
    ],
    "wof:name":"Bolkshoek",
    "wof:placetype":"locality"
},
  "geometry": {"coordinates":[6.69424,52.35267],"type":"Point"}
}