{
  "type": "Feature",
  "properties": {
    "gn:admin1_code":"3.0",
    "gn:admin2_code":"1945",
    "gn:asciiname":"Meerwijk",
    "gn:country_code":"NL",
    "gn:dem":98,
    "gn:feature_class":"P",
    "gn:feature_code":"PPL",
    "gn:name":"Meerwijk",
    "gn:population":0,
    "gn:timezone":"Europe/Amsterdam",
    "iso:country":"NL",
    "wof:name":"Meerwijk",
    "wof:placetype":"locality"
},
  "geometry": {"coordinates":[5.91667,51.81667],"type":"Point"}
}