{
  "type": "Feature",
  "properties": {
    "gn:admin1_code":"15.0",
    "gn:admin2_code":"0166",
    "gn:asciiname":"Zuideinde",
    "gn:country_code":"NL",
    "gn:dem":1,
    "gn:feature_class":"P",
    "gn:feature_code":"PPL",
    "gn:name":"Zuideinde",
    "gn:population":0,
    "gn:timezone":"Europe/Amsterdam",
    "iso:country":"NL",
    "wof:name":"Zuideinde",
    "wof:placetype":"locality"
},
  "geometry": {"coordinates":[5.93056,52.48167],"type":"Point"}
}