{
  "type": "Feature",
  "properties": {
    "gn:admin1_code":"3.0",
    "gn:admin2_code":"1859.0",
    "gn:asciiname":"Brinkmanshoek",
    "gn:country_code":"NL",
    "gn:dem":16,
    "gn:feature_class":"P",
    "gn:feature_code":"PPL",
    "gn:name":"Brinkmanshoek",
    "gn:population":0,
    "gn:timezone":"Europe/Amsterdam",
    "iso:country":"NL",
    "wof:name":"Brinkmanshoek",
    "wof:placetype":"locality"
},
  "geometry": {"coordinates":[6.49583,52.085],"type":"Point"}
}