{
  "type": "Feature",
  "properties": {
    "gn:admin1_code":"10.0",
    "gn:admin2_code":"703.0",
    "gn:asciiname":"Gawege",
    "gn:country_code":"NL",
    "gn:dem":0,
    "gn:feature_class":"P",
    "gn:feature_code":"PPL",
    "gn:name":"Gawege",
    "gn:population":0,
    "gn:timezone":"Europe/Amsterdam",
    "iso:country":"NL",
    "wof:name":"Gawege",
    "wof:placetype":"locality"
},
  "geometry": {"coordinates":[4.10278,51.41833],"type":"Point"}
}