{
  "type": "Feature",
  "properties": {
    "gn:admin1_code":"10.0",
    "gn:admin2_code":"0715",
    "gn:asciiname":"Schapenbout",
    "gn:country_code":"NL",
    "gn:dem":0,
    "gn:feature_class":"P",
    "gn:feature_code":"PPL",
    "gn:name":"Schapenbout",
    "gn:population":0,
    "gn:timezone":"Europe/Amsterdam",
    "iso:country":"NL",
    "wof:name":"Schapenbout",
    "wof:placetype":"locality"
},
  "geometry": {"coordinates":[3.87778,51.28],"type":"Point"}
}