{
  "type": "Feature",
  "properties": {
    "gn:admin1_code":"3.0",
    "gn:admin2_code":"0232",
    "gn:asciiname":"Laarstraat",
    "gn:country_code":"NL",
    "gn:dem":11,
    "gn:feature_class":"P",
    "gn:feature_code":"PPL",
    "gn:name":"Laarstraat",
    "gn:population":0,
    "gn:timezone":"Europe/Amsterdam",
    "iso:country":"NL",
    "wof:name":"Laarstraat",
    "wof:placetype":"locality"
},
  "geometry": {"coordinates":[5.97361,52.32917],"type":"Point"}
}