{
  "type": "Feature",
  "properties": {
    "gn:admin1_code":"2.0",
    "gn:admin2_code":"0058",
    "gn:asciiname":"Stiem",
    "gn:country_code":"NL",
    "gn:dem":-1,
    "gn:feature_class":"P",
    "gn:feature_code":"PPL",
    "gn:name":"Stiem",
    "gn:population":0,
    "gn:timezone":"Europe/Amsterdam",
    "iso:country":"NL",
    "name:fry_x_preferred":[
        "Stiem"
    ],
    "name:nld_x_preferred":[
        "Stiem"
    ],
    "wof:name":"Stiem",
    "wof:placetype":"locality"
},
  "geometry": {"coordinates":[6.14531,53.36867],"type":"Point"}
}