{
  "type": "Feature",
  "properties": {
    "gn:admin1_code":"4.0",
    "gn:admin2_code":"48.0",
    "gn:asciiname":"Poldert",
    "gn:country_code":"NL",
    "gn:dem":3,
    "gn:feature_class":"P",
    "gn:feature_code":"PPL",
    "gn:name":"Poldert",
    "gn:population":0,
    "gn:timezone":"Europe/Amsterdam",
    "iso:country":"NL",
    "wof:name":"Poldert",
    "wof:placetype":"locality"
},
  "geometry": {"coordinates":[7.14167,53.03],"type":"Point"}
}