{
  "type": "Feature",
  "properties": {
    "gn:admin1_code":"10.0",
    "gn:admin2_code":"0677",
    "gn:asciiname":"Kruisdorp",
    "gn:country_code":"NL",
    "gn:dem":0,
    "gn:feature_class":"P",
    "gn:feature_code":"PPL",
    "gn:name":"Kruisdorp",
    "gn:population":0,
    "gn:timezone":"Europe/Amsterdam",
    "iso:country":"NL",
    "wof:name":"Kruisdorp",
    "wof:placetype":"locality"
},
  "geometry": {"coordinates":[4.03889,51.365],"type":"Point"}
}