{
  "type": "Feature",
  "properties": {
    "gn:admin1_code":"15.0",
    "gn:admin2_code":"0160",
    "gn:asciiname":"Noord-Stegeren",
    "gn:country_code":"NL",
    "gn:dem":6,
    "gn:feature_class":"P",
    "gn:feature_code":"PPL",
    "gn:name":"Noord-Stegeren",
    "gn:population":0,
    "gn:timezone":"Europe/Amsterdam",
    "iso:country":"NL",
    "wof:name":"Noord-Stegeren",
    "wof:placetype":"locality"
},
  "geometry": {"coordinates":[6.47083,52.61333000000001],"type":"Point"}
}