{
  "type": "Feature",
  "properties": {
    "gn:admin1_code":"2.0",
    "gn:admin2_code":"0086",
    "gn:asciiname":"Sparjebird",
    "gn:country_code":"NL",
    "gn:dem":3,
    "gn:feature_class":"P",
    "gn:feature_code":"PPL",
    "gn:name":"Sparjebird",
    "gn:population":0,
    "gn:timezone":"Europe/Amsterdam",
    "iso:country":"NL",
    "name:fry_x_preferred":[
        "Sparjeburd"
    ],
    "name:nld_x_preferred":[
        "Sparjebird"
    ],
    "name:und_x_variant":[
        "Sparjebert"
    ],
    "wof:name":"Sparjebird",
    "wof:placetype":"locality"
},
  "geometry": {"coordinates":[6.16013,53.03665],"type":"Point"}
}