{
  "type": "Feature",
  "properties": {
    "gn:admin1_code":"7.0",
    "gn:admin2_code":"0448",
    "gn:asciiname":"Hoogeberg",
    "gn:country_code":"NL",
    "gn:dem":12,
    "gn:feature_class":"P",
    "gn:feature_code":"PPL",
    "gn:name":"Hoogeberg",
    "gn:population":0,
    "gn:timezone":"Europe/Amsterdam",
    "iso:country":"NL",
    "wof:name":"Hoogeberg",
    "wof:placetype":"locality"
},
  "geometry": {"coordinates":[4.8172,53.04362],"type":"Point"}
}