{
  "type": "Feature",
  "properties": {
    "gn:admin1_code":"11.0",
    "gn:admin2_code":"0505",
    "gn:asciiname":"Kop van 't Land",
    "gn:cc2":"NL",
    "gn:country_code":"NL",
    "gn:dem":0,
    "gn:feature_class":"P",
    "gn:feature_code":"PPL",
    "gn:name":"Kop van 't Land",
    "gn:population":0,
    "gn:timezone":"Europe/Amsterdam",
    "iso:country":"NL",
    "name:und_x_variant":[
        "De Kop van het Land",
        "Kop Van Het Land"
    ],
    "wof:name":"Kop van 't Land",
    "wof:placetype":"locality"
},
  "geometry": {"coordinates":[4.75694,51.78833],"type":"Point"}
}