{
  "type": "Feature",
  "properties": {
    "gn:admin1_code":"3.0",
    "gn:admin2_code":"209.0",
    "gn:asciiname":"Hoeve",
    "gn:country_code":"NL",
    "gn:dem":8,
    "gn:feature_class":"P",
    "gn:feature_code":"PPL",
    "gn:name":"Hoeve",
    "gn:population":0,
    "gn:timezone":"Europe/Amsterdam",
    "iso:country":"NL",
    "wof:name":"Hoeve",
    "wof:placetype":"locality"
},
  "geometry": {"coordinates":[5.73889,51.86333],"type":"Point"}
}