{
  "type": "Feature",
  "properties": {
    "gn:admin1_code":"6.0",
    "gn:admin2_code":"1702",
    "gn:asciiname":"Zandkant",
    "gn:country_code":"NL",
    "gn:dem":14,
    "gn:feature_class":"P",
    "gn:feature_code":"PPL",
    "gn:name":"Zandkant",
    "gn:population":0,
    "gn:timezone":"Europe/Amsterdam",
    "iso:country":"NL",
    "wof:name":"Zandkant",
    "wof:placetype":"locality"
},
  "geometry": {"coordinates":[5.90278,51.6325],"type":"Point"}
}