{
  "type": "Feature",
  "properties": {
    "cbsnl:BU_CODE":"BU00900002",
    "cbsnl:BU_NAAM":"De Wiken",
    "cbsnl:GM_CODE":"GM0090",
    "cbsnl:GM_NAAM":"Smallingerland",
    "cbsnl:IND_WBI":"1",
    "cbsnl:OAD":"1722",
    "cbsnl:STED":"2",
    "cbsnl:WATER":"NEE",
    "cbsnl:WK_CODE":"WK009000",
    "iso:country":"NL",
    "name:dut_x_preferred":[
        "De Wiken"
    ],
    "name:dut_x_variant":[
        "De Wieken"
    ],
    "name:eng_x_preferred":[
        "De Wiken"
    ],
    "name:eng_x_variant":[
        "De Wieken",
        "De Wiken"
    ],
    "name:nld_x_preferred":[
        "De Wieken"
    ],
    "name:unk_x_variant":[
        "De Wiken",
        "De Wieken"
    ],
    "qs:gn_adm0_cc":"NL",
    "qs:gn_fcode":"PPLX",
    "qs:gn_local":2756644,
    "qs:gn_nam_loc":"drachten",
    "qs:gn_namadm1":"02",
    "qs:gn_name":"De Wieken",
    "qs:local_max":2244,
    "qs:local_sum":4039,
    "qs:localhoods":2,
    "qs:name":"De Wieken",
    "qs:name_adm0":"Nederland",
    "qs:name_adm1":"Friesland",
    "qs:name_adm2":"Smallingerland",
    "qs:name_en":"De Wiken",
    "qs:name_local":"Drachten",
    "qs:photo_max":592,
    "qs:photo_sum":1795,
    "qs:placetype":"Suburb",
    "qs:quad_count":76,
    "qs:woe_adm0":23424909,
    "qs:woe_adm1":2346374,
    "qs:woe_adm2":12592402,
    "qs:woe_lau":0,
    "qs:woe_local":728824,
    "qs:woe_ver":"7.10.0",
    "wof:lang":[
        "dut"
    ],
    "wof:name":"De Wieken",
    "wof:placetype":"neighbourhood"
},
  "geometry": {"coordinates":[6.121698,53.115583],"type":"Point"}
}