{
  "type": "Feature",
  "properties": {
    "gn:admin1_code":"2.0",
    "gn:admin2_code":"140.0",
    "gn:asciiname":"De Grits",
    "gn:country_code":"NL",
    "gn:dem":-1,
    "gn:feature_class":"P",
    "gn:feature_code":"PPL",
    "gn:name":"De Grits",
    "gn:population":0,
    "gn:timezone":"Europe/Amsterdam",
    "iso:country":"NL",
    "wof:name":"De Grits",
    "wof:placetype":"locality"
},
  "geometry": {"coordinates":[5.56684,53.11622],"type":"Point"}
}