{
  "type": "Feature",
  "properties": {
    "gn:admin1_code":"6.0",
    "gn:admin2_code":"823.0",
    "gn:asciiname":"Pandgat",
    "gn:country_code":"NL",
    "gn:dem":11,
    "gn:feature_class":"P",
    "gn:feature_code":"PPL",
    "gn:name":"Pandgat",
    "gn:population":0,
    "gn:timezone":"Europe/Amsterdam",
    "iso:country":"NL",
    "wof:name":"Pandgat",
    "wof:placetype":"locality"
},
  "geometry": {"coordinates":[5.28194,51.5175],"type":"Point"}
}