{
  "type": "Feature",
  "properties": {
    "gn:admin1_code":"2.0",
    "gn:admin2_code":"1940",
    "gn:asciiname":"Onland",
    "gn:country_code":"NL",
    "gn:dem":-1,
    "gn:feature_class":"P",
    "gn:feature_code":"PPL",
    "gn:name":"Onland",
    "gn:population":0,
    "gn:timezone":"Europe/Amsterdam",
    "iso:country":"NL",
    "name:fry_x_preferred":[
        "Unl\u00e2n"
    ],
    "name:nld_x_preferred":[
        "Onland"
    ],
    "wof:name":"Onland",
    "wof:placetype":"locality"
},
  "geometry": {"coordinates":[5.84259,52.93526],"type":"Point"}
}