{
  "type": "Feature",
  "properties": {
    "gn:admin1_code":"7.0",
    "gn:admin2_code":"0852",
    "gn:asciiname":"Moeniswerf",
    "gn:country_code":"NL",
    "gn:dem":-1,
    "gn:feature_class":"P",
    "gn:feature_code":"PPL",
    "gn:name":"Moeniswerf",
    "gn:population":0,
    "gn:timezone":"Europe/Amsterdam",
    "iso:country":"NL",
    "wof:name":"Moeniswerf",
    "wof:placetype":"locality"
},
  "geometry": {"coordinates":[5.11944,52.45667],"type":"Point"}
}