{
  "type": "Feature",
  "properties": {
    "gn:admin1_code":"4.0",
    "gn:admin2_code":"0005",
    "gn:asciiname":"Onderwierum",
    "gn:country_code":"NL",
    "gn:dem":2,
    "gn:feature_class":"P",
    "gn:feature_code":"PPL",
    "gn:name":"Onderwierum",
    "gn:population":0,
    "gn:timezone":"Europe/Amsterdam",
    "iso:country":"NL",
    "wof:name":"Onderwierum",
    "wof:placetype":"locality"
},
  "geometry": {"coordinates":[6.58056,53.3275],"type":"Point"}
}