{
  "type": "Feature",
  "properties": {
    "gn:admin1_code":"6.0",
    "gn:admin2_code":"0856",
    "gn:asciiname":"Oosterheide",
    "gn:country_code":"NL",
    "gn:dem":21,
    "gn:feature_class":"P",
    "gn:feature_code":"PPL",
    "gn:name":"Oosterheide",
    "gn:population":0,
    "gn:timezone":"Europe/Amsterdam",
    "iso:country":"NL",
    "wof:name":"Oosterheide",
    "wof:placetype":"locality"
},
  "geometry": {"coordinates":[5.66857,51.64335],"type":"Point"}
}