{
  "type": "Feature",
  "properties": {
    "gn:admin1_code":"15.0",
    "gn:admin2_code":"0160",
    "gn:asciiname":"Witman",
    "gn:country_code":"NL",
    "gn:dem":10,
    "gn:feature_class":"P",
    "gn:feature_code":"PPL",
    "gn:name":"Witman",
    "gn:population":0,
    "gn:timezone":"Europe/Amsterdam",
    "iso:country":"NL",
    "wof:name":"Witman",
    "wof:placetype":"locality"
},
  "geometry": {"coordinates":[6.525,52.63166999999999],"type":"Point"}
}