{
  "type": "Feature",
  "properties": {
    "gn:admin1_code":"6.0",
    "gn:admin2_code":"1674.0",
    "gn:asciiname":"Bulkenaar",
    "gn:country_code":"NL",
    "gn:dem":6,
    "gn:feature_class":"P",
    "gn:feature_code":"PPL",
    "gn:name":"Bulkenaar",
    "gn:population":0,
    "gn:timezone":"Europe/Amsterdam",
    "iso:country":"NL",
    "wof:name":"Bulkenaar",
    "wof:placetype":"locality"
},
  "geometry": {"coordinates":[4.42222,51.51583],"type":"Point"}
}