{
  "type": "Feature",
  "properties": {
    "gn:admin1_code":"2.0",
    "gn:admin2_code":"1940.0",
    "gn:asciiname":"De Woudfennen",
    "gn:country_code":"NL",
    "gn:dem":0,
    "gn:feature_class":"P",
    "gn:feature_code":"PPLL",
    "gn:name":"De Woudfennen",
    "gn:population":0,
    "gn:timezone":"Europe/Amsterdam",
    "iso:country":"NL",
    "name:fry_x_preferred":[
        "De W\u00e2ldfinnen"
    ],
    "name:nld_x_preferred":[
        "De Woudfennen"
    ],
    "wof:name":"De Woudfennen",
    "wof:placetype":"locality"
},
  "geometry": {"coordinates":[5.75409,52.962],"type":"Point"}
}