{
  "type": "Feature",
  "properties": {
    "gn:admin1_code":"6.0",
    "gn:admin2_code":"1652.0",
    "gn:asciiname":"Benthem",
    "gn:cc2":"NL",
    "gn:country_code":"NL",
    "gn:dem":18,
    "gn:feature_class":"P",
    "gn:feature_code":"PPL",
    "gn:name":"Benthem",
    "gn:population":0,
    "gn:timezone":"Europe/Amsterdam",
    "iso:country":"NL",
    "name:deu_x_preferred":[
        "Benthem"
    ],
    "name:nds_x_preferred":[
        "Benthem"
    ],
    "name:nld_x_preferred":[
        "Benthem"
    ],
    "name:und_x_variant":[
        "Bentem",
        "Benten",
        "Bentum"
    ],
    "wof:name":"Benthem",
    "wof:placetype":"locality"
},
  "geometry": {"coordinates":[5.72361,51.49667],"type":"Point"}
}