{
  "type": "Feature",
  "properties": {
    "gn:admin1_code":"2.0",
    "gn:admin2_code":"74.0",
    "gn:asciiname":"Brongerga",
    "gn:country_code":"NL",
    "gn:dem":4,
    "gn:feature_class":"P",
    "gn:feature_code":"PPL",
    "gn:name":"Brongerga",
    "gn:population":0,
    "gn:timezone":"Europe/Amsterdam",
    "iso:country":"NL",
    "name:fry_x_preferred":[
        "Brongergea"
    ],
    "wof:name":"Brongerga",
    "wof:placetype":"locality"
},
  "geometry": {"coordinates":[5.98333,52.95],"type":"Point"}
}