{
  "type": "Feature",
  "properties": {
    "gn:admin1_code":"5.0",
    "gn:admin2_code":"0951",
    "gn:asciiname":"Nuinhof",
    "gn:country_code":"NL",
    "gn:dem":91,
    "gn:feature_class":"P",
    "gn:feature_code":"PPL",
    "gn:name":"Nuinhof",
    "gn:population":0,
    "gn:timezone":"Europe/Amsterdam",
    "iso:country":"NL",
    "wof:name":"Nuinhof",
    "wof:placetype":"locality"
},
  "geometry": {"coordinates":[5.88333,50.91667],"type":"Point"}
}