{
  "type": "Feature",
  "properties": {
    "gn:admin1_code":"2.0",
    "gn:admin2_code":"0085",
    "gn:asciiname":"Nieuw Weper",
    "gn:country_code":"NL",
    "gn:dem":6,
    "gn:feature_class":"P",
    "gn:feature_code":"PPL",
    "gn:name":"Nieuw Weper",
    "gn:population":0,
    "gn:timezone":"Europe/Amsterdam",
    "iso:country":"NL",
    "wof:name":"Nieuw Weper",
    "wof:placetype":"locality"
},
  "geometry": {"coordinates":[6.34458,53.02144000000001],"type":"Point"}
}