{
  "type": "Feature",
  "properties": {
    "gn:admin1_code":"6.0",
    "gn:admin2_code":"828.0",
    "gn:asciiname":"Heuvels",
    "gn:country_code":"NL",
    "gn:dem":8,
    "gn:feature_class":"P",
    "gn:feature_code":"PPL",
    "gn:name":"Heuvels",
    "gn:population":0,
    "gn:timezone":"Europe/Amsterdam",
    "iso:country":"NL",
    "wof:name":"Heuvels",
    "wof:placetype":"locality"
},
  "geometry": {"coordinates":[5.63333,51.76667],"type":"Point"}
}