{
  "type": "Feature",
  "properties": {
    "gn:admin1_code":"4.0",
    "gn:admin2_code":"56.0",
    "gn:asciiname":"Electra",
    "gn:country_code":"NL",
    "gn:dem":-2,
    "gn:feature_class":"P",
    "gn:feature_code":"PPL",
    "gn:name":"Electra",
    "gn:population":0,
    "gn:timezone":"Europe/Amsterdam",
    "iso:country":"NL",
    "wof:name":"Electra",
    "wof:placetype":"locality"
},
  "geometry": {"coordinates":[6.35556,53.31333000000001],"type":"Point"}
}