{
  "type": "Feature",
  "properties": {
    "gn:admin1_code":"5.0",
    "gn:admin2_code":"1507.0",
    "gn:asciiname":"De Hees",
    "gn:cc2":"NL",
    "gn:country_code":"NL",
    "gn:dem":29,
    "gn:feature_class":"P",
    "gn:feature_code":"PPL",
    "gn:name":"De Hees",
    "gn:population":0,
    "gn:timezone":"Europe/Amsterdam",
    "iso:country":"NL",
    "name:und_x_variant":[
        "Achterste Hees"
    ],
    "wof:name":"De Hees",
    "wof:placetype":"locality"
},
  "geometry": {"coordinates":[6.02083,51.41333],"type":"Point"}
}