{
  "type": "Feature",
  "properties": {
    "gn:admin1_code":"3.0",
    "gn:admin2_code":"0273",
    "gn:asciiname":"Norden",
    "gn:country_code":"NL",
    "gn:dem":9,
    "gn:feature_class":"P",
    "gn:feature_code":"PPL",
    "gn:name":"Norden",
    "gn:population":0,
    "gn:timezone":"Europe/Amsterdam",
    "iso:country":"NL",
    "name:ceb_x_preferred":[
        "Norden"
    ],
    "name:dan_x_preferred":[
        "Norden"
    ],
    "name:deu_x_preferred":[
        "Norden"
    ],
    "name:eus_x_preferred":[
        "Norden"
    ],
    "name:fin_x_preferred":[
        "Norden"
    ],
    "name:fra_x_preferred":[
        "Norden"
    ],
    "name:ita_x_preferred":[
        "Norden"
    ],
    "name:jpn_x_preferred":[
        "\u30ce\u30eb\u30c7\u30f3"
    ],
    "name:pol_x_preferred":[
        "Norden"
    ],
    "name:rus_x_preferred":[
        "\u041d\u043e\u0440\u0434\u0435\u043d"
    ],
    "name:swe_x_preferred":[
        "Norden"
    ],
    "wof:name":"Norden",
    "wof:placetype":"locality"
},
  "geometry": {"coordinates":[5.58353,52.26842],"type":"Point"}
}