{
  "type": "Feature",
  "properties": {
    "gn:admin1_code":"4.0",
    "gn:admin2_code":"0005",
    "gn:asciiname":"Menkeweer",
    "gn:country_code":"NL",
    "gn:dem":1,
    "gn:feature_class":"P",
    "gn:feature_code":"PPL",
    "gn:name":"Menkeweer",
    "gn:population":0,
    "gn:timezone":"Europe/Amsterdam",
    "iso:country":"NL",
    "wof:name":"Menkeweer",
    "wof:placetype":"locality"
},
  "geometry": {"coordinates":[6.58302,53.34119000000001],"type":"Point"}
}