{
  "type": "Feature",
  "properties": {
    "gn:admin1_code":"3.0",
    "gn:admin2_code":"294.0",
    "gn:asciiname":"Winterswijk Kotten",
    "gn:country_code":"NL",
    "gn:dem":41,
    "gn:feature_class":"P",
    "gn:feature_code":"PPL",
    "gn:name":"Winterswijk Kotten",
    "gn:population":0,
    "gn:timezone":"Europe/Amsterdam",
    "iso:country":"NL",
    "wof:name":"Winterswijk Kotten",
    "wof:placetype":"locality"
},
  "geometry": {"coordinates":[6.77011,51.93897],"type":"Point"}
}