{
  "type": "Feature",
  "properties": {
    "gn:admin1_code":"6.0",
    "gn:admin2_code":"840.0",
    "gn:asciiname":"DeDood",
    "gn:country_code":"NL",
    "gn:dem":11,
    "gn:feature_class":"P",
    "gn:feature_code":"PPL",
    "gn:name":"De Dood",
    "gn:population":0,
    "gn:timezone":"Europe/Amsterdam",
    "iso:country":"NL",
    "wof:name":"DeDood",
    "wof:placetype":"locality"
},
  "geometry": {"coordinates":[4.5625,51.52167],"type":"Point"}
}