{
  "type": "Feature",
  "properties": {
    "gn:admin1_code":"15.0",
    "gn:admin2_code":"0180",
    "gn:asciiname":"Lankhorst",
    "gn:country_code":"NL",
    "gn:dem":1,
    "gn:feature_class":"P",
    "gn:feature_code":"PPL",
    "gn:name":"Lankhorst",
    "gn:population":0,
    "gn:timezone":"Europe/Amsterdam",
    "iso:country":"NL",
    "wof:name":"Lankhorst",
    "wof:placetype":"locality"
},
  "geometry": {"coordinates":[6.22222,52.67833],"type":"Point"}
}