{
  "type": "Feature",
  "properties": {
    "gn:admin1_code":"6.0",
    "gn:admin2_code":"1728.0",
    "gn:asciiname":"De Pan",
    "gn:country_code":"NL",
    "gn:dem":32,
    "gn:feature_class":"P",
    "gn:feature_code":"PPL",
    "gn:name":"De Pan",
    "gn:population":0,
    "gn:timezone":"Europe/Amsterdam",
    "iso:country":"NL",
    "wof:name":"De Pan",
    "wof:placetype":"locality"
},
  "geometry": {"coordinates":[5.27361,51.34667],"type":"Point"}
}