{
  "type": "Feature",
  "properties": {
    "gn:admin1_code":"3.0",
    "gn:admin2_code":"1586",
    "gn:asciiname":"Ruurlosche Broek",
    "gn:country_code":"NL",
    "gn:dem":16,
    "gn:feature_class":"P",
    "gn:feature_code":"PPL",
    "gn:name":"Ruurlosche Broek",
    "gn:population":0,
    "gn:timezone":"Europe/Amsterdam",
    "iso:country":"NL",
    "name:und_x_variant":[
        "\u2019t Ruurlose Broek",
        "Ruurlosebroek",
        "Ruurlosche Broek"
    ],
    "wof:name":"Ruurlosche Broek",
    "wof:placetype":"locality"
},
  "geometry": {"coordinates":[6.4949,52.04824],"type":"Point"}
}