{
  "type": "Feature",
  "properties": {
    "gn:admin1_code":"15.0",
    "gn:admin2_code":"148.0",
    "gn:asciiname":"Leusenerslag",
    "gn:country_code":"NL",
    "gn:dem":4,
    "gn:feature_class":"P",
    "gn:feature_code":"PPL",
    "gn:name":"Leusenerslag",
    "gn:population":0,
    "gn:timezone":"Europe/Amsterdam",
    "iso:country":"NL",
    "wof:name":"Leusenerslag",
    "wof:placetype":"locality"
},
  "geometry": {"coordinates":[6.30833,52.54083000000001],"type":"Point"}
}