{
  "type": "Feature",
  "properties": {
    "gn:admin1_code":"15.0",
    "gn:admin2_code":"160.0",
    "gn:asciiname":"Gouden-Ploeg",
    "gn:country_code":"NL",
    "gn:dem":10,
    "gn:feature_class":"P",
    "gn:feature_code":"PPL",
    "gn:name":"Gouden Ploeg",
    "gn:population":0,
    "gn:timezone":"Europe/Amsterdam",
    "iso:country":"NL",
    "wof:name":"Gouden-Ploeg",
    "wof:placetype":"locality"
},
  "geometry": {"coordinates":[6.60139,52.51333],"type":"Point"}
}