{
  "type": "Feature",
  "properties": {
    "gn:admin1_code":"4.0",
    "gn:admin2_code":"0037",
    "gn:asciiname":"Vosseberg",
    "gn:country_code":"NL",
    "gn:dem":2,
    "gn:feature_class":"P",
    "gn:feature_code":"PPL",
    "gn:name":"Vosseberg",
    "gn:population":0,
    "gn:timezone":"Europe/Amsterdam",
    "iso:country":"NL",
    "wof:name":"Vosseberg",
    "wof:placetype":"locality"
},
  "geometry": {"coordinates":[7.04722,52.99166999999999],"type":"Point"}
}