{
  "type": "Feature",
  "properties": {
    "gn:admin1_code":"3.0",
    "gn:admin2_code":"262.0",
    "gn:asciiname":"Armhoede",
    "gn:country_code":"NL",
    "gn:dem":12,
    "gn:feature_class":"P",
    "gn:feature_code":"PPL",
    "gn:name":"Armhoede",
    "gn:population":0,
    "gn:timezone":"Europe/Amsterdam",
    "iso:country":"NL",
    "wof:name":"Armhoede",
    "wof:placetype":"locality"
},
  "geometry": {"coordinates":[6.44583,52.175],"type":"Point"}
}