{
  "type": "Feature",
  "properties": {
    "gn:admin1_code":"15.0",
    "gn:admin2_code":"0163",
    "gn:asciiname":"Rhaan",
    "gn:country_code":"NL",
    "gn:dem":7,
    "gn:feature_class":"P",
    "gn:feature_code":"PPL",
    "gn:name":"Rhaan",
    "gn:population":0,
    "gn:timezone":"Europe/Amsterdam",
    "iso:country":"NL",
    "wof:name":"Rhaan",
    "wof:placetype":"locality"
},
  "geometry": {"coordinates":[6.45,52.42916999999999],"type":"Point"}
}