{
  "type": "Feature",
  "properties": {
    "gn:admin1_code":"5.0",
    "gn:admin2_code":"0994",
    "gn:asciiname":"Keutenberg",
    "gn:country_code":"NL",
    "gn:dem":138,
    "gn:feature_class":"P",
    "gn:feature_code":"PPL",
    "gn:name":"Keutenberg",
    "gn:population":0,
    "gn:timezone":"Europe/Amsterdam",
    "iso:country":"NL",
    "name:deu_x_preferred":[
        "Keutenberg"
    ],
    "name:fra_x_preferred":[
        "Keutenberg"
    ],
    "name:lim_x_preferred":[
        "Keuteberg"
    ],
    "name:nld_x_preferred":[
        "Keutenberg"
    ],
    "name:spa_x_preferred":[
        "Keutenberg"
    ],
    "wof:name":"Keutenberg",
    "wof:placetype":"locality"
},
  "geometry": {"coordinates":[5.87222,50.8425],"type":"Point"}
}