{
  "type": "Feature",
  "properties": {
    "gn:admin1_code":"3.0",
    "gn:admin2_code":"1509",
    "gn:asciiname":"Rafelder",
    "gn:country_code":"NL",
    "gn:dem":12,
    "gn:feature_class":"P",
    "gn:feature_code":"PPL",
    "gn:name":"Rafelder",
    "gn:population":0,
    "gn:timezone":"Europe/Amsterdam",
    "iso:country":"NL",
    "wof:name":"Rafelder",
    "wof:placetype":"locality"
},
  "geometry": {"coordinates":[6.32917,51.89917],"type":"Point"}
}