{
  "type": "Feature",
  "properties": {
    "gn:population":1200,
    "iso:country":"NL",
    "name:ara_x_preferred":[
        "\u0628\u0648\u0644\u0646\u0633\u0644\u0627\u0646"
    ],
    "name:bul_x_preferred":[
        "\u0411\u043e\u0435\u043b\u0435\u043d\u0441\u043b\u0430\u043d"
    ],
    "name:ceb_x_preferred":[
        "Boelenslaan"
    ],
    "name:eng_x_preferred":[
        "Boelenslaan"
    ],
    "name:fra_x_preferred":[
        "Boelenslaan"
    ],
    "name:fry_x_preferred":[
        "Boelensloane"
    ],
    "name:nan_x_preferred":[
        "Boelenslaan"
    ],
    "name:nld_x_preferred":[
        "Boelenslaan"
    ],
    "name:nld_x_variant":[
        "Surhuisterveensterheide"
    ],
    "name:zho_min_nan_x_preferred":[
        "Boelenslaan"
    ],
    "qs:a0":"Nederland",
    "qs:a1":"*Friesland",
    "qs:a1r":"0",
    "qs:adm0":"Nederland",
    "qs:la_lc":"*",
    "qs:level":"locality",
    "qs:loc":"Boelenslaan",
    "qs:loc_alt":"Boelenslaan",
    "qs:pop":0,
    "qs:type":"buffered point",
    "wd:wordcount":212,
    "wof:name":"Boelenslaan",
    "wof:placetype":"locality",
    "wof:population":1200
},
  "geometry": {"coordinates":[6.145813,53.161633],"type":"Point"}
}