{
  "type": "Feature",
  "properties": {
    "gn:admin1_code":"15.0",
    "gn:admin2_code":"0150",
    "gn:asciiname":"Oxe",
    "gn:country_code":"NL",
    "gn:dem":12,
    "gn:feature_class":"P",
    "gn:feature_code":"PPL",
    "gn:name":"Oxe",
    "gn:population":0,
    "gn:timezone":"Europe/Amsterdam",
    "iso:country":"NL",
    "wof:name":"Oxe",
    "wof:placetype":"locality"
},
  "geometry": {"coordinates":[6.23611,52.23083],"type":"Point"}
}