{
  "type": "Feature",
  "properties": {
    "gn:admin1_code":"6.0",
    "gn:admin2_code":"1721.0",
    "gn:asciiname":"Hazelberg",
    "gn:country_code":"NL",
    "gn:dem":8,
    "gn:feature_class":"P",
    "gn:feature_code":"PPL",
    "gn:name":"Hazelberg",
    "gn:population":0,
    "gn:timezone":"Europe/Amsterdam",
    "iso:country":"NL",
    "wof:name":"Hazelberg",
    "wof:placetype":"locality"
},
  "geometry": {"coordinates":[5.53889,51.64],"type":"Point"}
}