{
  "type": "Feature",
  "properties": {
    "gn:admin1_code":"4.0",
    "gn:admin2_code":"0047",
    "gn:asciiname":"Numero Dertien",
    "gn:cc2":"NL",
    "gn:country_code":"NL",
    "gn:dem":2,
    "gn:feature_class":"P",
    "gn:feature_code":"PPL",
    "gn:name":"Numero Dertien",
    "gn:population":0,
    "gn:timezone":"Europe/Amsterdam",
    "iso:country":"NL",
    "name:und_x_variant":[
        "Nummerderlien",
        "Nummer Dertien"
    ],
    "wof:name":"Numero Dertien",
    "wof:placetype":"locality"
},
  "geometry": {"coordinates":[6.91944,53.05],"type":"Point"}
}