{
  "type": "Feature",
  "properties": {
    "gn:admin1_code":"4.0",
    "gn:admin2_code":"1651.0",
    "gn:asciiname":"Bethlehem",
    "gn:country_code":"NL",
    "gn:dem":1,
    "gn:feature_class":"P",
    "gn:feature_code":"PPL",
    "gn:name":"Bethlehem",
    "gn:population":0,
    "gn:timezone":"Europe/Amsterdam",
    "iso:country":"NL",
    "wof:name":"Bethlehem",
    "wof:placetype":"locality"
},
  "geometry": {"coordinates":[6.60972,53.38333000000001],"type":"Point"}
}