{
  "type": "Feature",
  "properties": {
    "gn:admin1_code":"4.0",
    "gn:admin2_code":"1651.0",
    "gn:asciiname":"Bethlehem",
    "gn:country_code":"NL",
    "gn:dem":1,
    "gn:feature_class":"P",
    "gn:feature_code":"PPL",
    "gn:name":"Bethlehem",
    "gn:population":0,
    "gn:timezone":"Europe/Amsterdam",
    "iso:country":"NL",
    "name:afr_x_preferred":[
        "Bethlehem"
    ],
    "name:ben_x_preferred":[
        "\u09ac\u09c7\u09a5\u09b2\u09c7\u09b9\u09c7\u09ae"
    ],
    "name:ell_x_preferred":[
        "\u0392\u03b7\u03b8\u03bb\u03b5\u03ad\u03bc"
    ],
    "name:fas_x_preferred":[
        "\u0628\u06cc\u062a \u0644\u062d\u0645"
    ],
    "name:fry_x_preferred":[
        "Bethlehem"
    ],
    "name:heb_x_preferred":[
        "\u05d1\u05d9\u05ea \u05dc\u05d7\u05dd"
    ],
    "name:hin_x_preferred":[
        "\u092c\u0947\u0925\u0932\u0939\u092e"
    ],
    "name:hun_x_preferred":[
        "Bethlehem"
    ],
    "name:ind_x_preferred":[
        "Bethlehem"
    ],
    "name:kor_x_preferred":[
        "\ubca0\ub4e4\ub808\ud5f4"
    ],
    "name:nld_x_preferred":[
        "Bethlehem"
    ],
    "name:spa_x_preferred":[
        "Bethlehem"
    ],
    "name:swe_x_preferred":[
        "Bethlehem"
    ],
    "name:tur_x_preferred":[
        "Bethlehem"
    ],
    "name:ukr_x_preferred":[
        "\u0411\u0435\u0442\u043b\u0435\u0445\u0435\u043c"
    ],
    "name:urd_x_preferred":[
        "\u0628\u06cc\u062a\u06be\u0644\u06cc\u06c1\u06cc\u0645"
    ],
    "name:vie_x_preferred":[
        "Bethlehem"
    ],
    "wof:name":"Bethlehem",
    "wof:placetype":"locality"
},
  "geometry": {"coordinates":[6.60972,53.38333],"type":"Point"}
}