{
  "type": "Feature",
  "properties": {
    "gn:admin1_code":"5.0",
    "gn:admin2_code":"1894",
    "gn:asciiname":"Tongerlo",
    "gn:cc2":"NL",
    "gn:country_code":"NL",
    "gn:dem":29,
    "gn:feature_class":"P",
    "gn:feature_code":"PPL",
    "gn:name":"Tongerlo",
    "gn:population":0,
    "gn:timezone":"Europe/Amsterdam",
    "iso:country":"NL",
    "name:und_x_variant":[
        "Tongerloo"
    ],
    "wof:name":"Tongerlo",
    "wof:placetype":"locality"
},
  "geometry": {"coordinates":[6.02361,51.37333],"type":"Point"}
}