{
  "type": "Feature",
  "properties": {
    "gn:admin1_code":"4.0",
    "gn:admin2_code":"1895.0",
    "gn:asciiname":"Bikkershorn",
    "gn:country_code":"NL",
    "gn:dem":0,
    "gn:feature_class":"P",
    "gn:feature_code":"PPL",
    "gn:name":"Bikkershorn",
    "gn:population":0,
    "gn:timezone":"Europe/Amsterdam",
    "iso:country":"NL",
    "wof:name":"Bikkershorn",
    "wof:placetype":"locality"
},
  "geometry": {"coordinates":[6.99444,53.1475],"type":"Point"}
}