{
  "type": "Feature",
  "properties": {
    "gn:admin1_code":"9.0",
    "gn:admin2_code":"307.0",
    "gn:asciiname":"Bieshaar",
    "gn:country_code":"NL",
    "gn:dem":2,
    "gn:feature_class":"P",
    "gn:feature_code":"PPL",
    "gn:name":"Bieshaar",
    "gn:population":0,
    "gn:timezone":"Europe/Amsterdam",
    "iso:country":"NL",
    "wof:name":"Bieshaar",
    "wof:placetype":"locality"
},
  "geometry": {"coordinates":[5.37399,52.18885],"type":"Point"}
}