{
  "type": "Feature",
  "properties": {
    "gn:admin1_code":"6.0",
    "gn:admin2_code":"840.0",
    "gn:asciiname":"De Posthoorn",
    "gn:cc2":"NL",
    "gn:country_code":"NL",
    "gn:dem":12,
    "gn:feature_class":"P",
    "gn:feature_code":"PPL",
    "gn:name":"De Posthoorn",
    "gn:population":0,
    "gn:timezone":"Europe/Amsterdam",
    "iso:country":"NL",
    "name:und_x_variant":[
        "Posthoorn"
    ],
    "wof:name":"De Posthoorn",
    "wof:placetype":"locality"
},
  "geometry": {"coordinates":[4.54167,51.52917],"type":"Point"}
}