{
  "type": "Feature",
  "properties": {
    "gn:admin1_code":"10.0",
    "gn:admin2_code":"1714",
    "gn:asciiname":"Nieuwland",
    "gn:country_code":"NL",
    "gn:dem":2,
    "gn:feature_class":"P",
    "gn:feature_code":"PPL",
    "gn:name":"Nieuwland",
    "gn:population":0,
    "gn:timezone":"Europe/Amsterdam",
    "iso:country":"NL",
    "name:ceb_x_preferred":[
        "Nieuwland"
    ],
    "name:deu_x_preferred":[
        "Nieuwland"
    ],
    "name:fra_x_preferred":[
        "Nieuwland"
    ],
    "name:nld_x_preferred":[
        "Nieuwland"
    ],
    "wof:name":"Nieuwland",
    "wof:placetype":"locality"
},
  "geometry": {"coordinates":[3.63333,51.33917],"type":"Point"}
}