{
  "type": "Feature",
  "properties": {
    "gn:admin1_code":"6.0",
    "gn:admin2_code":"826.0",
    "gn:asciiname":"Baarschot",
    "gn:country_code":"NL",
    "gn:dem":5,
    "gn:feature_class":"P",
    "gn:feature_code":"PPL",
    "gn:name":"Baarschot",
    "gn:population":0,
    "gn:timezone":"Europe/Amsterdam",
    "iso:country":"NL",
    "wof:name":"Baarschot",
    "wof:placetype":"locality"
},
  "geometry": {"coordinates":[4.84583,51.595],"type":"Point"}
}