{
  "type": "Feature",
  "properties": {
    "gn:admin1_code":"3.0",
    "gn:admin2_code":"0269",
    "gn:asciiname":"Kerkdorp",
    "gn:country_code":"NL",
    "gn:dem":-1,
    "gn:feature_class":"P",
    "gn:feature_code":"PPL",
    "gn:name":"Kerkdorp",
    "gn:population":0,
    "gn:timezone":"Europe/Amsterdam",
    "iso:country":"NL",
    "wof:name":"Kerkdorp",
    "wof:placetype":"locality"
},
  "geometry": {"coordinates":[5.89167,52.48833000000001],"type":"Point"}
}