{
  "type": "Feature",
  "properties": {
    "gn:admin1_code":"6.0",
    "gn:admin2_code":"788.0",
    "gn:asciiname":"t Winkel",
    "gn:country_code":"NL",
    "gn:dem":8,
    "gn:feature_class":"P",
    "gn:feature_code":"PPL",
    "gn:name":"t Winkel",
    "gn:population":0,
    "gn:timezone":"Europe/Amsterdam",
    "iso:country":"NL",
    "wof:name":"t Winkel",
    "wof:placetype":"locality"
},
  "geometry": {"coordinates":[5.18194,51.61917],"type":"Point"}
}