{
  "type": "Feature",
  "properties": {
    "gn:admin1_code":"6.0",
    "gn:admin2_code":"1723",
    "gn:asciiname":"Hondseind",
    "gn:country_code":"NL",
    "gn:dem":19,
    "gn:feature_class":"P",
    "gn:feature_code":"PPL",
    "gn:name":"Hondseind",
    "gn:population":0,
    "gn:timezone":"Europe/Amsterdam",
    "iso:country":"NL",
    "wof:name":"Hondseind",
    "wof:placetype":"locality"
},
  "geometry": {"coordinates":[4.87681,51.45813],"type":"Point"}
}