{
  "type": "Feature",
  "properties": {
    "gn:admin1_code":"1.0",
    "gn:admin2_code":"1690.0",
    "gn:asciiname":"Bultinge",
    "gn:country_code":"NL",
    "gn:dem":12,
    "gn:feature_class":"P",
    "gn:feature_code":"PPL",
    "gn:name":"Bultinge",
    "gn:population":0,
    "gn:timezone":"Europe/Amsterdam",
    "iso:country":"NL",
    "wof:name":"Bultinge",
    "wof:placetype":"locality"
},
  "geometry": {"coordinates":[6.44167,52.775],"type":"Point"}
}