{
  "type": "Feature",
  "properties": {
    "gn:admin1_code":"15.0",
    "gn:admin2_code":"177.0",
    "gn:asciiname":"Boetele",
    "gn:country_code":"NL",
    "gn:dem":7,
    "gn:feature_class":"P",
    "gn:feature_code":"PPL",
    "gn:name":"Boetele",
    "gn:population":0,
    "gn:timezone":"Europe/Amsterdam",
    "iso:country":"NL",
    "name:und_x_variant":[
        "Boeteloo",
        "Boetele"
    ],
    "wof:name":"Boetele",
    "wof:placetype":"locality"
},
  "geometry": {"coordinates":[6.30531,52.37244000000001],"type":"Point"}
}