{
  "type": "Feature",
  "properties": {
    "gn:admin1_code":"11.0",
    "gn:admin2_code":"1930",
    "gn:asciiname":"Tweede Vlotbrug",
    "gn:cc2":"NL",
    "gn:country_code":"NL",
    "gn:dem":-2,
    "gn:feature_class":"P",
    "gn:feature_code":"PPL",
    "gn:name":"Tweede Vlotbrug",
    "gn:population":0,
    "gn:timezone":"Europe/Amsterdam",
    "iso:country":"NL",
    "name:und_x_variant":[
        "2e Vlotbrug"
    ],
    "wof:name":"Tweede Vlotbrug",
    "wof:placetype":"locality"
},
  "geometry": {"coordinates":[4.19722,51.8525],"type":"Point"}
}