{
  "type": "Feature",
  "properties": {
    "gn:admin1_code":"10.0",
    "gn:admin2_code":"0654",
    "gn:asciiname":"Scheldeoord",
    "gn:country_code":"NL",
    "gn:dem":-1,
    "gn:feature_class":"P",
    "gn:feature_code":"PPL",
    "gn:name":"Scheldeoord",
    "gn:population":0,
    "gn:timezone":"Europe/Amsterdam",
    "iso:country":"NL",
    "wof:name":"Scheldeoord",
    "wof:placetype":"locality"
},
  "geometry": {"coordinates":[3.89871,51.39632],"type":"Point"}
}