{
  "type": "Feature",
  "properties": {
    "gn:admin1_code":"5.0",
    "gn:admin2_code":"1894.0",
    "gn:asciiname":"Hert",
    "gn:country_code":"NL",
    "gn:dem":20,
    "gn:feature_class":"P",
    "gn:feature_code":"PPL",
    "gn:name":"Hert",
    "gn:population":0,
    "gn:timezone":"Europe/Amsterdam",
    "iso:country":"NL",
    "wof:name":"Hert",
    "wof:placetype":"locality"
},
  "geometry": {"coordinates":[6.09444,51.34417],"type":"Point"}
}