{
  "type": "Feature",
  "properties": {
    "gn:admin1_code":"3.0",
    "gn:admin2_code":"0668",
    "gn:asciiname":"Oude Maasdijk",
    "gn:country_code":"NL",
    "gn:dem":4,
    "gn:feature_class":"P",
    "gn:feature_code":"PPL",
    "gn:name":"Oude Maasdijk",
    "gn:population":0,
    "gn:timezone":"Europe/Amsterdam",
    "iso:country":"NL",
    "wof:name":"Oude Maasdijk",
    "wof:placetype":"locality"
},
  "geometry": {"coordinates":[5.42361,51.83917],"type":"Point"}
}