{
  "type": "Feature",
  "properties": {
    "gn:admin1_code":"3.0",
    "gn:admin2_code":"0668",
    "gn:asciiname":"Velddijk",
    "gn:country_code":"NL",
    "gn:dem":6,
    "gn:feature_class":"P",
    "gn:feature_code":"PPL",
    "gn:name":"Velddijk",
    "gn:population":0,
    "gn:timezone":"Europe/Amsterdam",
    "iso:country":"NL",
    "wof:name":"Velddijk",
    "wof:placetype":"locality"
},
  "geometry": {"coordinates":[5.53333,51.83333],"type":"Point"}
}