{
  "type": "Feature",
  "properties": {
    "iso:country":"NL",
    "name:eng_x_preferred":[
        "Prinseneiland"
    ],
    "name:nld_x_preferred":[
        "Prinseneiland"
    ],
    "wof:name":"Prinseneiland",
    "wof:placetype":"microhood"
},
  "geometry": {"coordinates":[4.88718090860605,52.3856365624957],"type":"Point"}
}