{
  "type": "Feature",
  "properties": {
    "gn:admin1_code":"6.0",
    "gn:admin2_code":"0879",
    "gn:asciiname":"Luitert",
    "gn:country_code":"NL",
    "gn:dem":10,
    "gn:feature_class":"P",
    "gn:feature_code":"PPL",
    "gn:name":"Luitert",
    "gn:population":0,
    "gn:timezone":"Europe/Amsterdam",
    "iso:country":"NL",
    "wof:name":"Luitert",
    "wof:placetype":"locality"
},
  "geometry": {"coordinates":[4.65833,51.4875],"type":"Point"}
}