{
  "type": "Feature",
  "properties": {
    "iso:country":"NL",
    "name:eng_x_preferred":[
        "Lageweg"
    ],
    "name:nld_x_preferred":[
        "Lageweg"
    ],
    "wof:name":"Lageweg",
    "wof:placetype":"microhood"
},
  "geometry": {"coordinates":[6.6471514999999,53.25357449999993],"type":"Point"}
}