{
  "type": "Feature",
  "properties": {
    "gn:admin1_code":"5.0",
    "gn:admin2_code":"1641.0",
    "gn:asciiname":"Bilt",
    "gn:country_code":"NL",
    "gn:dem":26,
    "gn:feature_class":"P",
    "gn:feature_code":"PPL",
    "gn:name":"Bilt",
    "gn:population":0,
    "gn:timezone":"Europe/Amsterdam",
    "iso:country":"NL",
    "wof:name":"Bilt",
    "wof:placetype":"locality"
},
  "geometry": {"coordinates":[5.85417,51.1275],"type":"Point"}
}