{
  "type": "Feature",
  "properties": {
    "gn:admin1_code":"5.0",
    "gn:admin2_code":"1641.0",
    "gn:asciiname":"Bilt",
    "gn:country_code":"NL",
    "gn:dem":26,
    "gn:feature_class":"P",
    "gn:feature_code":"PPL",
    "gn:name":"Bilt",
    "gn:population":0,
    "gn:timezone":"Europe/Amsterdam",
    "iso:country":"NL",
    "name:ara_x_preferred":[
        "\u0628\u064a\u0644\u062a"
    ],
    "name:fas_x_preferred":[
        "\u0628\u06cc\u0644\u062a"
    ],
    "wof:name":"Bilt",
    "wof:placetype":"locality"
},
  "geometry": {"coordinates":[5.85417,51.1275],"type":"Point"}
}