{
  "type": "Feature",
  "properties": {
    "gn:admin1_code":"6.0",
    "gn:admin2_code":"757.0",
    "gn:asciiname":"Heult",
    "gn:country_code":"NL",
    "gn:dem":11,
    "gn:feature_class":"P",
    "gn:feature_code":"PPL",
    "gn:name":"Heult",
    "gn:population":0,
    "gn:timezone":"Europe/Amsterdam",
    "iso:country":"NL",
    "wof:name":"Heult",
    "wof:placetype":"locality"
},
  "geometry": {"coordinates":[5.33194,51.61583],"type":"Point"}
}