{
  "type": "Feature",
  "properties": {
    "gn:admin1_code":"7.0",
    "gn:admin2_code":"441.0",
    "gn:asciiname":"Het Korfwater",
    "gn:country_code":"NL",
    "gn:dem":5,
    "gn:feature_class":"P",
    "gn:feature_code":"PPL",
    "gn:name":"Het Korfwater",
    "gn:population":0,
    "gn:timezone":"Europe/Amsterdam",
    "iso:country":"NL",
    "wof:name":"Het Korfwater",
    "wof:placetype":"locality"
},
  "geometry": {"coordinates":[4.66806,52.77333],"type":"Point"}
}