{
  "type": "Feature",
  "properties": {
    "iso:country":"NL",
    "name:eng_x_preferred":[
        "Tuindorp Buiksloterham"
    ],
    "name:nld_x_preferred":[
        "Tuindorp Buiksloterham"
    ],
    "wof:name":"Tuindorp Buiksloterham",
    "wof:placetype":"microhood"
},
  "geometry": {"coordinates":[4.91561415954385,52.39637395074348],"type":"Point"}
}