{
  "type": "Feature",
  "properties": {
    "gn:admin1_code":"5.0",
    "gn:admin2_code":"1640.0",
    "gn:asciiname":"Hollander",
    "gn:country_code":"NL",
    "gn:dem":30,
    "gn:feature_class":"P",
    "gn:feature_code":"PPL",
    "gn:name":"Hollander",
    "gn:population":0,
    "gn:timezone":"Europe/Amsterdam",
    "iso:country":"NL",
    "wof:name":"Hollander",
    "wof:placetype":"locality"
},
  "geometry": {"coordinates":[5.85417,51.285],"type":"Point"}
}