{
  "type": "Feature",
  "properties": {
    "gn:admin1_code":"15.0",
    "gn:admin2_code":"153.0",
    "gn:asciiname":"Espelo",
    "gn:cc2":"NL",
    "gn:country_code":"NL",
    "gn:dem":31,
    "gn:feature_class":"P",
    "gn:feature_code":"PPL",
    "gn:name":"Espelo",
    "gn:population":0,
    "gn:timezone":"Europe/Amsterdam",
    "iso:country":"NL",
    "name:und_x_variant":[
        "Espeloo",
        "Hof Espelo",
        "Espelo"
    ],
    "wof:name":"Espelo",
    "wof:placetype":"locality"
},
  "geometry": {"coordinates":[6.86667,52.25],"type":"Point"}
}