{
  "type": "Feature",
  "properties": {
    "gn:admin1_code":"6.0",
    "gn:admin2_code":"0758",
    "gn:asciiname":"Lijndonk",
    "gn:country_code":"NL",
    "gn:dem":6,
    "gn:feature_class":"P",
    "gn:feature_code":"PPL",
    "gn:name":"Lijndonk",
    "gn:population":0,
    "gn:timezone":"Europe/Amsterdam",
    "iso:country":"NL",
    "wof:name":"Lijndonk",
    "wof:placetype":"locality"
},
  "geometry": {"coordinates":[4.85833,51.57],"type":"Point"}
}