{
  "type": "Feature",
  "properties": {
    "gn:admin1_code":"6.0",
    "gn:admin2_code":"0870",
    "gn:asciiname":"Perenboom",
    "gn:cc2":"NL",
    "gn:country_code":"NL",
    "gn:dem":1,
    "gn:feature_class":"P",
    "gn:feature_code":"PPL",
    "gn:name":"Peerenboom",
    "gn:population":0,
    "gn:timezone":"Europe/Amsterdam",
    "iso:country":"NL",
    "name:und_x_variant":[
        "Pereboom"
    ],
    "wof:name":"Perenboom",
    "wof:placetype":"locality"
},
  "geometry": {"coordinates":[4.91389,51.7225],"type":"Point"}
}