{
  "type": "Feature",
  "properties": {
    "gn:admin1_code":"15.0",
    "gn:admin2_code":"1708",
    "gn:asciiname":"'t Klooster",
    "gn:cc2":"NL",
    "gn:country_code":"NL",
    "gn:dem":1,
    "gn:feature_class":"P",
    "gn:feature_code":"PPLL",
    "gn:name":"'t Klooster",
    "gn:population":0,
    "gn:timezone":"Europe/Amsterdam",
    "iso:country":"NL",
    "name:afr_x_preferred":[
        "\u2019t Klooster"
    ],
    "name:fra_x_preferred":[
        "'t Klooster"
    ],
    "name:nld_x_preferred":[
        "'t Klooster"
    ],
    "name:und_x_variant":[
        "Klooster"
    ],
    "wof:name":"'t Klooster",
    "wof:placetype":"locality"
},
  "geometry": {"coordinates":[6.08986,52.74928000000001],"type":"Point"}
}