{
  "type": "Feature",
  "properties": {
    "gn:admin1_code":"2.0",
    "gn:admin2_code":"86.0",
    "gn:asciiname":"Hemrikerverlaat",
    "gn:country_code":"NL",
    "gn:dem":2,
    "gn:feature_class":"P",
    "gn:feature_code":"PPL",
    "gn:name":"Hemrikerverlaat",
    "gn:population":0,
    "gn:timezone":"Europe/Amsterdam",
    "iso:country":"NL",
    "name:fry_x_preferred":[
        "Himrikerferlaat"
    ],
    "name:nld_x_preferred":[
        "Hemrikerverlaat"
    ],
    "wof:name":"Hemrikerverlaat",
    "wof:placetype":"locality"
},
  "geometry": {"coordinates":[6.14045,53.02199],"type":"Point"}
}