{
  "type": "Feature",
  "properties": {
    "gn:admin1_code":"2.0",
    "gn:admin2_code":"1900.0",
    "gn:asciiname":"Galamadammen",
    "gn:country_code":"NL",
    "gn:dem":0,
    "gn:feature_class":"P",
    "gn:feature_code":"PPL",
    "gn:name":"Galamadammen",
    "gn:population":0,
    "gn:timezone":"Europe/Amsterdam",
    "iso:country":"NL",
    "wof:name":"Galamadammen",
    "wof:placetype":"locality"
},
  "geometry": {"coordinates":[5.46398,52.89938000000001],"type":"Point"}
}