{
  "type": "Feature",
  "properties": {
    "gn:admin1_code":"3.0",
    "gn:admin2_code":"1705",
    "gn:asciiname":"Looveer",
    "gn:country_code":"NL",
    "gn:dem":15,
    "gn:feature_class":"P",
    "gn:feature_code":"PPL",
    "gn:name":"Looveer",
    "gn:population":0,
    "gn:timezone":"Europe/Amsterdam",
    "iso:country":"NL",
    "wof:name":"Looveer",
    "wof:placetype":"locality"
},
  "geometry": {"coordinates":[5.95833,51.93667],"type":"Point"}
}