{
  "type": "Feature",
  "properties": {
    "gn:admin1_code":"6.0",
    "gn:admin2_code":"1723",
    "gn:asciiname":"Sas",
    "gn:cc2":"NL",
    "gn:country_code":"NL",
    "gn:dem":22,
    "gn:feature_class":"P",
    "gn:feature_code":"PPL",
    "gn:name":"Het Sas",
    "gn:population":0,
    "gn:timezone":"Europe/Amsterdam",
    "iso:country":"NL",
    "name:und_x_variant":[
        "'t Sas"
    ],
    "wof:name":"Sas",
    "wof:placetype":"locality"
},
  "geometry": {"coordinates":[4.98472,51.46917],"type":"Point"}
}