{
  "type": "Feature",
  "properties": {
    "gn:admin1_code":"3.0",
    "gn:admin2_code":"197.0",
    "gn:asciiname":"Het Beggelder",
    "gn:country_code":"NL",
    "gn:dem":16,
    "gn:feature_class":"P",
    "gn:feature_code":"PPL",
    "gn:name":"Het Beggelder",
    "gn:population":0,
    "gn:timezone":"Europe/Amsterdam",
    "iso:country":"NL",
    "wof:name":"Het Beggelder",
    "wof:placetype":"locality"
},
  "geometry": {"coordinates":[6.47361,51.86333],"type":"Point"}
}