{
  "type": "Feature",
  "properties": {
    "gn:admin1_code":"7.0",
    "gn:admin2_code":"400.0",
    "gn:asciiname":"Friese Buurt",
    "gn:country_code":"NL",
    "gn:dem":1,
    "gn:feature_class":"P",
    "gn:feature_code":"PPL",
    "gn:name":"Friese Buurt",
    "gn:population":0,
    "gn:timezone":"Europe/Amsterdam",
    "iso:country":"NL",
    "wof:name":"Friese Buurt",
    "wof:placetype":"locality"
},
  "geometry": {"coordinates":[4.77361,52.92167],"type":"Point"}
}