{
  "type": "Feature",
  "properties": {
    "gn:admin1_code":"10.0",
    "gn:admin2_code":"0677",
    "gn:asciiname":"Keizerrijk",
    "gn:country_code":"NL",
    "gn:dem":1,
    "gn:feature_class":"P",
    "gn:feature_code":"PPL",
    "gn:name":"Keizerrijk",
    "gn:population":0,
    "gn:timezone":"Europe/Amsterdam",
    "iso:country":"NL",
    "wof:name":"Keizerrijk",
    "wof:placetype":"locality"
},
  "geometry": {"coordinates":[3.9625,51.3375],"type":"Point"}
}