{
  "type": "Feature",
  "properties": {
    "gn:admin1_code":"6.0",
    "gn:admin2_code":"0758",
    "gn:asciiname":"Vaareind",
    "gn:country_code":"NL",
    "gn:dem":3,
    "gn:feature_class":"P",
    "gn:feature_code":"PPL",
    "gn:name":"Vaareind",
    "gn:population":0,
    "gn:timezone":"Europe/Amsterdam",
    "iso:country":"NL",
    "wof:name":"Vaareind",
    "wof:placetype":"locality"
},
  "geometry": {"coordinates":[4.71667,51.58667],"type":"Point"}
}